Workbook
Name _Toc322014478: 'Пр 23 Справочник статей и КУУ'!#REF!
Name _Toc520384594: 'Пр 1 Планы '!$C$1
Name _Toc520384594: 'Пр 24 (иск. из экспл.)'!#REF!
Name _выбор_из_выпадающего_списка: #REF!
Name _выбор_из_выпадающего_списка: 'Пр 3.3 заявка Пл. 104.1-201.1'!$R$12
Name _выбор_из_выпадающего_списка: #REF!
Name _выбор_из_выпадающего_списка: #REF!
Name _выбор_из_выпадающего_списка: #REF!
Name _выбор_из_выпадающего_списка: #REF!
Name _выбор_из_выпадающего_списка: #REF!
Name _табл2: #NAME?
Name A48_табл2: #NAME?
Name aaaaa: #REF!
Name aaaaa: #REF!
Name aaaaa: #REF!
Name aaaaa: #REF!
Name aaaaa: #REF!
Name aaaaa: #REF!
Name aaaaa: #REF!
Name aq: #REF!
Name aq: #REF!
Name aq: #REF!
Name aq: #REF!
Name aq: #REF!
Name aq: #REF!
Name aq: #REF!
Name as: #REF!
Name as: #REF!
Name as: #REF!
Name as: #REF!
Name as: #REF!
Name as: #REF!
Name as: #REF!
Name asweer: #REF!
Name asweer: #REF!
Name asweer: #REF!
Name asweer: #REF!
Name asweer: #REF!
Name asweer: #REF!
Name asweer: #REF!
Name B2К: #REF!
Name B2К: #REF!
Name B2К: #REF!
Name B2К: #REF!
Name B2К: #REF!
Name B2К: #REF!
Name B2К: #REF!
Name B3К: #REF!
Name B3К: #REF!
Name B3К: #REF!
Name B3К: #REF!
Name B3К: #REF!
Name B3К: #REF!
Name B3К: #REF!
Name Button_1: "ГлобалВылеты_Лист1_Таблица"
Name Button_2: "ГлобалВылеты_Лист1_Таблица"
Name cghuyuibjh: #REF!
Name cghuyuibjh: #REF!
Name cghuyuibjh: #REF!
Name cghuyuibjh: #REF!

Sheet Пр 1 Планы 
C1: ПРИЛОЖЕНИЕ № 1
C2: К ПОРЯДКУ ТЕКУЩЕГО ЭКОНОМИЧЕСКОГО ПЛАНИРОВАНИЯ ПРОИЗВОДСТВЕННО-ХОЗЯЙСТВЕННОЙ ДЕЯТЕЛЬНОСТИ ФГУП «ГОСКОРПОРАЦИЯ ПО ОрВД»
A4: Перечень централизованных (ц) и децентрализованных (д) планов ФГУП «Госкорпорация по ОрВД» 1, 2,3 и 4 групп
A5: Группа планов | B5: № подгруппы планов | C5: Наименование плана | D5: Признак ц/д
A6: 1. Централизованные планы мероприятий по модернизации объектов ЕС ОрВД, реализуемых в рамках федеральных целевых программ и по отдельным постановлениям Правительства Российской Федерации
B7: 101.1 | C7: Государственная программа Российской Федерации "Космическая деятельность России» | D7: ц
B8: 104.1 | C8: Централизованный план мероприятий по реализации федерального проекта «Развитие инфраструктуры, обеспечение безопасности и формирование специализированной системы сертификации беспилотных авиационных систем» ФГУП «Госкорпорация по ОрВД» | D8: ц
B9: 105.1 | C9: Централизованный план по развитию опорной сети аэродромов объектов ЕС ОрВД ФГУП "Госкорпорация по ОрВД" | D9: ц
A10: 2. Планы развития и поддержания имущественного комплекса ФГУП «Госкорпорация по ОрВД» (непрограммная часть)
B11: 201.1 | C11: Централизованный план строительства, оснащения и модернизации объектов ЕС ОрВД | D11: ц
B12: 201.2 | C12: План развития и поддержания работоспособности объектов ЕС ОрВД филиала ______ФГУП «Госкорпорация по ОрВД» (часть 1) | D12: д
B13: 202.1 | C13: Централизованный план мероприятий по обеспечению информационной безопасности ФГУП «Госкорпорация по ОрВД» | D13: ц
B14: 202.3 | C14: План мероприятий по обеспечению транспортной безопасности в компетенции филиала_______ФГУП «Госкорпорация по ОрВД» | D14: д
B15: 203.1 | C15: Централизованный план мероприятий по поддержанию и развитию информационных технологий ФГУП «Госкорпорация по ОрВД» | D15: ц
B16: 203.2 | C16: План мероприятий по поддержанию и развитию информационных технологий в компетенции филиала_______ФГУП «Госкорпорация по ОрВД» | D16: д
B17: 205.1 | C17: Централизованный план ремонтно-восстановительных работ ФГУП «Госкорпорация по ОрВД» | D17: ц
B18: 205.2 | C18: План ремонтно-восстановительных работ в компетенции филиала______ФГУП «Госкорпорация по ОрВД» | D18: д
B19: 206.1 | C19: План научно-исследовательских и опытно-конструкторских работ ФГУП «Госкорпорация по ОрВД» | D19: ц
B20: 207.2 | C20: План развития и поддержания работоспособности объектов ЕС ОрВД филиала ______ФГУП «Госкорпорация по ОрВД» (часть 2) | D20: д
B21: 208.2 | C21: План мероприятий по обеспечению информационной безопасности в компетенции филиала_______ФГУП «Госкорпорация по ОрВД» | D21: д
A22: 3. Планы мероприятий для обеспечения производственно-хозяйственной деятельности ФГУП «Госкорпорация по ОрВД»
B23: 301.1 | C23: Централизованный план мероприятий по поисково-спасательному обеспечению в части дежурства поисково-спасательных воздушных судов и экипажей и выполнение дежурными экипажами тренировочных полетов ФГУП «Госкорпорация по ОрВД» | D23: ц
B24: 302.1
A25: 4. Планы мероприятий, инициированные ФГУП «Госкорпорация по ОрВД» в целях повышения квалификации, клиентоориентированности, мотивации персонала, представления Предприятия на международных и российских выставках, форумах и т.д.
B26: 401.1 | C26: Централизованный план профессиональной подготовки и переподготовки ФГУП «Госкорпорация по ОрВД» | D26: ц
B27: 402.1 | C27: Централизованный план мероприятий социальной программы ФГУП «Госкорпорация по ОрВД» | D27: ц
B28: 403.1 | C28: Централизованный план международных и корпоративных мероприятий ФГУП «Госкорпорация по ОрВД» | D28: ц

Sheet Пр 2а Структура планов  
K1: ПРИЛОЖЕНИЕ № 2 а
K2: К ПОРЯДКУ ТЕКУЩЕГО ПЛАНИРОВАНИЯ ПРОИЗВОДСТВЕННО-ХОЗЯЙСТВЕННОЙ ДЕЯТЕЛЬНОСТИ ФГУП «ГОСКОРПОРАЦИЯ ПО ОрВД»
D3: Структура планов ФГУП "Госкорпорация по ОрВД" 1 и 2 группы
A5: № пп | B5: Разделы, подразделы плана | C5: Объекты, средства, системы | D5: Централизованные планы, в том числе по группам | L5: Децентрализованные планы | M5: Наименование подразделений, ответственных за разделы, подразделы плана
D6: планы 1 группы | G6: планы 2 группы
D7: № 101.1. Государственная программа Российской Федерации "Космическая деятельность России» | E7: № 104.1. Централизованный план мероприятий по реализации федерального проекта «Развитие инфраструктуры, обеспечение безопасности и формирование специализированной системы сертификации беспилотных авиационных систем» ФГУП «Госкорпорация по ОрВД» на 20____ год | F7: № 105.1. Централизованный план по развитию опорной сети аэродромов объектов ЕС ОрВД ФГУП "Госкорпорация по ОрВД" на 20____ год | G7: № 201.1. Централизованный план строительства, оснащения и модернизации объектов ЕС ОрВД» на 20____год | H7: № 202.1. Централизованный план мероприятий по обеспечению информационной безопасности ФГУП «Госкорпорация по ОрВД» на 20____год | I7: № 203.1. Централизованный план мероприятий по развитию поддержанию информационных технологий ФГУП «Госкорпорация по ОрВД» на 20____ год | J7: № 205.1. Централизованный план ремонтно-восстановительных работ (РВР) ФГУП «Госкорпорация по ОрВД» на 20____ год | K7: № 206.1. План НИОКР ФГУП «Госкорпорация по ОрВД» на 20____ год | L7: Программа деятельности филиала ФГУП «Госкорпорация по ОрВД» на 20____ год
D9: капитальные | E9: капитальные | F9: капитальные | G9: капитальные | H9: текущие, капитальные | I9: текущие, капитальные | J9: текущие | K9: текущие | L9: текущие, капитальные
D10: 2070311 | E10: 2070314 | F10: 2070315 | G10: 2070322 | H10: 204321/2070323 | I10: 204951/2070324 | J10: 204961 | K10: 20430
A11: 1 | B11: 2 | C11: 3 | D11: 4 | E11: 7 | F11: 8 | G11: 9 | H11: 10 | I11: 11 | J11: 12 | K11: 13 | L11: 14 | M11: 15
A12: 01.0000 | B12: Организация воздушного движения (ОрВД)
A13: 01.0100 | B13: Мероприятия в отношении укрупненных центров, систем и средств ОрВД
A14: 01.0110 | B14: Мероприятия в отношении укрупненных центров ЕС ОрВД
A15: 01.0111 | B15: Мероприятия в отношении укрупненных центров ЕС ОрВД | C15: Укрупненные центры ЕС ОрВД (Cтроительство/реконструкция зданий, модернизация / замена АС ОрВД) | D15: Х | E15: Х | F15: Создание/Проектирование/Приобретение/Поставка/МиПНР/ПСИ/Оснащение/Модернизация/Реконструкция - основные этапы | G15: Создание/Проектирование/Приобретение/Поставка/МиПНР/ПСИ/Оснащение/Модернизация/Реконструкция - основные этапы | H15: Х | I15: Х | J15: Ремонтно-восстановительные работы, поддержание эксплуатационной готовности, выполнение работ по бюллетеням, закупка ЗИП, сервисное сопровождение | K15: Исследования, связанные с созданием, внедрением, применением (эксплуатацией) и модернизацией объектов, средств, систем | L15: Создание/Приобретение/Модернизация/Реконструкция - вспомогательные этапы стоимостью менее 10 млн руб. (ВПО 20701) | M15: Дирекция стратегического развития, эксплуатации и технической политики ГД Филиал
A16: 01.0120 | B16: Мероприятия в отношении комплексов средств автоматизации планирования и использования воздушного пространства
A17: 01.0121 | B17: Мероприятия в отношении комплексов средств автоматизации планирования использования воздушного пространства | C17: Комплексы средств автоматизации планирования использования воздушного пространства (КСА ПИВП ГЦ ЕС ОрВД, зональных, региональных и районных центров ЕС ОрВД, органов ОВД, таких как ГО ПВД, МДП, ВМДП, КДП, КДП МВЛ, КДП МВЛ РЗО, ЦПИ) - (АС ПИВП, КСА ПИВП ЗЦ/УЦ, КСА ПИВП РЦ, КСА ПВД, КСА ПИВП, КСА ПИВП ГО ПВД, КСА ПИВП МДП) | D17: Х | E17: Создание/Проектирование/Приобретение/Поставка/МиПНР/ПСИ/Оснащение/Модернизация/Реконструкция - основные этапы | F17: Создание/Проектирование/Приобретение/Поставка/МиПНР/ПСИ/Оснащение/Модернизация/Реконструкция - основные этапы | G17: Создание/Проектирование/Приобретение/Поставка/МиПНР/ПСИ/Оснащение/Модернизация/Реконструкция - основные этапы | H17: Х | I17: Х | J17: Ремонтно-восстановительные работы, поддержание эксплуатационной готовности, выполнение работ по бюллетеням, закупка ЗИП, сервисное сопровождение | K17: Исследования, связанные с созданием, внедрением, применением (эксплуатацией) и модернизацией объектов, средств, систем | L17: Создание/Приобретение/Модернизация/Реконструкция - вспомогательные этапы (ВПО 20701) | M17: Дирекция стратегического развития, эксплуатации и технической политики ГД Филиал
A18: 01.0130 | B18: Мероприятия в отношении средств и систем ОВД в районах аэродромов
A19: 01.0131 | B19: Мероприятия в отношении средств и систем ОВД в районах аэродромов | C19: Средства и системы ОВД в районах аэродромов (включая строительство КДП и оборудование для КДП, в том числе КТС УВД, КСА НКАД, системы видеонаблюдения для УВД (КСА УВН, АРМ УВД, АС УВД, РАС УВД, КСА УВД, НКАД, АО РЛИ) | D19: Х | E19: Х | F19: Создание (включая строительство КДП)/Приобретение/Поставка/МиПНР/ПСИ/Оснащение/Модернизация/Реконструкция - основные этапы | G19: Создание (включая строительство КДП)/Приобретение/Поставка/МиПНР/ПСИ/Оснащение/Модернизация/Реконструкция - основные этапы | H19: Х | I19: Х | J19: Ремонтно-восстановительные работы, поддержание эксплуатационной готовности, выполнение работ по бюллетеням, закупка ЗИП, сервисное сопровождение | K19: Исследования, связанные с созданием, внедрением, применением (эксплуатацией) и модернизацией объектов, средств, систем | L19: Создание/Приобретение/Модернизация/Реконструкция - вспомогательные этапы стоимостью менее 10 млн руб. (ВПО 20701) | M19: Дирекция стратегического развития, эксплуатации и технической политики ГД Филиал
A20: 01.0140 | B20: Мероприятия в отношении тренажерного оборудования для УЦ
A21: 01.0141 | B21: Мероприятия в отношении тренажерного оборудования для УЦ | C21: Тренажерное оборудование, оборудование учебных классов УЦ (АУК, КДТ) | D21: Х | E21: Х | F21: Х | G21: Создание/Проектирование/Приобретение/Поставка/МиПНР/Оснащение/Модернизация/Реконструкция - основные этапы | H21: Х | I21: Х | J21: Ремонтно-восстановительные работы, поддержание эксплуатационной готовности, выполнение работ по бюллетеням, закупка ЗИП, сервисное сопровождение | K21: Исследования, связанные с созданием, внедрением, применением (эксплуатацией) и модернизацией объектов, средств, систем | L21: Создание/Приобретение/Модернизация/Реконструкция - вспомогательные этапы (ВПО 20701) | M21: Дирекция стратегического развития, эксплуатации и технической политики ГД Филиал
A22: 01.0150 | B22: Мероприятия в отношении средств предоставления АНИ
A23: 01.0151 | B23: Мероприятия в отношении ПАК АНИ | C23: ПАК АНИ | D23: Х | E23: Х | F23: Х | G23: Создание/Проектирование/Приобретение/Поставка/МиПНР/Оснащение/Модернизация/Реконструкция - основные этапы | H23: Х | I23: Х | J23: Х | K23: Исследования, связанные с созданием, внедрением, применением (эксплуатацией) и модернизацией объектов, средств, систем | L23: Создание/Приобретение/Модернизация/Реконструкция - вспомогательные этапы (ВПО 20701)/Ремонтно-восстановительные работы (ВПО 204962) | M23: Дирекция стратегического развития, эксплуатации и технической политики ГД Филиал
A24: 01.0152 | B24: Мероприятия в отношении КАС СИДИМ | C24: КАС СИДИМ | D24: Х | E24: Х | F24: Х | G24: Создание/Проектирование/Приобретение/Поставка/МиПНР/Оснащение/Модернизация/Реконструкция - основные этапы | H24: Х | I24: Х | J24: Ремонтно-восстановительные работы, поддержание эксплуатационной готовности, выполнение работ по бюллетеням, закупка ЗИП, сервисное сопровождение | K24: Исследования, связанные с созданием, внедрением, применением (эксплуатацией) и модернизацией объектов, средств, систем | L24: Создание/Приобретение/Модернизация/Реконструкция - вспомогательные этапы (ВПО 20701)/Ремонтно-восстановительные работы (ВПО 204962) | M24: Дирекция стратегического развития, эксплуатации и технической политики ГД Филиал
A25: 01.0200 | B25: Технологические мероприятия, процессы ОрВД и ИВП
A26: 01.0210 | B26: Технологические мероприятия, процессы ОрВД и ИВП | C26: КИМ ОрВД | D26: Х | E26: Х | F26: Х | G26: Х | H26: Х | I26: Х | J26: Х | K26: Исследования, связанные с технологиями и процессами ОрВД и ИВП | L26: Х | M26: Дирекция стратегического развития, эксплуатации и технической политики ГД
A27: 01.0300 | B27: Мероприятия в отношении прочих средств организации воздушного движения
A28: 01.0310 | B28: Мероприятия в отношении прочих средств организации воздушного движения | C28: Метео, СЕВ, ПД, КПУ, АДИ, АПОИ, КСПИ, СТВ, ИСС | D28: Х | E28: Х | F28: Х | G28: Х | H28: Х | I28: Х | J28: Х | K28: Х | L28: Приобретение/создание/реконструкция/модернизация (ВПО 207012)/Ремонтно-восстановительные работы (ВПО 204962) | M28: Филиал
A29: 01.0311 | B29: Мероприятия в отношении оборудования автоматической передачи метеорологической и полетной информации | C29: Оборудование автоматической передачи метеорологической и полетной информации (АТИС/ВОЛМЕТ) | D29: Х | E29: Х | F29: Создание/Проектирование/Приобретение/Поставка/МиПНР/ПСИ/Оснащение/Модернизация/Реконструкция - основные этапы | G29: Создание/Проектирование/Приобретение/Поставка/МиПНР/ПСИ/Оснащение/Модернизация/Реконструкция - основные этапы | H29: Х | I29: Х | J29: Ремонтно-восстановительные работы, поддержание эксплуатационной готовности, выполнение работ по бюллетеням, закупка ЗИП, сервисное сопровождение | K29: Исследования, связанные с созданием, внедрением, применением (эксплуатацией) и модернизацией объектов, средств, систем | L29: Создание/Приобретение/Модернизация/Реконструкция - вспомогательные этапы (ВПО 20701)/Ремонтно-восстановительные работы (ВПО 204962) | M29: Дирекция стратегического развития, эксплуатации и технической политики ГД Филиал
A30: 02.0000 | B30: Наблюдение
A31: 02.0100 | B31: Мероприятия в отношении комплексов средств наблюдения
A32: 02.0110 | B32: Мероприятия в отношении средств наблюдения за полетами воздушных судов в районах аэродромов
A33: 02.0111 | B33: Мероприятия в отношении ОРЛ-А | C33: АРЛК, ОРЛ-А | D33: Х | E33: Х | F33: Создание/Проектирование/Строительство/Приобретение/Поставка/МиПНР/ПСИ/Оснащение/Модернизация/Реконструкция - основные этапы | G33: Создание/Проектирование/Строительство/Приобретение/Поставка/МиПНР/ПСИ/Оснащение/Модернизация/Реконструкция - основные этапы | H33: Х | I33: Х | J33: Ремонтно-восстановительные работы, поддержание эксплуатационной готовности, выполнение работ по бюллетеням, закупка ЗИП, сервисное сопровождение | K33: Исследования, связанные с созданием, внедрением, применением (эксплуатацией) и модернизацией объектов, средств, систем | L33: Создание/Приобретение/Модернизация/Реконструкция - вспомогательные этапы (ВПО 20701)/Ремонтно-восстановительные работы (ВПО 204962) | M33: Дирекция стратегического развития, эксплуатации и технической политики/Дирекция по инфраструктуре ГД/Филиал
A34: 02.0112 | B34: Мероприятия в отношении РЛС ОЛП | C34: РЛС ОЛП | D34: Х | E34: Х | F34: Создание/Проектирование/Строительство/Приобретение/Поставка/МиПНР/ПСИ/Оснащение/Модернизация/Реконструкция - основные этапы | G34: Создание/Проектирование/Строительство/Приобретение/Поставка/МиПНР/ПСИ/Оснащение/Модернизация/Реконструкция - основные этапы | H34: Х | I34: Х | J34: Ремонтно-восстановительные работы, поддержание эксплуатационной готовности, выполнение работ по бюллетеням, закупка ЗИП, сервисное сопровождение | K34: Исследования, связанные с созданием, внедрением, применением (эксплуатацией) и модернизацией объектов, средств, систем | L34: Создание/Приобретение/Модернизация/Реконструкция - вспомогательные этапы (ВПО 20701)/Ремонтно-восстановительные работы (ВПО 204962) | M34: Дирекция стратегического развития, эксплуатации и технической политики/Дирекция по инфраструктуре ГД/Филиал
A35: 02.0113 | B35: Мероприятия в отношении АРП | C35: АРП | D35: Х | E35: Х | F35: Создание/Проектирование/Строительство/Приобретение/Поставка/МиПНР/ПСИ/Оснащение/Модернизация/Реконструкция - основные этапы | G35: Создание/Проектирование/Строительство/Приобретение/Поставка/МиПНР/ПСИ/Оснащение/Модернизация/Реконструкция - основные этапы | H35: Х | I35: Х | J35: Ремонтно-восстановительные работы, поддержание эксплуатационной готовности, выполнение работ по бюллетеням, закупка ЗИП, сервисное сопровождение | K35: Исследования, связанные с созданием, внедрением, применением (эксплуатацией) и модернизацией объектов, средств, систем | L35: Создание/Приобретение/Модернизация/Реконструкция - вспомогательные этапы (ВПО 20701)/Ремонтно-восстановительные работы (ВПО 204962) | M35: Дирекция стратегического развития, эксплуатации и технической политики/Дирекция по инфраструктуре ГД/Филиал
A36: 02.0114 | B36: Мероприятия в отношении МПСН-А | C36: МПСН-А | D36: Х | E36: Х | F36: Создание/Проектирование/Приобретение/Поставка/МиПНР/ПСИ/Оснащение/Модернизация/Реконструкция - основные этапы | G36: Создание/Проектирование/Приобретение/Поставка/МиПНР/ПСИ/Оснащение/Модернизация/Реконструкция - основные этапы | H36: Х | I36: Х | J36: Ремонтно-восстановительные работы, поддержание эксплуатационной готовности, выполнение работ по бюллетеням, закупка ЗИП, сервисное сопровождение | K36: Исследования, связанные с созданием, внедрением, применением (эксплуатацией) и модернизацией объектов, средств, систем | L36: Создание/Приобретение/Модернизация/Реконструкция - вспомогательные этапы (ВПО 20701)/Ремонтно-восстановительные работы (ВПО 204962) | M36: Дирекция стратегического развития, эксплуатации и технической политики ГД Филиал
A37: 02.0120 | B37: Мероприятия в отношении средств наблюдения за полетами воздушных судов на воздушных трассах
A38: 02.0121 | B38: Мероприятия в отношении ВРЛ, ОРЛ-Т, ТРЛК | C38: ВРЛ, ОРЛ-Т | D38: Х | E38: Х | F38: Х | G38: Создание/Проектирование/Строительство/Приобретение/Поставка/МиПНР/ПСИ/Оснащение/Модернизация/Реконструкция - основные этапы | H38: Х | I38: Х | J38: Ремонтно-восстановительные работы, поддержание эксплуатационной готовности, выполнение работ по бюллетеням, закупка ЗИП, сервисное сопровождение | K38: Исследования, связанные с созданием, внедрением, применением (эксплуатацией) и модернизацией объектов, средств, систем | L38: Создание/Приобретение/Модернизация/Реконструкция - вспомогательные этапы (ВПО 20701)/Ремонтно-восстановительные работы (ВПО 204962) | M38: Дирекция стратегического развития, эксплуатации и технической политики/Дирекция по инфраструктуре ГД/Филиал
A39: 02.0122 | B39: Мероприятия в отношении АЗН-В | C39: АЗН-В, АЗН, СК АЗН-В | D39: Х | E39: Х | F39: Создание/Проектирование/Приобретение/Поставка/МиПНР/ПСИ/Оснащение/Модернизация/Реконструкция - основные этапы | G39: Создание/Проектирование/Приобретение/Поставка/МиПНР/ПСИ/Оснащение/Модернизация/Реконструкция - основные этапы | H39: Х | I39: Х | J39: Ремонтно-восстановительные работы, поддержание эксплуатационной готовности, выполнение работ по бюллетеням, закупка ЗИП, сервисное сопровождение | K39: Исследования, связанные с созданием, внедрением, применением (эксплуатацией) и модернизацией объектов, средств, систем | L39: Создание/Приобретение/Модернизация/Реконструкция - вспомогательные этапы (ВПО 20701)/Ремонтно-восстановительные работы (ВПО 204962) | M39: Дирекция стратегического развития, эксплуатации и технической политики ГД Филиал
A40: 02.0123 | B40: Мероприятия в отношении МПСН-Ш | C40: МПСН-Ш | D40: Х | E40: Создание/Проектирование/Приобретение/Поставка/МиПНР/ПСИ/Оснащение/Модернизация/Реконструкция - основные этапы | F40: Х | G40: Создание/Проектирование/Приобретение/Поставка/МиПНР/ПСИ/Оснащение/Модернизация/Реконструкция - основные этапы | H40: Х | I40: Х | J40: Ремонтно-восстановительные работы, поддержание эксплуатационной готовности, выполнение работ по бюллетеням, закупка ЗИП, сервисное сопровождение | K40: Исследования, связанные с созданием, внедрением, применением (эксплуатацией) и модернизацией объектов, средств, систем | L40: Создание/Приобретение/Модернизация/Реконструкция - вспомогательные этапы (ВПО 20701)/Ремонтно-восстановительные работы (ВПО 204962) | M40: Дирекция стратегического развития, эксплуатации и технической политики ГД Филиал
A41: 02.0124 | B41: Мероприятия в отношении HMU, AHMS | C41: HMU, AHMS | D41: X | E41: Х | F41: Х | G41: Создание/Проектирование/Приобретение/Поставка/МиПНР/ПСИ/Оснащение/Модернизация/Реконструкция - основные этапы | H41: X | I41: X | J41: Ремонтно-восстановительные работы, поддержание эксплуатационной готовности, выполнение работ по бюллетеням, закупка ЗИП, сервисное сопровождение | K41: Исследования, связанные с созданием, внедрением, применением (эксплуатацией) и модернизацией объектов, средств, систем | L41: Ремонтно-восстановительные работы (ВПО 204962) | M41: Дирекция стратегического развития, эксплуатации и технической политики ГД Филиал
A42: 02.0200 | B42: Мероприятия в отношении прочих средств наблюдения
A43: 02.0210 | B43: Мероприятия в отношении прочих средств наблюдения | C43: АЗН-К, АСК РЛС, НПС, НРЗ, НС СНН, ОВ, ПРЛ | D43: Х | E43: Х | F43: Х | G43: Х | H43: Х | I43: Х | J43: Х | K43: Х | L43: Приобретение/создание/реконструкция/модернизация (ВПО 207012)/Ремонтно-восстановительные работы (ВПО 204962) | M43: Филиал
A44: 03.0000 | B44: Навигация
A45: 03.0100 | B45: Мероприятия в отношении комплексов средств навигации и посадки
A46: 03.0110 | B46: Мероприятия в отношении средств ближней навигации
A47: 03.0111 | B47: Мероприятия в отношении средств навигации на базе (D)VOR/DME | C47: Средства навигации на базе (D)VOR/DME - РМА/РМД, РМА, РМД, РСБН | D47: Х | E47: Х | F47: Создание/Проектирование/Строительство/Приобретение/Поставка/МиПНР/ПСИ/Оснащение/Модернизация/Реконструкция - основные этапы | G47: Создание/Проектирование/Строительство/Приобретение/Поставка/МиПНР/ПСИ/Оснащение/Модернизация/Реконструкция - основные этапы | H47: Х | I47: Х | J47: Ремонтно-восстановительные работы, поддержание эксплуатационной готовности, выполнение работ по бюллетеням, закупка ЗИП, сервисное сопровождение | K47: Исследования, связанные с созданием, внедрением, применением (эксплуатацией) и модернизацией объектов, средств, систем | L47: Создание/Приобретение/Модернизация/Реконструкция - вспомогательные этапы (ВПО 20701)/Ремонтно-восстановительные работы (ВПО 204962) | M47: Дирекция стратегического развития, эксплуатации и технической политики/Дирекция по инфраструктуре ГД/Филиал
A48: 03.0120 | B48: Мероприятия в отношении приводных радиостанций
A49: 03.0121 | B49: Мероприятия в отношении приводных радиостанций | C49: ОПРС, МРМ, ПРС | D49: Х | E49: Х | F49: Создание/Проектирование/Строительство/Приобретение/Поставка/МиПНР/ПСИ/Оснащение/Модернизация/Реконструкция - основные этапы | G49: Создание/Проектирование/Строительство/Приобретение/Поставка/МиПНР/ПСИ/Оснащение/Модернизация/Реконструкция - основные этапы | H49: Х | I49: Х | J49: Ремонтно-восстановительные работы, поддержание эксплуатационной готовности, выполнение работ по бюллетеням, закупка ЗИП, сервисное сопровождение | K49: Х | L49: Создание/Приобретение/Модернизация/Реконструкция - вспомогательные этапы (ВПО 20701)/Ремонтно-восстановительные работы (ВПО 204962) | M49: Дирекция стратегического развития, эксплуатации и технической политики/Дирекция по инфраструктуре ГД/Филиал
A50: 03.0130 | B50: Мероприятия в отношении радиомаячных систем инструментального захода воздушного судна на посадку
A51: 03.0131 | B51: Мероприятия в отношении радиомаячных систем инструментального захода воздушного судна на посадку | C51: РМС, РМД-НП, ОСП | D51: Х | E51: Х | F51: Создание/Проектирование/Строительство/Приобретение/Поставка/МиПНР/ПСИ/Оснащение/Модернизация/Реконструкция - основные этапы | G51: Создание/Проектирование/Строительство/Приобретение/Поставка/МиПНР/ПСИ/Оснащение/Модернизация/Реконструкция - основные этапы | H51: Х | I51: Х | J51: Ремонтно-восстановительные работы, поддержание эксплуатационной готовности, выполнение работ по бюллетеням, закупка ЗИП, сервисное сопровождение | K51: Исследования, связанные с созданием, внедрением, применением (эксплуатацией) и модернизацией объектов, средств, систем | L51: Создание/Приобретение/Модернизация/Реконструкция - вспомогательные этапы (ВПО 20701)/Ремонтно-восстановительные работы (ВПО 204962) | M51: Дирекция стратегического развития, эксплуатации и технической политики/Дирекция по инфраструктуре ГД/Филиал
A52: 03.0140 | B52: Мероприятия в отношении средств спутниковой навигации/посадки
A53: 03.0141 | B53: Мероприятия в отношении средств спутниковой навигации/посадки | C53: Локальная контрольно-корректирующая станция (ЛККС) | D53: Х | E53: Создание/Проектирование/Приобретение/Поставка/МиПНР/ПСИ/Оснащение/Модернизация/Реконструкция - основные этапы | F53: Создание/Проектирование/Приобретение/Поставка/МиПНР/ПСИ/Оснащение/Модернизация/Реконструкция - основные этапы | G53: Создание/Проектирование/Приобретение/Поставка/МиПНР/ПСИ/Оснащение/Модернизация/Реконструкция - основные этапы | H53: Х | I53: Х | J53: Ремонтно-восстановительные работы, поддержание эксплуатационной готовности, выполнение работ по бюллетеням, закупка ЗИП, сервисное сопровождение | K53: Исследования, связанные с созданием, внедрением, применением (эксплуатацией) и модернизацией объектов, средств, систем | L53: Ремонтно-восстановительные работы (ВПО 204962) | M53: Дирекция стратегического развития, эксплуатации и технической политики ГД Филиал
A54: 03.0200 | B54: Мероприятия в отношении прочих средств навигации
A55: 03.0210 | B55: Мероприятия в отношении прочих средств навигации | C55: АДУ | D55: Х | E55: Х | F55: Х | G55: Х | H55: Х | I55: Х | J55: Х | K55: Х | L55: Создание/Приобретение/Модернизация/Реконструкция - все этапы (ВПО 207012)/ Ремонтно-восстановительные работы (ВПО 204962) | M55: Филиал
A56: 03.0300 | B56: Мероприятия по разработке схем маневрирования
A57: 03.0400 | B57: Создание средств наземной инфраструктуры в интересах воздушного транспорта
A58: 03.0410 | B58: Создание средств наземной инфраструктуры в интересах воздушного транспорта | C58: Массивы цифровой информации о местности и препятствиях (МЦИ) | D58: Выполнение геодезических работ по обеспечению навигационной аппаратуры потребителей ГЛОНАСС массивами цифровой информации о местности и препятствиях в районах аэродромов Российской Федерации на воздушных трассах Российской Федерации | E58: Х | F58: Х | G58: Х | H58: Х | I58: Х | J58: Х | K58: Создание средств наземной инфраструктуры в интересах воздушного транспорта | L58: Х | M58: Дирекция стратегического развития, эксплуатации и технической политики ГД
A59: 04.0000 | B59: Связь
A60: 04.0100 | B60: Мероприятия в отношении сети авиационной электросвязи и передачи данных
A61: 04.0110 | B61: Мероприятия в отношении средств и систем авиационной наземной фиксированной связи
A62: 04.0111 | B62: Мероприятия в отношении средств и систем авиационной наземной фиксированной связи | C62: ЦКС AFTN/AMHS, СКРС | D62: Х | E62: Х | F62: Создание/Проектирование/Приобретение/Поставка/МиПНР/ПСИ/Оснащение/Модернизация/Реконструкция - основные этапы | G62: Создание/Проектирование/Приобретение/Поставка/МиПНР/ПСИ/Оснащение/Модернизация/Реконструкция - основные этапы | H62: Х | I62: Х | J62: Ремонтно-восстановительные работы, поддержание эксплуатационной готовности, выполнение работ по бюллетеням, закупка ЗИП, сервисное сопровождение | K62: Исследования, связанные с созданием, внедрением, применением (эксплуатацией) и модернизацией объектов, средств, систем | L62: Создание/Приобретение/Модернизация/Реконструкция - вспомогательные этапы (ВПО 20701)/Ремонтно-восстановительные работы (ВПО 204962) | M62: Дирекция стратегического развития, эксплуатации и технической политики ГД Филиал
A63: 04.0121 | B63: Мероприятия в отношении АППЦ | C63: АППЦ | D63: Х | E63: Х | F63: Создание/Проектирование/Приобретение/Поставка/МиПНР/ПСИ/Оснащение/Модернизация/Реконструкция - основные этапы | G63: Создание/Проектирование/Приобретение/Поставка/МиПНР/ПСИ/Оснащение/Модернизация/Реконструкция - основные этапы | H63: Х | I63: Х | J63: Ремонтно-восстановительные работы, поддержание эксплуатационной готовности, выполнение работ по бюллетеням, закупка ЗИП, сервисное сопровождение | K63: Исследования, связанные с созданием, внедрением, применением (эксплуатацией) и модернизацией объектов, средств, систем | L63: Создание/Приобретение/Модернизация/Реконструкция - вспомогательные этапы (ВПО 20701)/Ремонтно-восстановительные работы (ВПО 204962) | M63: Дирекция стратегического развития, эксплуатации и технической политики ГД Филиал
A64: 04.0123 | B64: Мероприятия в отношении ретрансляторов, радиостанций, радиоприёмников и радиопередатчиков ОВЧ диапазона | C64: Радиоретрансляторы, радиостанции, радиоприёмники и радиопередатчики ОВЧ диапазона (АРТР, ПРМ ОВЧ, ПРД ОВЧ, Р/С ОВЧ) | D64: Х | E64: Создание/Приобретение/Модернизация/Реконструкция - основные этапы | F64: Создание/Проектирование/Приобретение/Поставка/МиПНР/ПСИ/Оснащение/Модернизация/Реконструкция - основные этапы | G64: Создание/Проектирование/Приобретение/Поставка/МиПНР/ПСИ/Оснащение/Модернизация/Реконструкция - основные этапы | H64: Х | I64: Х | J64: Ремонтно-восстановительные работы, поддержание эксплуатационной готовности, выполнение работ по бюллетеням, закупка ЗИП, сервисное сопровождение | K64: Исследования, связанные с созданием, внедрением, применением (эксплуатацией) и модернизацией объектов, средств, систем | L64: Создание/Приобретение/Модернизация/Реконструкция - вспомогательные этапы (ВПО 20701)/Ремонтно-восстановительные работы (ВПО 204962) | M64: Дирекция стратегического развития, эксплуатации и технической политики ГД Филиал
A65: 04.0130 | B65: Мероприятия в отношении средств и систем авиационной подвижной электросвязи ВЧ диапазона
A66: 04.0131 | B66: Мероприятия в отношении приемников, передатчиков и радиостанций ВЧ диапазона | C66: Приемники, передатчики и радиостанции ВЧ диапазона (ПРМ ВЧ, ПРД ВЧ, Р/С ВЧ) | D66: Х | E66: Х | F66: Создание/Проектирование/Приобретение/Поставка/МиПНР/ПСИ/Оснащение/Модернизация/Реконструкция - основные этапы | G66: Создание/Проектирование/Приобретение/Поставка/МиПНР/ПСИ/Оснащение/Модернизация/Реконструкция - основные этапы | H66: Х | I66: Х | J66: Ремонтно-восстановительные работы, поддержание эксплуатационной готовности, выполнение работ по бюллетеням, закупка ЗИП, сервисное сопровождение | K66: Исследования, связанные с созданием, внедрением, применением (эксплуатацией) и модернизацией объектов, средств, систем | L66: Создание/Приобретение/Модернизация/Реконструкция - вспомогательные этапы (ВПО 20701)/Ремонтно-восстановительные работы (ВПО 204962) | M66: Дирекция стратегического развития, эксплуатации и технической политики ГД Филиал
A67: 04.0132 | B67: Мероприятия в отношении антенн ВЧ диапазона | C67: АФУ ВЧ | D67: Х | E67: Х | F67: Создание/Проектирование/Приобретение/Поставка/МиПНР/ПСИ/Оснащение/Модернизация/Реконструкция - основные этапы | G67: Создание/Проектирование/Приобретение/Поставка/МиПНР/ПСИ/Оснащение/Модернизация/Реконструкция - основные этапы | H67: Х | I67: Х | J67: Ремонтно-восстановительные работы, поддержание эксплуатационной готовности, выполнение работ по бюллетеням, закупка ЗИП, сервисное сопровождение | K67: Исследования, связанные с созданием, внедрением, применением (эксплуатацией) и модернизацией объектов, средств, систем | L67: Создание/Приобретение/Модернизация/Реконструкция - вспомогательные этапы (ВПО 20701)/Ремонтно-восстановительные работы (ВПО 204962) | M67: Дирекция стратегического развития, эксплуатации и технической политики ГД Филиал
A68: 04.0133 | B68: Мероприятия в отношении элементов системы связи и передачи данных ВЧ диапазона для Аэронавигационной системы Российской Федерации | C68: Элементы системы связи и передачи данных ВЧ диапазона для Аэронавигационной системы Российской Федерации | D68: Х | E68: Х | F68: Создание/Проектирование/Приобретение/Поставка/МиПНР/ПСИ/Оснащение/Модернизация/Реконструкция - основные этапы | G68: Создание/Проектирование/Приобретение/Поставка/МиПНР/ПСИ/Оснащение/Модернизация/Реконструкция - основные этапы | H68: Х | I68: Х | J68: Ремонтно-восстановительные работы, поддержание эксплуатационной готовности, выполнение работ по бюллетеням, закупка ЗИП, сервисное сопровождение | K68: Исследования, связанные с созданием, внедрением, применением (эксплуатацией) и модернизацией объектов, средств, систем | L68: Создание/Приобретение/Модернизация/Реконструкция - вспомогательные этапы (ВПО 20701)/Ремонтно-восстановительные работы (ВПО 204962) | M68: Дирекция стратегического развития, эксплуатации и технической политики ГД Филиал
A69: 04.0140 | B69: Мероприятия в отношении средств и систем авиационной фиксированной спутниковой связи
A70: 04.0141 | B70: Мероприятия в отношении средств и систем авиационной фиксированной спутниковой связи | C70: Средства и системы авиационной фиксированной спутниковой связи (ЗССС) | D70: Х | E70: Х | F70: Создание/Проектирование/Приобретение/Поставка/МиПНР/ПСИ/Оснащение/Модернизация/Реконструкция - основные этапы | G70: Создание/Проектирование/Приобретение/Поставка/МиПНР/ПСИ/Оснащение/Модернизация/Реконструкция - основные этапы | H70: Х | I70: Х | J70: Ремонтно-восстановительные работы, поддержание эксплуатационной готовности, выполнение работ по бюллетеням, закупка ЗИП, сервисное сопровождение | K70: Исследования, связанные с созданием, внедрением, применением (эксплуатацией) и модернизацией объектов, средств, систем | L70: Создание/Приобретение/Модернизация/Реконструкция - вспомогательные этапы (ВПО 20701)/Ремонтно-восстановительные работы (ВПО 204962) | M70: Дирекция стратегического развития, эксплуатации и технической политики ГД Филиал
A71: 04.0200 | B71: Мероприятия в отношении прочих средств связи
A72: 04.0210 | B72: Мероприятия в отношении прочих средств связи | C72: Кабели связи, в т.ч. ВОЛС (Кабель), прочее оборудование связи (АРТР, АФУ, АИВА, АПД, АТРС, АТС, КОА, ПРМ СЧ, , РРС, Р/С ВПС, СИТВ, БШД, ТЛГ-А) | D72: Х | E72: Х | F72: Х | G72: Х | H72: Х | I72: Х | J72: Х | K72: Х | L72: Создание/Приобретение/Модернизация/Реконструкция - все этапы (ВПО 207012)/ Ремонтно-восстановительные работы (ВПО 204962) | M72: Филиал
A73: 05.0000 | B73: Техническое обеспечение проведения летных проверок
A74: 05.0100 | B74: Мероприятия в отношении технических средств оснащения ВС | C74: Технические средства оснащения ВС (ТС ВС) | D74: Х | E74: Х | F74: Х | G74: Основные этапы мероприятий капитального характера | H74: Х | I74: Х | J74: Ремонтно-восстановительные работы, поддержание эксплуатационной готовности, выполнение работ по бюллетеням, закупка ЗИП, сервисное сопровождение | K74: Х | L74: Вспомогательные этапы мероприятий капитального характера (ВПО 20701)/ Ремонтно-восстановительные работы (ВПО 204962) | M74: Дирекция стратегического развития, эксплуатации и технической политики ГД Филиал
A75: 05.0200 | B75: Мероприятия в отношении ВС | C75: Воздушные суда (ВС) | D75: Х | E75: Х | F75: Х | G75: Основные этапы мероприятий капитального характера | H75: Х | I75: Х | J75: Ремонтно-восстановительные работы, поддержание эксплуатационной готовности, выполнение работ по бюллетеням, закупка ЗИП, сервисное сопровождение | K75: Х | L75: Вспомогательные этапы мероприятий капитального характера (ВПО 20701)/ Ремонтно-восстановительные работы (ВПО 204962) | M75: Дирекция стратегического развития, эксплуатации и технической политики ГД Филиал
A76: 06.0000 | B76: Оснащение гражданских аэродромов РФ и аэродромов совместного базирования ССО
A77: 06.0100 | B77: Оснащение гражданских аэродромов РФ и аэродромов совместного базирования ССО | C77: Свето-сигнальное оборудование (ССО) | D77: Х | E77: Х | F77: Все мероприятия капитального характера | G77: Все мероприятия капитального характера | H77: Х | I77: Х | J77: Ремонтно-восстановительные работы, поддержание эксплуатационной готовности, выполнение работ по бюллетеням, закупка ЗИП, сервисное сопровождение | K77: Х | L77: Ремонтно-восстановительные работы (ВПО 204962) | M77: Дирекция стратегического развития, эксплуатации и технической политики ГД Филиал
A78: 07.0000 | B78: Здания и сооружения, инфраструктура объектов
A79: 07.0100 | B79: Мероприятия в отношении объектов РТОП, административных зданий и автостоянок | C79: Здание административное (ЗданиеАдм), объекты РТОП, автостоянки | D79: Х | E79: Х | F79: Создание/Приобретение/Модернизация/Реконструкция - основные этапы стоимостью свыше 10 млн руб. | G79: Создание/Приобретение/Модернизация/Реконструкция - основные этапы стоимостью свыше 10 млн руб. | H79: Х | I79: Х | J79: Ремонтно-восстановительные работы, поддержание эксплуатационной готовности, выполнение работ по бюллетеням, закупка ЗИП, сервисное сопровождение | K79: Х | L79: Создание/Приобретение/Модернизация/Реконструкция - вспомогательные этапы стоимостью менее 10 млн руб. (ВПО 20701)/Ремонтно-восстановительные работы (ВПО 204962) | M79: Дирекция стратегического развития, эксплуатации и технической политики, Филиал в части СМР. Дирекция по правовому обеспечению, закупочной деятельности, договорной работе и имущественным отношениям, Филиал в части приобретения.
A80: 07.0200 | B80: Мероприятия в отношении ангаров | C80: Ангар (Ангар) | D80: Х | E80: Х | F80: Х | G80: Х | H80: Х | I80: Х | J80: Х | K80: Х | L80: Создание/Приобретение/Модернизация/Реконструкция - все этапы (ВПО 207012)/ Ремонтно-восстановительные работы (ВПО 204962) | M80: Филиал
A81: 07.0300 | B81: Мероприятия в отношении гаражей | C81: Гараж (Гараж) | D81: Х | E81: Х | F81: Х | G81: Х | H81: Х | I81: Х | J81: Х | K81: Х | L81: Создание/Приобретение/Модернизация/Реконструкция - все этапы (ВПО 207012)/ Ремонтно-восстановительные работы (ВПО 204962) | M81: Филиал
A82: 07.0400 | B82: Мероприятия в отношении периметровых ограждений | C82: Периметровые ограждения (ОгрПер) | D82: Х | E82: Х | F82: Х | G82: Х | H82: Х | I82: Х | J82: Х | K82: Х | L82: Создание/Приобретение/Модернизация/Реконструкция - все этапы (ВПО 207012)/ Ремонтно-восстановительные работы (ВПО 204962) | M82: Филиал
A83: 07.0500 | B83: Мероприятия в отношении иных зданий и сооружений, объектов инфраструктуры | C83: Иные здания и сооружения, объекты инфраструктуры (Здание проч) | D83: Х | E83: Х | F83: Х | G83: Х | H83: Х | I83: Х | J83: Х | K83: Х | L83: Создание/Приобретение/Модернизация/Реконструкция - все этапы (ВПО 207012)/ Ремонтно-восстановительные работы (ВПО 204962) | M83: Филиал
A84: 08.0000 | B84: Мероприятий, реализуемые по отдельным решениям Правительства РФ
A85: 08.0100 | B85: Софинансирование объекта: "Строительство комплекса новой взлётно-посадочной полосы (ВПП-3) международного а/п Шереметьево, Московская область" | C85: ВПП | D85: Х | E85: Х | F85: Х | G85: Все мероприятия капитального характера | H85: Х | I85: Х | J85: Х | K85: Х | L85: Х | M85: Дирекция стратегического развития, эксплуатации и технической политики ГД Филиал
A86: 09.0000 | B86: Объекты промышленного и резервного энергоснабжения
A87: 09.0100 | B87: Мероприятия в отношении трансформаторных подстанций | C87: Трансформаторные подстанции (ТП) | D87: Х | E87: Х | F87: Создание/Приобретение/Модернизация/Реконструкция - основные этапы стоимостью свыше 5 млн руб. | G87: Создание/Приобретение/Модернизация/Реконструкция - основные этапы стоимостью свыше 5 млн руб. | H87: Х | I87: Х | J87: Ремонтно-восстановительные работы, поддержание эксплуатационной готовности, выполнение работ по бюллетеням, закупка ЗИП, сервисное сопровождение | K87: Х | L87: Создание/Приобретение/Модернизация/Реконструкция - вспомогательные этапы стоимостью менее 5 млн руб. (ВПО 20701)/Ремонтно-восстановительные работы (ВПО 204962) | M87: Дирекция стратегического развития, эксплуатации и технической политики ГД Филиал
A88: 09.0200 | B88: Мероприятия в отношении линий электроснабжения | C88: Линии энергоснабжения (ЛЭС) | D88: Х | E88: Х | F88: Создание/Приобретение/Модернизация/Реконструкция - основные этапы стоимостью свыше 5 млн руб. | G88: Создание/Приобретение/Модернизация/Реконструкция - основные этапы стоимостью свыше 5 млн руб. | H88: Х | I88: Х | J88: Ремонтно-восстановительные работы, поддержание эксплуатационной готовности, выполнение работ по бюллетеням, закупка ЗИП, сервисное сопровождение | K88: Х | L88: Создание/Приобретение/Модернизация/Реконструкция - вспомогательные этапы стоимостью менее 5 млн руб. (ВПО 20701)/Ремонтно-восстановительные работы (ВПО 204962) | M88: Дирекция стратегического развития, эксплуатации и технической политики ГД Филиал
A89: 09.0300 | B89: Мероприятия в отношении дизель-генераторов | C89: Дизель-электрические установки (ДЭУ) | D89: Х | E89: Х | F89: Х | G89: Х | H89: Х | I89: Х | J89: Х | K89: Х | L89: Все мероприятия капитального характера (ВПО 207012)/ Ремонтно-восстановительные работы (ВПО 204962) | M89: Филиал
A90: 09.0400 | B90: Мероприятия в отношении источников бесперебойного питания | C90: Источники (агрегаты) бесперебойного питания (ИБП) | D90: Х | E90: Х | F90: Х | G90: Х | H90: Х | I90: Х | J90: Х | K90: Х | L90: Все мероприятия капитального характера (ВПО 207012)/ Ремонтно-восстановительные работы (ВПО 204962) | M90: Филиал
A91: 10.0000 | B91: Объекты транспортной и информационной безопасности
A92: 10.0100 | B92: Обеспечение безопасности критической информационной инфраструктуры
A93: 10.0110 | B93: Аттестация объектов ЕС ОрВД на соответствие требованиям по защите информации | D93: Х | E93: Х | F93: Х | G93: Х | H93: Мероприятия стоимостью свыше 0,5 млн руб. (ВПО 204321) | I93: Х | J93: Х | K93: Х | L93: Мероприятия стоимостью менее 0,5 млн руб. (ВПО 204322) | M93: Центр кибербезопасности ГД Филиал
A94: 10.0120 | B94: Приобретение лицензий, техническая поддержка программного обеспечения, сопровождение средств и систем защиты информации в целях обеспечения информационной безопасности ЕС ОрВД | D94: Х | E94: Х | F94: Х | G94: Х | H94: Все мероприятия (ВПО 204321) | I94: Х | J94: Х | K94: Х | L94: Х | M94: Центр кибербезопасности ГД
A95: 10.0130 | B95: Капитальные расходы на обеспечение информационной безопасности ЕС ОрВД | C95: Средства защиты информации (СЗИ ЕС ОрВД) | D95: Х | E95: Х | F95: Х | G95: Х | H95: Мероприятия стоимостью свыше 0,5 млн руб. (ВПО 2070323) | I95: Х | J95: Х | K95: Х | L95: Мероприятия стоимостью менее 0,5 млн руб. (ВПО 20701) | M95: Центр кибербезопасности ГД Филиал
A96: 10.0140 | B96: Обеспечение информационной безопасности и безопасности инфраструктуры воздушного транспорта от противоправного применения БВС | D96: Х | E96: Все мероприятия | F96: Х | G96: Х | H96: Х | I96: Х | J96: Х | K96: Х | L96: Х | M96: Центр кибербезопасности ГД
A97: 10.0200 | B97: Обеспечение информационной безопасности корпоративной информационной системы
A98: 10.0210 | B98: Аттестация объектов информатизации на соответствие требованиям по защите информации | D98: Х | E98: Х | F98: Х | G98: Х | H98: Мероприятия стоимостью свыше 0,5 млн руб. (ВПО 204321) | I98: Х | J98: Х | K98: Х | L98: Мероприятия стоимостью менее 0,5 млн руб. (ВПО 204322) | M98: Центр кибербезопасности ГД Филиал
A99: 10.0220 | B99: Приобретение лицензий, техническая поддержка программного обеспечения, сопровождение средств и систем защиты информации в целях обеспечения информационной безопасности КИС | D99: Х | E99: Х | F99: Х | G99: Х | H99: Все мероприятия (ВПО 204321) | I99: Х | J99: Х | K99: Х | L99: Х | M99: Центр кибербезопасности ГД
A100: 10.0230 | B100: Капитальные расходы на обеспечение информационной безопасности КИС | C100: Средства защиты информации корпоративной информационной системы (СЗИ КИС) | D100: Х | E100: Х | F100: Х | G100: Х | H100: Мероприятия стоимостью свыше 0,5 млн руб. (ВПО 2070323) | I100: Х | J100: Х | K100: Х | L100: Мероприятия стоимостью менее 0,5 млн руб. (ВПО 20701) | M100: Центр кибербезопасности ГД Филиал
A101: 10.0300 | B101: Прочие мероприятия по обеспечению информационной безопасности
A102: 10.0310 | B102: Прочие мероприятия по обеспечению информационной безопасности | C102: Средства защиты информации информационной системы прочие (СЗИ прочие) | D102: Х | E102: Х | F102: Х | G102: Х | H102: Х | I102: Х | J102: Х | K102: Х | L102: Все мероприятия (ВПО 204322/207012/204962) | M102: Филиал
...

Sheet Пр 2б Структура планов
D1: ПРИЛОЖЕНИЕ № 2 б
D2: К ПОРЯДКУ ТЕКУЩЕГО ПЛАНИРОВАНИЯ ПРОИЗВОДСТВЕННО-ХОЗЯЙСТВЕННОЙ ДЕЯТЕЛЬНОСТИ ФГУП «ГОСКОРПОРАЦИЯ ПО ОрВД»
A4: Структура планов ФГУП "Госкорпорация по ОрВД" 3 группы
A5: № п/п | B5: Разделы, подразделы плана | C5: Централизованные планы 3 группы | F5: Децентрализованные планы ПДФ
C6: №301.1 Централизованный план мероприятий по поисково-спасательному обеспечению в части дежурства поисково-спасательных воздушных судов и экипажей и выполнение дежурными экипажами тренировочных полетов ФГУП «Госкорпорация по ОрВД» на 20____ год | D6: №302.1 | E6: №303.1 | F6: ВПО ПДФ
A7: 1. | B7: 2. | C7: 3. | D7: 4. | E7: 5. | F7: 6.
C8: текущие
C9: 20302
A10: 23.0000 | B10: Поисково-спасательное обеспечение в части дежурства поисково-спасательных воздушных судов и экипажей и выполнение дежурными экипажами тренировочных полетов
A11: 23.0100 | B11: Мероприятия по поисково-спасательному обеспечению в части дежурства поисково-спасательных воздушных судов и экипажей и выполнению дежурными экипажами тренировочных полетов | C11: Все мероприятия

Sheet Пр 2в Структура планов
D1: ПРИЛОЖЕНИЕ № 2 в
D2: К ПОРЯДКУ ТЕКУЩЕГО ПЛАНИРОВАНИЯ ПРОИЗВОДСТВЕННО-ХОЗЯЙСТВЕННОЙ ДЕЯТЕЛЬНОСТИ ФГУП «ГОСКОРПОРАЦИЯ ПО ОрВД»
A4: Структура планов ФГУП "Госкорпорация по ОрВД" 4 группы
A5: № п/п | B5: Разделы, подразделы плана | C5: Централизованные планы 4 группы | F5: Децентрализованные планы ПДФ
C6: 4.1. Централизованный план профессиональной подготовки | D6: 4.2. Централизованный план мероприятий социальной программы | E6: 4.3. Централизованный План международных и корпоративных мероприятий | F6: ВПО ПДФ
A7: 1. | B7: 2. | C7: 3. | D7: 4. | E7: 5. | F7: 6.
A8: 20.0000 | B8: Профессиональная подготовка и переподготовка
A9: 20.0100 | B9: Целевое обучение | C9: Все мероприятия | D9: Х | E9: Х
A10: 20.0200 | B10: Первоначальная подготовка (ускоренные курсы) | C10: Все мероприятия | D10: Х | E10: Х
A11: 20.0300 | B11: Расходы на организацию и проведение конкурсов профессионального мастерства | C11: Проведение финалов конкурсов, участие в международных конкурсах | D11: Х | E11: Х | F11: Проведение конкурсов профмастерства филиалов
A12: 20.0400 | B12: Расходы на обучение в Институте аэронавигации | C12: Все мероприятия | D12: Х | E12: Х | F12: Х
A13: 20.0600 | B13: Обучение работников, включенных в кадровый резерв Предприятия | C13: Все мероприятия | D13: Х | E13: Х | F13: Х
A14: 20.0700 | B14: Профессиональная подготовка и переподготовка | C14: Обучение работников предприятия | D14: Х | E14: Х | F14: Обучение работников филиала
A15: 20.0900 | B15: Прочее обучение | C15: Х | D15: Х | E15: Х | F15: Обучение работников филиала
A16: 21.0000 | B16: Социальная программа
A17: 21.0100 | B17: Жилищная программа Предприятия | C17: Х | D17: Все мероприятия | E17: Х | F17: Х
A18: 21.0200 | B18: Добровольное коллективное страхование от потери профессиональной трудоспособности, несчастных случаев и болезней | C18: Х | D18: Все мероприятия | E18: Х | F18: Х
A19: 21.0300 | B19: Санаторно-курортное лечение | C19: Х | D19: По централизованной программе | E19: Х | F19: Прочее
A20: 21.0400 | B20: Спортивные мероприятия | C20: Х | D20: Международные и корпоративные спортивные мероприятия | E20: Х | F20: Спортивные мероприятия филиала
A21: 21.0500 | B21: Негосударственное пенсионное обеспечение | C21: Х | D21: Все мероприятия | E21: Х | F21: Х
A22: 21.0600 | B22: Программа по привлечению и закреплению работников служб движения и служб ЭРТОС в отдельных структурных подразделениях филиалов ФГУП «Госкорпорация по ОрВД», расположенных в районах Дальнего Востока, Крайнего Севера и приравненных к ним местностях | C22: Х | D22: Все мероприятия | E22: Х | F22: Х
A23: 21.0700 | B23: Прочие расходы по коллективному договору | C23: Х | D23: Х | E23: Х | F23: Все мероприятия
A24: 21.0800 | B24: Социальные расходы по трудовым договорам и законодательству | C24: Х | D24: Х | E24: Х | F24: Все мероприятия
A25: 22.0000 | B25: Международные и корпоративные мероприятия
A26: 22.0100 | B26: Международные мероприятия | C26: Х | D26: Х | E26: Все мероприятия | F26: Х
A27: 22.0200 | B27: Корпоративные мероприятия | C27: Х | D27: Х | E27: Мероприятия по централизованной программе | F27: Мероприятия филиала
A28: 22.0300 | B28: Выставки | C28: Х | D28: Х | E28: Все мероприятия | F28: Х
A29: 22.0400 | B29: Участие в форумах, семинарах, конференциях, круглых столах и др. | C29: Х | D29: Х | E29: Мероприятия по централизованной программе | F29: Мероприятия филиала
A30: 22.0500 | B30: Членские взносы | C30: Х | D30: Х | E30: Все | F30: Х

Sheet Пр 3 заявка 1- 3
BB1: ПРИЛОЖЕНИЕ № 3
BB2: К ПОРЯДКУ ТЕКУЩЕГО ПЛАНИРОВАНИЯ ПРОИЗВОДСТВЕННО-ХОЗЯЙСТВЕННОЙ ДЕЯТЕЛЬНОСТИ ФГУП «ГОСКОРПОРАЦИЯ ПО ОрВД»
AE3: Форма заявки на мероприятия в планы 1 - 3 группы (кроме планов подгрупп 104.1, 105.1, 201.1)
AD5: ФГУП «Госкорпорация по ОрВД»
AB6: (включая корректировку № ________от _______)
AY7: тыс. руб.
A8: КИП | B8: НД | C8: КМ | D8: Год инициации | E8: Порядковый номер | F8: Код инпициатора мероприятия =1-ГК, =2-филиал | G8: Код Плана (Пр. 1) | H8: Территориальный код этапа мероприятия | I8: Код места установки | J8: Объект, средство, система | K8: Тип этапа (Пр. 27) | L8: Порядковый номер этапа мероприятия | M8: Номер раздела/подраздела (Пр 2а) | N8: Статья ВПО | O8: КУУ | P8: КВУ | Q8: Филиал | R8: Номер УИПа (справочник) | S8: Номер показателя ПДП (справочник) | T8: Наименование показателя Ипр (справочник) | U8: Номер поручения ФОИВ (справочник) | V8: Признак инновационности мероприятия (да/нет) | W8: Относится к Стратегии цифровой трансформации (да/нет) | X8: Статус мероприятия (закрыто/исполняется) | Y8: Наименование мероприятия | Z8: Наименование этапа | AA8: Место реализации | AB8: Наименование оборудования / ОС / НМА | AC8: Объект, средство, система | AD8: Общая плановая стоимость мероприятия/этапа | AE8: Срок начала реализации мероприятия/этапа (мм_гггг, мм-месяц, гггг-год) | AF8: Срок завершения реализации мероприятия/этапа (мм_гггг, мм-месяц, гггг-год) | AG8: Выполнено по состоянию на 01.01.____ | AH8: Оплачено по состоянию на 01.01.____ | AI8: Централизованное финансирование по состоянию на 01.01.____ | AJ8: Платежи текущего финансового года | AW8: Платежи последующих периодов | AZ8: Планируемая дата заключения договора (мм_гггг, мм - месяц, гггг - год | BA8: Реквизиты договора | BC8: Ответственный исполнитель в филиале | BD8: Ответственный исполнитель ГД | BE8: Передано на исполнение в филиал (дата и номер Распоряжения) | BF8: Обеспечение финансированием в планируемом году-1, опцион -0 | BG8: Обеспечение финансированием в планируемом году-1, опцион -1
AJ9: 1 кв-л по оплате | AM9: 2 кв-л по оплате | AP9: 3 кв-л по оплате | AS9: 4 кв-л по оплате | AV9: Итого | AW9: 1-й плановый год | AX9: 2-й плановый год | AY9: последующие годы | BA9: Номер / Планируемый ** | BB9: Дата /Планируемый**
D10: ОО | E10: YYYY | F10: К | G10: XXX.X | H10: FFFF | I10: BBB | J10: CCC | K10: GG | L10: HH | M10: DD.EEEE | AJ10: январь | AK10: февраль | AL10: март | AM10: апрель | AN10: май | AO10: июнь | AP10: июль | AQ10: август | AR10: сентябрь | AS10: октябрь | AT10: ноябрь | AU10: декабрь
A11: * | B11: * | C11: * | D11: * | E11: * | F11: * | G11: * | H11: * | I11: * | J11: * | K11: * | L11: * | M11: * | N11: * | O11: * | P11: * | Q11: * | R11: * | S11: * | T11: * | U11: * | V11: * | W11: * | X11: * | Y11: 1 | Z11: 2 | AA11: 3 | AB11: 4 | AC11: 5 | AD11: 6 | AE11: 7 | AF11: 8 | AG11: 9 | AH11: 10 | AI11: 11 | AJ11: 12 | AK11: 13 | AL11: 14 | AM11: 15 | AN11: 16 | AO11: 17 | AP11: 18 | AQ11: 19 | AR11: 20 | AS11: 21 | AT11: 22 | AU11: 23 | AV11: 24 | AW11: 25 | AX11: 26 | AY11: 27 | AZ11: 28 | BA11: 29 | BB11: 30 | BC11: 31 | BD11: 32 | BE11: 33 | BF11: 34 | BG11: 35
R12: Наблюдение (УИП 2) | S12: выбор из выпадающего списка | T12: выбор из выпадающего списка | U12: выбор из выпадающего списка
R13: Наблюдение (УИП 2) | S13: Раздел | T13: Раздел | U13: Раздел | V13: Раздел
R14: Наблюдение (УИП 2) | S14: выбор из выпадающего списка | T14: выбор из выпадающего списка | U14: выбор из выпадающего списка
R15: Хоз деятельность (УИП 6 Прочее) | S15: Подраздел | T15: Подраздел | U15: Подраздел | V15: Подраздел
S16: выбор из выпадающего списка | T16: выбор из выпадающего списка | U16: выбор из выпадающего списка
S17: выбор из выпадающего списка | T17: выбор из выпадающего списка | U17: выбор из выпадающего списка
S18: выбор из выпадающего списка | T18: выбор из выпадающего списка | U18: выбор из выпадающего списка
A19: Примечание:
A20: Колонки (1)-(35) для печатной формы плана
A21: Колонки (1)-(35),(*) - для электронной формы плана
A22: В случае проставления признака "да" в колонке "Относится к Стратегии цифровой трансформации (да/нет)" заполнятся приложение к Приложению № 3
Z23: ОН - мероприятия общего назначения (АНО), ПД - мероприятия по прочим видам деятельности.

Sheet Приложение к Пр 3 заявка 1-3
Y1: ПРИЛОЖЕНИЕ К ПРИЛОЖЕНИЮ № 3
Y2: К ПОРЯДКУ ТЕКУЩЕГО ПЛАНИРОВАНИЯ ПРОИЗВОДСТВЕННО-ХОЗЯЙСТВЕННОЙ ДЕЯТЕЛЬНОСТИ ФГУП «ГОСКОРПОРАЦИЯ ПО ОрВД»
A3: Приложение к форме заявки на мероприятия в планы 1 - 3 группы (кроме планов подгрупп 104.1, 105.1, 201.1) *
AI4: тыс. рублей
A5: № п/п | B5: КМ | C5: № инициативы СЦТ | D5: Код мероприятия | E5: Наименование мероприятия | F5: Номер договора и дата/планируемый | G5: Стоимость мероприятия (этапа) планируемая | H5: Лимит финансирования на ____ год, в т.ч. | I5: Текущий год | O5: Платежи последующих периодов
O6: 1-й плановый год | V6: 2-й плановый год | AC6: последующие годы
I7: Ключевые показатели эффективности (КПЭ) цифровой трансформации** | O7: Итого | P7: Ключевые показатели эффективности (КПЭ) цифровой трансформации** | V7: Итого | W7: Ключевые показатели эффективности (КПЭ) цифровой трансформации** | AC7: Итого | AD7: Ключевые показатели эффективности (КПЭ) цифровой трансформации**
I8: КПЭ 17 | J8: КПЭ 23 | K8: КПЭ 19 | L8: КПЭ 26 | M8: КПЭ 20 | N8: КПЭ 22 | P8: КПЭ 17 | Q8: КПЭ 23 | R8: КПЭ 19 | S8: КПЭ 26 | T8: КПЭ 20 | U8: КПЭ 22 | W8: КПЭ 17 | X8: КПЭ 23 | Y8: КПЭ 19 | Z8: КПЭ 26 | AA8: КПЭ 20 | AB8: КПЭ 22 | AD8: КПЭ 17 | AE8: КПЭ 23 | AF8: КПЭ 19 | AG8: КПЭ 26 | AH8: КПЭ 20 | AI8: КПЭ 22
A9: 1 | C9: 2 | D9: 3 | E9: 4 | F9: 5 | G9: 6 | H9: 7 | I9: 8 | J9: 9 | K9: 11 | L9: 12 | M9: 13 | N9: 14 | O9: 15 | P9: 16 | Q9: 17 | R9: 19 | S9: 20 | T9: 21 | U9: 22 | V9: 23 | W9: 24 | X9: 25 | Y9: 27 | Z9: 28 | AA9: 29 | AB9: 30 | AC9: 31 | AD9: 32 | AE9: 33 | AF9: 35 | AG9: 36 | AH9: 37 | AI9: 38
A10: 1 | C10: 1 | E10: Мероприятие 1 | F10: № ___ от _____ | G10: =H10+O10+V10+AC10 -> 500000 | H10: =SUM(I10:N10) -> 100000 | I10: =SUM(I11:I15) -> 30000 | J10: 20000 | K10: =SUM(K11:K15) -> 30000 | L10: =SUM(L11:L15) -> 20000 | M10: =SUM(M11:M15) -> 0 | N10: =SUM(N11:N15) -> 0 | O10: =SUM(P10:U10) -> 100000 | P10: =SUM(P11:P15) -> 30000 | Q10: =SUM(Q11:Q15) -> 20000 | R10: =SUM(R11:R15) -> 30000 | S10: =SUM(S11:S15) -> 20000 | T10: =SUM(T11:T15) -> 0 | U10: =SUM(U11:U15) -> 0 | V10: =SUM(W10:AB10) -> 100000 | W10: =SUM(W11:W15) -> 30000 | X10: =SUM(X11:X15) -> 20000 | Y10: =SUM(Y11:Y15) -> 30000 | Z10: =SUM(Z11:Z15) -> 20000 | AA10: =SUM(AA11:AA15) -> 0 | AB10: =SUM(AB11:AB15) -> 0 | AC10: =SUM(AD10:AI10) -> 200000 | AD10: =SUM(AD11:AD15) -> 0 | AE10: =SUM(AE11:AE15) -> 0 | AF10: =SUM(AF11:AF15) -> 100000 | AG10: =SUM(AG11:AG15) -> 100000 | AH10: =SUM(AH11:AH15) -> 0 | AI10: =SUM(AI11:AI15) -> 0
C11: 1 | E11: Код ОКПД2 | I11: 30000 | P11: 30000 | W11: 30000
C12: 1 | E12: Код ОКПД2 | J12: 20000 | Q12: 20000 | X12: 20000
C13: 1 | E13: Код ОКПД2 | K13: 20000 | R13: 30000 | AF13: 100000
C14: 1 | E14: Код ОКПД2 | K14: 10000 | Y14: 30000
C15: 1 | E15: Код ОКПД2 | L15: 20000 | S15: 20000 | Z15: 20000 | AG15: 100000
A16: 2 | C16: 3 | E16: Мероприятие 2 | F16: Планируемый | G16: =H16+O16+V16+AC16 -> 30000 | H16: =SUM(H17) -> 30000 | I16: =SUM(I17) -> 0 | K16: 0 | M16: 0 | N16: =SUM(N17) -> 30000 | O16: =SUM(P16:U16) -> 0 | P16: =SUM(P17) -> 0 | R16: =SUM(R17) -> 0 | T16: =SUM(T17) -> 0 | U16: =SUM(U17) -> 0 | V16: =W16+Y16+AA16+AB16 -> 0 | W16: =SUM(W17) -> 0 | Y16: =SUM(Y17) -> 0 | AA16: =SUM(AA17) -> 0 | AB16: =SUM(AB17) -> 0 | AC16: =SUM(AD16:AI16) -> 0 | AD16: =SUM(AD17) -> 0 | AF16: =SUM(AF17) -> 0 | AH16: =SUM(AH17) -> 0 | AI16: =SUM(AI17) -> 0
C17: 3 | E17: Код ОКПД2 | G17: =H17+O17+V17+AC17 -> 30000 | H17: =I17+K17+M17+N17 -> 30000 | I17: 0 | K17: 0 | M17: 0 | N17: 30000 | O17: =SUM(P17:U17) -> 0 | P17: 0 | R17: 0 | T17: 0 | U17: 0 | V17: 0 | W17: 0 | Y17: 0 | AA17: 0 | AB17: 0 | AC17: 0 | AD17: 0 | AF17: 0 | AH17: 0 | AI17: 0
A18: 3 | C18: 6 | E18: Мероприятие 3 | F18: Планируемый | G18: =H18+O18+V18+AC18 -> 200000 | H18: =I18+K18+M18+N18 -> 70000 | I18: =SUM(I19) -> 0 | K18: =SUM(K19) -> 0 | M18: =SUM(M19) -> 70000 | N18: =SUM(N19) -> 0 | O18: =P18+R18+T18+U18 -> 100000 | P18: =SUM(P19) -> 100000 | R18: =SUM(R19) -> 0 | T18: =SUM(T19) -> 0 | U18: =SUM(U19) -> 0 | V18: 30000 | W18: =SUM(W19) -> 0 | Y18: =SUM(Y19) -> 0 | AA18: =SUM(AA19) -> 0 | AB18: =SUM(AB19) -> 0 | AC18: =AD18+AF18+AH18+AI18 -> 0 | AD18: =SUM(AD19) -> 0 | AF18: =SUM(AF19) -> 0 | AH18: =SUM(AH19) -> 0 | AI18: =SUM(AI19) -> 0
C19: 6 | E19: Код ОКПД2 | G19: =H19+O19+V19+AC19 -> 170000 | H19: =I19+K19+M19+N19 -> 70000 | I19: 0 | K19: 0 | M19: 70000 | N19: 0 | O19: =P19+R19+T19+U19 -> 100000 | P19: 100000 | R19: 0 | T19: 0 | U19: 0 | V19: =W19+Y19+AA19+AB19 -> 0 | W19: 0 | Y19: 0 | AA19: 0 | AB19: 0 | AC19: =AD19+AF19+AH19+AI19 -> 0 | AD19: 0 | AF19: 0 | AH19: 0 | AI19: 0
A20: N
A22: * Приложение заполняется только в том случае , если мероприятие относится к Стратегии цифровой трансформации (СЦТ)
A23: ** Определяются в соответствии с общероссийским классификатором по видам экономической деятельности (ОКПД2).
A24: В гр.2 указывается № инициативы СЦТ в соответсвии с утвержденной СЦТ ФГУП «Госкорпорация по ОрВД» до 2030 года и действующей редакцией методических рекомендаций по цифровой трансформации государственных корпораций и компаний с государственным участием (приложение №3)
A25: Сумма КПЭ: по гр. 8-14 должна быть равна лимиту финансирования текущего года, отраженному в гр. 7; по гр. 16-22 должна быть равна лимиту 1-го планового года, отраженному в гр. 15; по гр. 24-30 должна быть равна лимиту 2-го планового года, отраженному в гр. 23; по гр. 32-38 должна быть равна лимиту последующих годов, отраженному в гр. 31;
A26: Гр. 6 равна сумме гр. 7, 15,23,31
A27: В гр. 8; гр. 16; гр. 24; гр.32 (КПЭ 17 -"Увеличение вложений в российские решения в сфере информационных технологий")- указывается объем расходов на российское ПО, включенное в Единый реестр российских программ для электронных вычислительных машин и баз данных или в Единый реестр программ для электронных вычислительных машин и баз данных государств - членов Евразийского экономического союза, и связанные с ним работы (услуги). В случае если ПО является свободно распространяемым, но сведения о таком программном обеспечении не включены в Единый реестр российского ПО, то такое ПО относится к иностранному ПО и заполняются гр. 9; гр. 17; гр. 25; гр.33 в соответствующем периоде;
A28: В гр. 9, гр.17, гр. 25, гр. 33 (КПЭ 23 " Увеличение расходов на информационные технологии") - указывается объем расходов на иностранное ПО и связанные с ним работы (услуги).
A29: В гр. 11; гр. 19; гр. 27; гр.35 (КПЭ 19 "Увеличение вложений в радиоэлектронную продукцию российского происхождения, в том числе в телекоммуникационное оборудование и программно-аппаратные комплексы"- указывается объем расходов государственной компании на радиоэлектронную продукцию российского происхождения, в том числе телекоммуникационное оборудование и программно-аппаратные комплексы. Под радиоэлектронной продукцией российского происхождения понимается радиоэлектронная продукция, сведения о которой включены в реестр российской промышленной продукции (согласно постановлению Правительства Российской Федерации от 17.07.2015 N 719). Также включаются расходы на радиоэлектронную продукцию, которая включена в евразийский реестр промышленных товаров государств - членов Евразийского экономического союза. В данные графы не включаются расходы на работы (услуги), связанные с радиоэлектронной продукцией. Указанные затраты отражаются в гр. 12,гр.20,гр.28, гр. 36 в соответствующем периоде.
A30: В гр. 12; гр. 20; гр. 28; гр.36 (КПЭ 26 "Увеличение расходов, направленных на закупку радиоэлектронной продукции, телекоммуникационного оборудования и программно-аппаратных комплексов, а также связанных с ней работ (услуг)") - указывается объем расходов государственной компании на радиоэлектронную продукцию иностранного производства, в том числе телекоммуникационное оборудование и программно-аппаратные комплексы, а также связанные с ней работы (услуги), а также работы (услуги) связанные с приобретением радиоэлектронной продукции российского производства.
A31: В гр. 13; гр. 21; гр. 29; гр.37 (КПЭ 20 "Объем затрат на исследования и разработки, направленных на создание и развитие передовых и критически важных для отрасли цифровых технологий и решений, в том числе новых производственных технологий, связанных с интенсивным применением информационно-коммуникационных технологий в рамках реализации инициатив (проектов) СЦТ") - указывается объем затрат на научные исследования и разработки (НИОКР), направленных на создание и развитие передовых и критически важных для отрасли цифровых технологий и решений, в том числе новых производственных технологий, связанных с интенсивным применением информационно-коммуникационных технологий.
A32: В гр. 13; гр. 21; гр. 29; гр.37 (КПЭ 22 "Объем расходов государственных компаний на реализацию инициатив (мероприятий), связанных с созданием, внедрением и применением технологий и решений в сфере искусственного интеллекта") - указываются расходы связанные с технологиями и решениями в сфере искусственного интеллекта.

Sheet Пр.3.2 заявка в Пл.НИОКР 
E1: ПРИЛОЖЕНИЕ № 3.2.
E2: К ПОРЯДКУ ТЕКУЩЕГО ПЛАНИРОВАНИЯ ПРОИЗВОДСТВЕННО-ХОЗЯЙСТВЕННОЙ ДЕЯТЕЛЬНОСТИ ФГУП «ГОСКОРПОРАЦИЯ ПО ОрВД»
A3: Заявка на включение мероприятия в План научно-исследовательских и опытно-конструкторских работ ФГУП "Госкорпорация по ОрВД" на 20___ год из Перечня тематик (Приложение к Плану НИОКР на ___ год)
A5: 1. Данные по работе в форму Плана НИОКР:
A7: 1.1. Наименование темы:
A9: 1.2. Наименование раздела, подраздела Плана НИОКР:
A11: 1.3. Структурное подразделение, ответственное за сопровождение работы, ФИО ответственного за сопровождение работы:
A13: 1.4. Период выполнения работы (сроки реализации мероприятия): | G13: год (годы)
A14: Срок начала реализации мероприятия | G14: месяц, год
A15: Срок завершения реализации мероприятия | G15: месяц, год
A17: 1.5. Результаты работы, этапа:
A19: 1.6. Объем финансирования:
B20: общий: | D20: тыс. руб.
B21: 20___ г.: | D21: тыс. руб.
B22: 20___ г.: | D22: тыс. руб.
B23: 20___ г.: | D23: тыс. руб.
A25: 2. Цель работы:
A27: 3. Краткое описание работы:
A29: 4. Ожидаемые результаты:
A31: 5. Этапность выполнения работ (указать количество этапов):
A33: № этапа | B33: Содержание работ по этапу | E33: Стоимость этапа (тыс. руб.) | G33: Период выполнения | I33: Отчетность по этапу
E34: (тыс. руб.) | F34: % от общей стоимости мероприятия | G34: Начало | H34: Окончание (Х + __ мес)
A38: Х -
A39: Условия оплаты (в соответствии с описанием предмета закупки):
A41: 6. Примечание:
A43: 7. Принадлежность к стратегии цифровой трансформации (да/нет)**
A45: 8. Планируемый срок заключения договора (месяц, год):
A47: 9. Приложение: | C47: 1. Проект технического задания, согласованный Росавиацией, на ___ л. 2. Служебная записка дирекции ЦОЗД о размере лимитной стоимости мероприятия для целей включения мероприятия в План НИОКР из Перечня тематик НИОКР, на ___ л.
A49: Директор по направлению деятельности:
A52: Руководитель структурного подразделения:
A55: Ответственный за сопровождение НИР от структурного подразделения:
A58: Дата:
B61: * | C61: Актуальные формы для заполнения сетевых графиков Корпоративном портале: Документы предприятия/Регламенты и стандарты/Общекорпоративные документы СМК/СТО-ГК-0001-017 Текущее экономическое планирование»
B62: ** В случае проставления признака "да" заполнятся приложение к Приложению № 3

Sheet Пр3.1.Заявка в Перечень тем
E1: ПРИЛОЖЕНИЕ № 3.1.
E2: К ПОРЯДКУ ТЕКУЩЕГО ПЛАНИРОВАНИЯ ПРОИЗВОДСТВЕННО-ХОЗЯЙСТВЕННОЙ ДЕЯТЕЛЬНОСТИ ФГУП «ГОСКОРПОРАЦИЯ ПО ОрВД»
A3: Заявка на включение новой работы в Перечень тематик НИОКР (Приложение к Плану научно-исследовательских и опытно-конструкторских работ ФГУП "Госкорпорация по ОрВД" на 20___ год)
A5: 1. Данные по работе в форму Плана НИОКР:
A7: 1.1. Наименование темы:
A9: 1.2. Наименование раздела, подраздела Плана НИОКР:
A11: 1.3. Структурное подразделение, ответственное за сопровождение работы, ФИО ответственного за сопровождение работы:
A13: 1.4. Период выполнения работы (сроки реализации мероприятия): | G13: год (годы)
A14: Срок начала реализации мероприятия | G14: месяц, год
A15: Срок завершения реализации мероприятия | G15: месяц, год
A17: 1.5. Результаты работы, этапа:
A19: 1.6. Объем финансирования:
B20: общий: | D20: тыс. руб.
B21: 20___ г.: | D21: тыс. руб.
B22: 20___ г.: | D22: тыс. руб.
B23: 20___ г.: | D23: тыс. руб.
A25: 2. Цель работы:
A27: 3. Краткое описание работы:
A29: 4. Ожидаемые результаты:
A31: 5. Этапность выполнения работ (указать количество этапов):
A33: № этапа | B33: Содержание работ по этапу | E33: Стоимость этапа | G33: Период выполнения | I33: Отчетность по этапу
E34: (тыс. руб.) | F34: % от общей стоимости мероприятия | G34: Начало (месяц, год) | H34: Окончание (Х + __ мес)
A38: Х -
A40: 6. Примечание:
A42: 7. Планируемый срок заключения договора (месяц, год):
A44: 8. Приложение: | C44: 1. Обоснование необходимости выполнения работы, на ___ л. 2. Обоснование ориентировочной лимитной стоимости мероприятия, согласованное дирекцией ЦОЗД, на ___ л.
A46: Директор по направлению деятельности:
A49: Руководитель структурного подразделения:
A52: Ответственный за сопровождение НИР от структурного подразделения:
A55: Дата:
A58: * | B58: Актуальные формы для заполнения сетевых графиков Корпоративном портале: Документы предприятия/Регламенты и стандарты/Общекорпоративные документы СМК/СТО-ГК-0001-017 Текущее экономическое планирование»

Sheet Пр 3.3 заявка Пл. 104.1-201.1
BI1: ПРИЛОЖЕНИЕ № 3.3
BI2: К ПОРЯДКУ ТЕКУЩЕГО ПЛАНИРОВАНИЯ ПРОИЗВОДСТВЕННО-ХОЗЯЙСТВЕННОЙ ДЕЯТЕЛЬНОСТИ ФГУП «ГОСКОРПОРАЦИЯ ПО ОрВД»
AD3: Форма заявки на мероприятия в централизованный план 1- 2 группы подгрупп 104.1, 105.1, 201.1
AH5: ФГУП «Госкорпорация по ОрВД»
AB6: (включая корректировку № ________от _______)
AY7: тыс. руб.
A8: НД | B8: КИП | C8: КМ | D8: Год инициации | E8: Порядковый номер | F8: Код инициатора мероприятия =1-ГК, =2-филиал | G8: Код Плана (Пр. 1) | H8: Территориальный код этапа мероприятия | I8: Код места установки | J8: Объект, средство, система | K8: Тип этапа (Пр. 27) | L8: Порядковый номер этапа мероприятия | M8: Номер раздела/подраздела (Пр 2а) | N8: Статья ВПО | O8: КУУ | P8: КВУ | Q8: Филиал | R8: Номер УИПа (справочник) | S8: Номер показателя ПДП (справочник) | T8: Наименование показателя Ипр (справочник) | U8: Номер поручения ФОИВ (справочник) | V8: Признак инновационности мероприятия (да/нет) | W8: Относится к Стратегии цифровой трансформации (да/нет)* | X8: Статус мероприятия (закрыто/исполняется) | Y8: Наименование мероприятия | Z8: Краткое наименование мероприятия | AA8: Место реализации | AB8: Наименование оборудования / ОС / НМА/Воздушного судна | AC8: Тип этапа / Вид работ | AD8: Срок начала реализации мероприятия/этапа (мм_гггг, мм-месяц, гггг-год) | AE8: Срок завершения реализации мероприятия/этапа (мм_гггг, мм-месяц, гггг-год) | AF8: Реквизиты договора | AH8: Общая плановая стоимость мероприятия/этапа | AI8: Финансирование по договору по состоянию на 01.01.___ | AJ8: Платежи текущего финансового года | AW8: Платежи последующих периодов | AZ8: Планируемая дата заключения договора (мм_гггг, мм - месяц, гггг - год | BA8: Дата выполнения обязательств по договору (мм_гггг ) | BB8: Ответственный исполнитель в филиале | BC8: Ответственный исполнитель ГД | BD8: Передано на исполнение в филиал (дата и номер Распоряжения) | BE8: Обеспечение финансированием в планируемом году-1, опцион -0 | BF8: Проект-аналог/новое (ранее не закупалось) | BG8: Критерии | BJ8: Информация по действующему оборудованию | BO8: Объемы финансирования
AF9: Номер / Планируемый ** | AG9: Дата /Планируемый** | AJ9: 1 кв-л по оплате | AM9: 2 кв-л по оплате | AP9: 3 кв-л по оплате | AS9: 4 кв-л по оплате | AV9: Итого | AW9: 1-й плановый год | AX9: 2-й плановый год | AY9: последующие годы | BG9: Наличие утвержденной ПСД или положительное заключение | BH9: Земля (Кадастровый номер; Номер и дата правоустанавливающие документа; Дата окончания срока предоставления) | BI9: Стадия оформления прав на землю (Если не оформлена) | BJ9: Дата ввода оборудования (дд.мм.гг.) | BK9: Назначенный ресурс (лет) | BL9: Фактический срок службы (лет) | BM9: Из них продление срока службы (лет) | BN9: Обоснование включения (с приложением Акта о техническом состоянии с указанием невозможности продления ресурса)
D10: ОО | E10: YYYY | F10: К | G10: XXX.X | H10: FFFF | I10: BBB | J10: CCC | K10: GG | L10: HH | M10: DD.EEEE | AJ10: январь | AK10: февраль | AL10: март | AM10: апрель | AN10: май | AO10: июнь | AP10: июль | AQ10: август | AR10: сентябрь | AS10: октябрь | AT10: ноябрь | AU10: декабрь | BO10: по состоянию на 01.01.20___ | BP10: 01.01.20__ | BQ10: 01.02.20__ | BR10: 01.03.20__ | BS10: 01.04.20__ | BT10: 01.05.20__ | BU10: 01.06.20__ | BV10: 01.07.20__ | BW10: 01.08.20__ | BX10: 01.09.20__ | BY10: 01.10.20__ | BZ10: 01.11.20__ | CA10: 01.12.20__ | CB10: ИТОГО 20__ | CC10: 202_ | CD10: 202_ | CE10: 202_ | CF10: 202_ | CG10: 202_ | CH10: 202_ | CI10: 203_
A11: 1 | B11: * | C11: * | D11: * | E11: * | F11: * | G11: * | H11: * | I11: * | J11: * | K11: * | L11: * | M11: * | N11: * | O11: * | P11: * | Q11: * | R11: * | S11: * | T11: * | U11: * | V11: * | W11: * | X11: * | Y11: 2 | Z11: * | AA11: 3 | AB11: 4 | AC11: 5 | AD11: 6 | AE11: 7 | AF11: 8 | AG11: 9 | AH11: 10 | AI11: 11 | AJ11: 12 | AK11: 13 | AL11: 14 | AM11: 15 | AN11: 16 | AO11: 17 | AP11: 18 | AQ11: 19 | AR11: 20 | AS11: 21 | AT11: 22 | AU11: 23 | AV11: 24 | AW11: 25 | AX11: 26 | AY11: 27 | AZ11: 28 | BA11: 29 | BB11: 30 | BC11: 31 | BD11: 32 | BE11: 33 | BF11: 34 | BG11: 35 | BH11: 36 | BI11: 37 | BJ11: 38 | BK11: 39 | BL11: 40 | BM11: 41 | BN11: 42 | BO11: * | BP11: * | BQ11: * | BR11: * | BS11: * | BT11: * | BU11: * | BV11: * | BW11: * | BX11: * | BY11: * | BZ11: * | CA11: * | CB11: * | CC11: * | CD11: * | CE11: * | CF11: * | CG11: * | CH11: * | CI11: *
R12: выбор из выпадающего списка | S12: КДП | T12: выбор из выпадающего списка | U12: 1
A13: 1. Организация воздушного движения (ОрВД) | C13: Раздел | R13: Наблюдение (УИП 2) | S13: Раздел | T13: Раздел | U13: Раздел | V13: Раздел
R14: Наблюдение (УИП 2) | S14: выбор из выпадающего списка | T14: выбор из выпадающего списка | U14: выбор из выпадающего списка
A15: 1.1.Модернизация укрупненных центров ЕС ОрВД (включая строительство/реконструкция) | C15: Подраздел | R15: Хоз деятельность (УИП 6 Прочее) | S15: Подраздел | T15: Подраздел | U15: Подраздел | V15: Подраздел
S16: выбор из выпадающего списка | T16: выбор из выпадающего списка | U16: выбор из выпадающего списка
S17: выбор из выпадающего списка | T17: выбор из выпадающего списка | U17: выбор из выпадающего списка
S18: выбор из выпадающего списка | T18: выбор из выпадающего списка | U18: выбор из выпадающего списка
S19: выбор из выпадающего списка | T19: выбор из выпадающего списка | U19: выбор из выпадающего списка
A21: Примечание:
A22: Колонки (1)-(42) для печатной формы заявки
A23: Колонки (1)-(42),(*) - для электронной формы заявки
A24: В случае проставления признака "да" в колонке "Относится к Стратегии цифровой трансформации (да/нет)" заполнятся приложение к Приложению № 3.3
AC25: ОН - мероприятия общего назначения (АНО), ПД - мероприятия по прочим видам деятельности.

Sheet Приложение к Пр 3.3 заявка
Y1: ПРИЛОЖЕНИЕ К ПРИЛОЖЕНИЮ № 3.3
Y2: К ПОРЯДКУ ТЕКУЩЕГО ПЛАНИРОВАНИЯ ПРОИЗВОДСТВЕННО-ХОЗЯЙСТВЕННОЙ ДЕЯТЕЛЬНОСТИ ФГУП «ГОСКОРПОРАЦИЯ ПО ОрВД»
A3: Приложение к форме заявки на мероприятия в централизованный план 1- 2 группы подгрупп 104.1, 105.1, 201.1*
AI4: тыс. рублей
A5: № п/п | B5: КМ | C5: № инициативы СЦТ | D5: Код мероприятия | E5: Наименование мероприятия | F5: Номер договора и дата/планируемый | G5: Стоимость мероприятия (этапа) планируемая | H5: Лимит финансирования на ____ год, в т.ч. | I5: Текущий год | O5: Платежи последующих периодов
O6: 1-й плановый год | V6: 2-й плановый год | AC6: последующие годы
I7: Ключевые показатели эффективности (КПЭ) цифровой трансформации** | O7: Итого | P7: Ключевые показатели эффективности (КПЭ) цифровой трансформации** | V7: Итого | W7: Ключевые показатели эффективности (КПЭ) цифровой трансформации** | AC7: Итого | AD7: Ключевые показатели эффективности (КПЭ) цифровой трансформации**
I8: КПЭ 17 | J8: КПЭ 23 | K8: КПЭ 19 | L8: КПЭ 26 | M8: КПЭ 20 | N8: КПЭ 22 | P8: КПЭ 17 | Q8: КПЭ 23 | R8: КПЭ 19 | S8: КПЭ 26 | T8: КПЭ 20 | U8: КПЭ 22 | W8: КПЭ 17 | X8: КПЭ 23 | Y8: КПЭ 19 | Z8: КПЭ 26 | AA8: КПЭ 20 | AB8: КПЭ 22 | AD8: КПЭ 17 | AE8: КПЭ 23 | AF8: КПЭ 19 | AG8: КПЭ 26 | AH8: КПЭ 20 | AI8: КПЭ 22
A9: 1 | C9: 2 | D9: 3 | E9: 4 | F9: 5 | G9: 6 | H9: 7 | I9: 8 | J9: 9 | K9: 11 | L9: 12 | M9: 13 | N9: 14 | O9: 15 | P9: 16 | Q9: 17 | R9: 19 | S9: 20 | T9: 21 | U9: 22 | V9: 23 | W9: 24 | X9: 25 | Y9: 27 | Z9: 28 | AA9: 29 | AB9: 30 | AC9: 31 | AD9: 32 | AE9: 33 | AF9: 35 | AG9: 36 | AH9: 37 | AI9: 38
A10: 1 | C10: 1 | E10: Мероприятие 1 | F10: № ___ от _____ | G10: =H10+O10+V10+AC10 -> 500000 | H10: =SUM(I10:N10) -> 100000 | I10: =SUM(I11:I15) -> 30000 | J10: 20000 | K10: =SUM(K11:K15) -> 30000 | L10: =SUM(L11:L15) -> 20000 | M10: =SUM(M11:M15) -> 0 | N10: =SUM(N11:N15) -> 0 | O10: =SUM(P10:U10) -> 100000 | P10: =SUM(P11:P15) -> 30000 | Q10: =SUM(Q11:Q15) -> 20000 | R10: =SUM(R11:R15) -> 30000 | S10: =SUM(S11:S15) -> 20000 | T10: =SUM(T11:T15) -> 0 | U10: =SUM(U11:U15) -> 0 | V10: =SUM(W10:AB10) -> 100000 | W10: =SUM(W11:W15) -> 30000 | X10: =SUM(X11:X15) -> 20000 | Y10: =SUM(Y11:Y15) -> 30000 | Z10: =SUM(Z11:Z15) -> 20000 | AA10: =SUM(AA11:AA15) -> 0 | AB10: =SUM(AB11:AB15) -> 0 | AC10: =SUM(AD10:AI10) -> 200000 | AD10: =SUM(AD11:AD15) -> 0 | AE10: =SUM(AE11:AE15) -> 0 | AF10: =SUM(AF11:AF15) -> 100000 | AG10: =SUM(AG11:AG15) -> 100000 | AH10: =SUM(AH11:AH15) -> 0 | AI10: =SUM(AI11:AI15) -> 0
C11: 1 | E11: Код ОКПД2 | I11: 30000 | P11: 30000 | W11: 30000
C12: 1 | E12: Код ОКПД2 | J12: 20000 | Q12: 20000 | X12: 20000
C13: 1 | E13: Код ОКПД2 | K13: 20000 | R13: 30000 | AF13: 100000
C14: 1 | E14: Код ОКПД2 | K14: 10000 | Y14: 30000
C15: 1 | E15: Код ОКПД2 | L15: 20000 | S15: 20000 | Z15: 20000 | AG15: 100000
A16: 2 | C16: 3 | E16: Мероприятие 2 | F16: Планируемый | G16: =H16+O16+V16+AC16 -> 30000 | H16: =SUM(H17) -> 30000 | I16: =SUM(I17) -> 0 | K16: 0 | M16: 0 | N16: =SUM(N17) -> 30000 | O16: =SUM(P16:U16) -> 0 | P16: =SUM(P17) -> 0 | R16: =SUM(R17) -> 0 | T16: =SUM(T17) -> 0 | U16: =SUM(U17) -> 0 | V16: =W16+Y16+AA16+AB16 -> 0 | W16: =SUM(W17) -> 0 | Y16: =SUM(Y17) -> 0 | AA16: =SUM(AA17) -> 0 | AB16: =SUM(AB17) -> 0 | AC16: =SUM(AD16:AI16) -> 0 | AD16: =SUM(AD17) -> 0 | AF16: =SUM(AF17) -> 0 | AH16: =SUM(AH17) -> 0 | AI16: =SUM(AI17) -> 0
C17: 3 | E17: Код ОКПД2 | G17: =H17+O17+V17+AC17 -> 30000 | H17: =I17+K17+M17+N17 -> 30000 | I17: 0 | K17: 0 | M17: 0 | N17: 30000 | O17: =SUM(P17:U17) -> 0 | P17: 0 | R17: 0 | T17: 0 | U17: 0 | V17: 0 | W17: 0 | Y17: 0 | AA17: 0 | AB17: 0 | AC17: 0 | AD17: 0 | AF17: 0 | AH17: 0 | AI17: 0
A18: 3 | C18: 6 | E18: Мероприятие 3 | F18: Планируемый | G18: =H18+O18+V18+AC18 -> 200000 | H18: =I18+K18+M18+N18 -> 70000 | I18: =SUM(I19) -> 0 | K18: =SUM(K19) -> 0 | M18: =SUM(M19) -> 70000 | N18: =SUM(N19) -> 0 | O18: =P18+R18+T18+U18 -> 100000 | P18: =SUM(P19) -> 100000 | R18: =SUM(R19) -> 0 | T18: =SUM(T19) -> 0 | U18: =SUM(U19) -> 0 | V18: 30000 | W18: =SUM(W19) -> 0 | Y18: =SUM(Y19) -> 0 | AA18: =SUM(AA19) -> 0 | AB18: =SUM(AB19) -> 0 | AC18: =AD18+AF18+AH18+AI18 -> 0 | AD18: =SUM(AD19) -> 0 | AF18: =SUM(AF19) -> 0 | AH18: =SUM(AH19) -> 0 | AI18: =SUM(AI19) -> 0
C19: 6 | E19: Код ОКПД2 | G19: =H19+O19+V19+AC19 -> 170000 | H19: =I19+K19+M19+N19 -> 70000 | I19: 0 | K19: 0 | M19: 70000 | N19: 0 | O19: =P19+R19+T19+U19 -> 100000 | P19: 100000 | R19: 0 | T19: 0 | U19: 0 | V19: =W19+Y19+AA19+AB19 -> 0 | W19: 0 | Y19: 0 | AA19: 0 | AB19: 0 | AC19: =AD19+AF19+AH19+AI19 -> 0 | AD19: 0 | AF19: 0 | AH19: 0 | AI19: 0
A20: N
A22: * Приложение заполняется только в том случае , если мероприятие относится к Стратегии цифровой трансформации (СЦТ)
A23: ** Определяются в соответствии с общероссийским классификатором по видам экономической деятельности (ОКПД2).
A24: В гр.2 указывается № инициативы СЦТ в соответсвии с утвержденной СЦТ ФГУП «Госкорпорация по ОрВД» до 2030 года и действующей редакцией методических рекомендаций по цифровой трансформации государственных корпораций и компаний с государственным участием (приложение №3)
A25: Сумма КПЭ: по гр. 8-14 должна быть равна лимиту финансирования текущего года, отраженному в гр. 7; по гр. 16-22 должна быть равна лимиту 1-го планового года, отраженному в гр. 15; по гр. 24-30 должна быть равна лимиту 2-го планового года, отраженному в гр. 23; по гр. 32-38 должна быть равна лимиту последующих годов, отраженному в гр. 31;
A26: Гр. 6 равна сумме гр. 7, 15,23,31
A27: В гр. 8; гр. 16; гр. 24; гр.32 (КПЭ 17 -"Увеличение вложений в российские решения в сфере информационных технологий")- указывается объем расходов на российское ПО, включенное в Единый реестр российских программ для электронных вычислительных машин и баз данных или в Единый реестр программ для электронных вычислительных машин и баз данных государств - членов Евразийского экономического союза, и связанные с ним работы (услуги). В случае если ПО является свободно распространяемым, но сведения о таком программном обеспечении не включены в Единый реестр российского ПО, то такое ПО относится к иностранному ПО и заполняются гр. 9; гр. 17; гр. 25; гр.33 в соответствующем периоде;
A28: В гр. 9, гр.17, гр. 25, гр. 33 (КПЭ 23 " Увеличение расходов на информационные технологии") - указывается объем расходов на иностранное ПО и связанные с ним работы (услуги).
A29: В гр. 11; гр. 19; гр. 27; гр.35 (КПЭ 19 "Увеличение вложений в радиоэлектронную продукцию российского происхождения, в том числе в телекоммуникационное оборудование и программно-аппаратные комплексы"- указывается объем расходов государственной компании на радиоэлектронную продукцию российского происхождения, в том числе телекоммуникационное оборудование и программно-аппаратные комплексы. Под радиоэлектронной продукцией российского происхождения понимается радиоэлектронная продукция, сведения о которой включены в реестр российской промышленной продукции (согласно постановлению Правительства Российской Федерации от 17.07.2015 N 719). Также включаются расходы на радиоэлектронную продукцию, которая включена в евразийский реестр промышленных товаров государств - членов Евразийского экономического союза. В данные графы не включаются расходы на работы (услуги), связанные с радиоэлектронной продукцией. Указанные затраты отражаются в гр. 12,гр.20,гр.28, гр. 36 в соответствующем периоде.
A30: В гр. 12; гр. 20; гр. 28; гр.36 (КПЭ 26 "Увеличение расходов, направленных на закупку радиоэлектронной продукции, телекоммуникационного оборудования и программно-аппаратных комплексов, а также связанных с ней работ (услуг)") - указывается объем расходов государственной компании на радиоэлектронную продукцию иностранного производства, в том числе телекоммуникационное оборудование и программно-аппаратные комплексы, а также связанные с ней работы (услуги), а также работы (услуги) связанные с приобретением радиоэлектронной продукции российского производства.
A31: В гр. 13; гр. 21; гр. 29; гр.37 (КПЭ 20 "Объем затрат на исследования и разработки, направленных на создание и развитие передовых и критически важных для отрасли цифровых технологий и решений, в том числе новых производственных технологий, связанных с интенсивным применением информационно-коммуникационных технологий в рамках реализации инициатив (проектов) СЦТ") - указывается объем затрат на научные исследования и разработки (НИОКР), направленных на создание и развитие передовых и критически важных для отрасли цифровых технологий и решений, в том числе новых производственных технологий, связанных с интенсивным применением информационно-коммуникационных технологий.
A32: В гр. 13; гр. 21; гр. 29; гр.37 (КПЭ 22 "Объем расходов государственных компаний на реализацию инициатив (мероприятий), связанных с созданием, внедрением и применением технологий и решений в сфере искусственного интеллекта") - указываются расходы связанные с технологиями и решениями в сфере искусственного интеллекта.

Sheet Показатели ИПР ПДП
B2: Справочник показателей инвестиционной программы Предприятия и программы деятельности Предприятия
B4: Показатели ИПР | D4: Показатели ПДП
B5: Завершение создания УЦ | D5: Число введенных в эксплуатацию укрупненных центров управления воздушным движением | E5: УЦ УВД
B6: Модернизация УЦ | D6: Число введённых в эксплуатацию доплеровских азимутально-дальномерных радиомаяков, радиотехнических систем ближней навигации, дальномерных радиомаяков | E6: DME
B7: Создание резервных центров | D7: Число введенных в эксплуатацию приводных радиостанций | E7: ПРС
B8: Модернизация КТС АУВД | D8: Число введенных в эксплуатацию средств АУВД аэродромов | E8: АУВД
B9: АРП | D9: Число введенных в эксплуатацию радиомаячных систем посадки | E9: РМС
B10: ОРЛ-А | D10: Число введенных в эксплуатацию аэродромных радиолокационных комплексов (модернизация) | E10: АРЛК
B11: ОРЛ-Т | D11: Число введенных в эксплуатацию трассовых радиолокационных комплексов (модернизация) | E11: ТРЛК
B12: МВРЛ | D12: Число введенных в эксплуатацию средств функционального дополнения GBAS (локальная контрольно-корректирующая станция ЛККС-А-2000) | E12: ЛККС
B13: РЛС ОЛП | D13: Число введенных в эксплуатацию средств вторичной моноимпульсной радиолокации (МВРЛ) | E13: МВРЛ
B14: МПСН | D14: Число введенных в эксплуатацию многопозиционных систем наблюдения | E14: МПСН
B15: РМС | D15: Число введённых в эксплуатацию центров коммутации сообщений и AMHS | E15: ЦКС и AMHS
B16: РМА/РМД | D16: Число введенных ОПСС ЦСИАФС | E16: ОПСС ЦСИАФС
... B19: ПРС | D19: Число введённых в эксплуатацию командно-диспетчерских пунктов (КДП) | E19: КДП
B20: ЛККС
B21: ОПСС ЦСИАФС
B22: VDL-2*
B23: D-ATIS*
B24: ATN*
B25: ЦКС, AMHS
B26: ОВЧ
B27: ВЧ
B28: СКРС
B29: ЗССС | D29: Справочник является динамичным и может обновляться по мере необходимости!
B30: ПС административных зданий
B31: ПС многофункциональных комплексов
B32: ПС производственно-технических зданий
B33: ПС здания ВЛЭК
B34: *ПС - проектирование и строительство

Sheet Пр. 3а Сетевой график к пл. 1-3
AV2: ПРИЛОЖЕНИЕ № 3а
AV3: К ПОРЯДКУ ТЕКУЩЕГО ПЛАНИРОВАНИЯ ПРОИЗВОДСТВЕННО-ХОЗЯЙСТВЕННОЙ ДЕЯТЕЛЬНОСТИ ФГУП «ГОСКОРПОРАЦИЯ ПО ОрВД»
AK4: Форма сетевого графика к заявкам в планы 1 - 3 группы (кроме подгруппы 104.1)
AJ6: ФГУП «Госкорпорация по ОрВД» | AV6: год
A8: № п/п | B8: Код мероприятия (КМ) | C8: Наименование плана | D8: Филиал | E8: Передано на исполнение в филиал (дата и номер Распоряжения) | F8: Наименование мероприятия | G8: Место установки | H8: Оборудование | I8: Наименование этапа (вид работ) | J8: Год инициации мероприятия | K8: Срок начала реализации мероприятия/этапа (мм_гггг -мм_гггг, мм-месяц, гггг-год) | L8: Номер договора и дата | M8: Рекзизиты договора | O8: Стоимость мероприятия (этапа) планируемая | P8: Централизованное финансирование по состоянию на 01.01.____ | Q8: Лимит финансирования на 20__ год | R8: Платежи последующих периодов | U8: Планируемая дата заключения контракта (договора) | V8: Ответственный исполнитель | W8: Директор, осуществляющий контроль за реализацией | X8: Этап 1. | Z8: Этап 2: Согласование и утверждение ТЗ/ПСД /проект установки | AM8: Этап 3. Подготовка закупочной процедуры | BQ8: Этап 4. Подготовка, согласование проекта договора/документации о закупке | ED8: Комментарии | EE8: Разница в сроках (количество дней) | EF8: Ответственный исполнитель | EG8: Комментарии филиалов | EH8: доп.информация для расчета даты проведения конкурентных процедур | EI8: Прогнозируемая дата заключения договора
X9: Способ закупки | Y9: Ответственный директор по направлению деятельности -Директор ПО,ЗД,ДРиИО | Z9: Подготовка проекта ТЗ (технических требований)/Задания на проектирования/Задания на обследование | AC9: Согласование проекта ТЗ (технических требований)/Задания на проектирования/Задания на обследование с Алмаз-Антей, производителем | AF9: Согласование проекта ТЗ (технических требований)в Росавиации и с Департаментом программы развития и Департаментом цифровой трансформации Минтранса России +28 | AG9: Фактическое исполнение | AI9: Утверждение ТЗ (технических требований)/Задания на проектирования/Задания на обследование и передача его для формирования НМЦД (в случае размещения у ЕП - направление в Алмаз-Антей | AL9: Ответственный (директор по направлению деятельности) | AM9: Формирование описания предмета закупки и состава оборудования (спецификации оборудования) | AP9: Ответственный (директор по направлению деятельности, директор филиала) | AQ9: Запрос ценовой информации в Алмаз-Антей с описанием объекта закупки /Запрос технико - коммерческих предложений | AT9: Ответственный директор по направлению деятельности - Директор ПО,ЗД,ДРиИО/Директор филиала | AU9: Получения ТКП от Алмаз-Антея/ потенциальных исполнителей | AX9: Ответственный директор по направлению деятельности - Директор ПО,ЗД,ДРиИО /Директор филиала | AY9: Рассмотрение ЦИ | BB9: Ответственный директор по направлению деятельности - Директор ПО,ЗД,ДРиИО/Директор филиала | BC9: Формирование заявки в план закупки с НМЦД | BF9: Ответственный директор по направлению деятельности - Директор ПО,ЗД,ДРиИО/Директор филиала | BG9: Согласование заявки в план закупки и планируемая дата опубликования в план закупки Ответственный директор по направлению деятельности - Директор ПО,ЗД,ДРиИО | BJ9: Комментарии Службы планирования закупочной деятельности и ценообразования (Служба ПЗДиЦО) | BL9: Комментарии ФИЛИАЛОВ | BM9: Уведомление Алмаз-Антей о включении мероприятия в ПЗ с запросом проекта договора | BP9: Дирекцию правового обеспечения, закупочной деятельности, договорной работы и имущественных отношений | BQ9: Предоставление проекта договора по мероприятию от Генерального подрядчика/формирование документации о закупке | BT9: Ответственный (директор по направлению деятельности, директор филиала)/Дирекцию правового обеспечения, закупочной деятельности, договорной работы и имущественных отношений | BU9: Подписание Извещения о проведении закупки у единственного поставщика (подрядчика, исполнителя), решения по выбору поставщика | BX9: Ответственный директор по направлению деятельности - Дирекция ПО,ЗД,ДРиИО | BY9: Формирование комплекта документации о закупке (обоснование проведения закупки, НМЦД, извещения проекта договора/ документации о закупке и т.д.) в договорной отдел для согласования | CB9: Ответственный (директор по направлению деятельности, директор филиала) | CC9: Дата направления филиалом пакета документов на согласование в ген. дирекцию на согласование | CD9: Назначение Эксперта по проекту договору/ документации о закупке от договорного отдела | CG9: Ответственный директор по направлению деятельности - Дирекция ПО, ЗД, ДРиИО | CH9: Рассмотрение проекта договора /документации о закупке Экспертом по договору от договорного отдела | CK9: Ответственный директор по направлению деятельности - Дирекция ПО,ЗД,ДРиИО директор филиала | CL9: Согласование проекта договора/ документации о закупке | CO9: Директор филиала, Дирекция ПО,ЗД,ДРиИО, Директор по направлению деятельности в части тех. вопросов | CP9: Необходимость согласования протокола разногласий к договору в АО «Концерн ВКО «Алмаз-Антей» (да/нет) | CQ9: Формирование протокола разногласий по итогам согласования проекта договора в генеральной дирекции (при наличии) - Дирекция ПО,ЗД,ДРиИО | CT9: Ответственный директор по направлению деятельности - Дирекция ПО,ЗД,ДРиИО | CU9: Согласование протокола разногласий к договору в АО «Концерн ВКО «Алмаз-Антей» (при наличии) | CX9: Направление на согласование проекта договора/ документации о закупке в Росавиацию с приложением юридического заключения Ответственный директор по направлению деятельности - Дирекция ПО,ЗД,ДРиИО | DA9: Ответственный директор по направлению деятельности - Дирекция ПО,ЗД,ДРиИО | DB9: Согласование проекта договора/документации о закупке в Росавиации Ответственный - Росавиация Вносит информацию Дирекция ПО,ЗД,ДРиИО | DE9: Публикация в ЕИС Извещения о проведении закупки у единственного поставщика (подрядчика, исполнителя)/ Извещения и документации о проведении закупки | DH9: Ответственный директор по направлению деятельности - Дирекция ПО,ЗД,ДРиИО | DI9: Определение победителя конкурентных процедур | DL9: Ответственный директор по направлению деятельности - Дирекция ПО,ЗД,ДРиИО директор филиала | DM9: Организация согласования обеспечения договора (в случае наличия такого требования) | DP9: Ответственный директор по направлению деятельности - Дирекция ПО,ЗД,ДРиИО | DQ9: Заключение договора (подписание со стороны ФГУП "Госкорпорация по ОрВД") | DT9: Ответственный директор по направлению деятельности - Дирекция ПО,ДР и ИО директор филиала | DU9: Публикования договора в ЕИС | DX9: Ответственный директор по направлению деятельности - Служба ПЗДиЦО, директор филиала | DY9: Информирование дирекции по направлению деятельности о заключении договора | EB9: Ответственный директор по направлению деятельности - Дирекция ПО,ДР и ИО, директор филиала
M10: номер | N10: дата | R10: 20__ год | S10: 20__ год | T10: последующие годы | Z10: План | AA10: Факт | AB10: Отклонение | AC10: План +10 | AD10: Факт | AE10: Отклонение | AG10: № документа | AH10: дата документа | AI10: План +1 | AJ10: Факт | AK10: Отклонение | AM10: План +2 | AN10: Факт | AO10: Отклонение | AQ10: План +3 | AR10: Факт | AS10: Отклонение | AU10: План | AV10: Факт | AW10: Отклонение | AY10: План +5 | AZ10: Факт | BA10: Отклонение | BC10: План +1 | BD10: Факт | BE10: Отклонение | BG10: План +1 | BH10: Факт | BI10: Отклонение | BJ10: Ответственный | BK10: Комментарий | BM10: План +1 | BN10: Факт | BO10: Отклонение | BQ10: План +20/10 | BR10: Факт | BS10: Отклонение | BU10: План +2/0 | BV10: Факт | BW10: Отклонение | BY10: План +3 | BZ10: Факт | CA10: Отклонение | CD10: План +3 | CE10: Факт | CF10: Отклонение | CH10: План +2 | CI10: Факт | CJ10: Отклонение | CL10: План +2 | CM10: Факт | CN10: Отклонение | CQ10: План +3/0 | CR10: Факт | CS10: Отклонение | CU10: План +15/0 | CV10: Факт | CW10: Отклонение | CX10: План +2/0 | CY10: Факт | CZ10: Отклонение | DB10: План +15 | DC10: Факт | DD10: Отклонение | DE10: План +2 | DF10: Факт | DG10: Отклонение | DI10: План | DJ10: Факт | DK10: Отклонение | DM10: План 0/+5 | DN10: Факт | DO10: Отклонение | DQ10: План +1 | DR10: Факт | DS10: Отклонение | DU10: План +3 | DV10: Факт | DW10: Отклонение | DY10: План +1 | DZ10: Факт | EA10: Отклонение
A11: 1 | B11: * | C11: * | D11: * | E11: * | F11: 2 | G11: * | H11: * | I11: * | J11: * | K11: 3 | L11: * | M11: * | N11: * | O11: * | P11: * | Q11: * | R11: * | S11: * | T11: * | U11: * | V11: * | W11: * | X11: 4 | Y11: 5 | Z11: 6 | AA11: 7 | AB11: 8 | AC11: 9 | AD11: 10 | AE11: 11 | AF11: 12 | AG11: 13 | AH11: 14 | AI11: 15 | AJ11: 16 | AK11: 17 | AL11: 18 | AM11: 19 | AN11: 20 | AO11: 21 | AP11: 22 | AQ11: 23 | AR11: 24 | AS11: 25 | AT11: 26 | AU11: 27 | AV11: 28 | AW11: 29 | AX11: 30 | AY11: 31 | AZ11: 32 | BA11: 33 | BB11: 34 | BC11: 35 | BD11: 36 | BE11: 37 | BF11: 38 | BG11: 39 | BH11: 40 | BI11: 41 | BJ11: 42 | BK11: 43 | BL11: 44 | BM11: 45 | BN11: 46 | BO11: 47 | BP11: 48 | BQ11: 49 | BR11: 50 | BS11: 51 | BT11: 52 | BU11: 53 | BV11: 54 | BW11: 55 | BX11: 56 | BY11: 57 | BZ11: 58 | CA11: 59 | CB11: 60 | CC11: 61 | CD11: 62 | CE11: 63 | CF11: 64 | CG11: 65 | CH11: 66 | CI11: 67 | CJ11: 68 | CK11: 69 | CL11: 70 | CM11: 71 | CN11: 72 | CO11: 73 | CP11: 74 | CQ11: 75 | CR11: 76 | CS11: 77 | CT11: 78 | CU11: 79 | CV11: 80 | CW11: 81 | CX11: 82 | CY11: 83 | CZ11: 84 | DA11: 85 | DB11: 86 | DC11: 87 | DD11: 88 | DE11: 89 | DF11: 90 | DG11: 91 | DH11: 92 | DI11: 93 | DJ11: 94 | DK11: 95 | DL11: 96 | DM11: 97 | DN11: 98 | DO11: 99 | DP11: 100 | DQ11: 101 | DR11: 102 | DS11: 103 | DT11: 104 | DU11: 105 | DV11: 106 | DW11: 107 | DX11: 108 | DY11: 109 | DZ11: 110 | EA11: 111 | EB11: 112 | EC11: 113 | ED11: 114 | EE11: 115 | EF11: 116 | EG11: 117 | EH11: 118 | EI11: 119
A12: 1. Организация воздушного движения (ОрВД) | C12: Раздел
A14: 1.1.Модернизация укрупненных центров ЕС ОрВД (включая строительство/реконструкция) | C14: Подраздел
K17: * | X17: Актуальные формы с детализацией заполнения сетевых графиков, учитывающие локальные акты предприятия размещены на Корпоративном портале: Документы предприятия/Регламенты и стандарты/Общекорпоративные документы СМК/СТО-ГК-0001-017 Текущее экономическое планирование»

Sheet Пр.3б Сетевой график к пл.104.1
AW2: ПРИЛОЖЕНИЕ № 3а
AW3: К ПОРЯДКУ ТЕКУЩЕГО ПЛАНИРОВАНИЯ ПРОИЗВОДСТВЕННО-ХОЗЯЙСТВЕННОЙ ДЕЯТЕЛЬНОСТИ ФГУП «ГОСКОРПОРАЦИЯ ПО ОрВД»
AL4: Форма сетевого графика к заявкам в планы 1 группы 104.1 подгруппы
AK6: ФГУП «Госкорпорация по ОрВД» | AW6: год
A8: № п/п | B8: Код мероприятия (КМ) | C8: Наименование плана | D8: Филиал | E8: Передано на исполнение в филиал (дата и номер Распоряжения) | F8: Наименование мероприятия | G8: Место установки | H8: Оборудование | I8: Наименование этапа (вид работ) | J8: Год инициации мероприятия | K8: Срок начала реализации мероприятия/этапа (мм_гггг -мм_гггг, мм-месяц, гггг-год) | L8: Номер договора и дата | M8: Рекзизиты договора | O8: Стоимость мероприятия (этапа) планируемая | P8: Централизованное финансирование по состоянию на 01.01.____ | Q8: Лимит финансирования на 20__ год | R8: Платежи последующих периодов | U8: Планируемая дата заключения контракта (договора) | V8: Ответственный исполнитель | W8: Директор, осуществляющий контроль за реализацией | X8: Этап 1. | Y8: Этап 2: Формирование и согласование Технического задания (технических требований) | AO8: Этап 3. Подготовка закупочной процедуры | BM8: Этап 4. Подготовка, согласование проекта договора/документации о закупке | DF8: Комментарии | DG8: Разница в сроках (количество дней) | DH8: Ответственный исполнитель | DI8: Комментарии филиалов | DJ8: доп.информация для расчета даты проведения конкурентных процедур | DK8: Прогнозируемая дата заключения договора
X9: Формирование Централизованных Планов на планируемый год | Y9: Подготовка проекта ТЗ (технических требований) на выполнение работы ГРАФА "ПЛАН" ОБЯЗАТЕЛЬНА К ЗАПОЛНЕНИЮ ДЛЯ КОРРЕКТНОГО РАСЧЕТА | AB9: Дирекция по направлению деятельности | AC9: Согласование проекта ТЗ (технических требований) с АО "Концерн ВКО "Алмаз-Антей", производителем | AF9: Дирекция по направлению деятельности - отв АО "Концерн ВКО "Алмаз-Антей" | AG9: Согласование Технического задания (технических требований) в Росавиации и с Департаментом программ развития Минтранса России (при необходимости) | AJ9: Росавиация, Минтранс России, Дирекция по направлению деятельности - контроль | AK9: Передача ТЗ для учета при выполнении ПИР по строительству технологического здания и оснащения АС ОрВД | AN9: Дирекция по направлению деятельности | AO9: Формирование и направление на согласование описания объекта закупки на основании ТЗ и запроса ценовой информации ЕСЛИ ТЗ НЕ ТРЕБУЕТСЯ. ГРАФА "ПЛАН" ЗАПОЛНЯЕТСЯ ВРУЧНУЮ | AR9: Дирекция по направлению деятельности | AS9: Рассмотрение поступившего запроса ценовой информации на соответствие норм законодательства в сфере закупок, внутренних НПА и вложенным обосновывающим документам. Направление согласованного Запроса ценовой информации в АО "Концерн ВКО "Алмаз-Антей" | AV9: Дирекция правового обеспечения, закупочной деятельности, договорной работы и имущественных отношений | AW9: Представление ответа на запрос ЦИ от АО "Концерн ВКО "Алмаз-Антей" | AZ9: АО "Концерн ВКО "Алмаз-Антей" | BA9: Формирование обоснования НМЦК (НМЦД) (включая экспертную оценку СПО*), Создание и организация процедуры согласования Предложения на закупку и заявки в План-график закупок (далее - ПГ) (План закупки, далее - ПЗ) | BD9: Дирекция по направлению деятельности Дирекция правового обеспечения, закупочной деятельности, договорной работы и имущественных отношений - при организации работы по 223-ФЗ | BE9: Проверка и согласование НМЦК (НМЦД), предложения на закупку и заявки в ПГ (ПЗ для 223-ФЗ). Формирования плана-графика закупок или изменений в план-график закупок. Организация согласования и утверждения Плана-графика закупок (Плана закупки). Внесение информации о Предложении на закупку в Электронный бюджет (в ручном формате). Публикация предложений на закупку в Электронном бюджете. Внесение информации в План-график закупок в Электронный бюджет и ЕИС (в ручном формате). Публикация Плана-графика закупок (Плана закупки) в ЕИС. | BH9: Дирекция правового обеспечения, закупочной деятельности, договорной работы и имущественных отношений-отв. Дирекция по экономике и финансам - согл. Дирекция по направлению деятельности - согл. | BI9: Уведомление Генерального подрядчика о включении мероприятия в ПГ (ПЗ) с запросом контракта (оферты) (с приложением типового проекта контракта/договора) | BL9: Дирекция правового обеспечения, закупочной деятельности, договорной работы и имущественных отношений Дирекция по направлению деятельности | BM9: Представление проекта договора (оферты) по мероприятию от АО «Концерн ВКО «Алмаз-Антей»* | BP9: АО "Концерн ВКО "Алмаз-Антей" Дирекция по направлению деятельности - контроль за получением ГК договора (запрос в случае несвоевременного получения) | BQ9: Подписание Извещения о проведении закупки у единственного поставщика (подрядчика, исполнителя), решения по выбору поставщика | BT9: Дирекция по направлению деятельности | BU9: Формирование комплекта документации о закупке (обоснование проведения закупки, НМЦК, Извещение и Проект контракта/договора АА, иные док) | BX9: Дирекция по направлению деятельности - отв., Дирекция по экономике и финансам - справка об источнике финансирования; Дирекция правового обеспечения, закупочной деятельности, договорной работы и имущественных отношений | BY9: Назначение Эксперта по контракту/договору от договорного отдела | CB9: Дирекция правового обеспечения, закупочной деятельности, договорной работы и имущественных отношений | CC9: Рассмотрение проекта контракта/договора Экспертом по контракту/договору от договорного отдела | CF9: Дирекция правового обеспечения, закупочной деятельности, договорной работы и имущественных отношений, Дирекция по направлению деятельности - участие в части тех.вопросов | CG9: Согласование проекта контракта/договора в генеральной дирекции ФГУП «Госкорпорация по ОрВД» | CJ9: Дирекция правового обеспечения, закупочной деятельности, договорной работы и имущественных отношений - отв. Дирекция по направлению деятельности - участие в части тех.вопросов, согл. Все остальные по списку листа согласования. -согл. | CK9: Необходимость согласования протокола разногласий к договору в АО «Концерн ВКО «Алмаз-Антей» (да/нет) | CL9: Формирование протокола разногласий по итогам согласования проекта контракта/договора в генеральной дирекции (при наличии) * | CO9: Дирекция правового обеспечения, закупочной деятельности, договорной работы и имущественных отношений - отв. Дирекция по направлению деятельности - участие в части тех.вопросов, согл. Все остальные по списку листа согласования. -согл. | CP9: Согласование протокола разногласий к контракту/договору в АО «Концерн ВКО «Алмаз-Антей» * (при наличии) | CS9: АО "Концерн ВКО "Алмаз-Антей" | CT9: Направление на согласование проекта контракта/договора в Росавиацию | CW9: Дирекция правового обеспечения, закупочной деятельности, договорной работы и имущественных отношений | CX9: Согласование проекта контракта/договора в Росавиации * | DA9: Росавиация | DB9: Заключение договора (подписание договора со стороны ФГУП "Госкорпорация по ОрВД") | DE9: Дирекция правового обеспечения, закупочной деятельности, договорной работы и имущественных отношений
M10: номер | N10: дата | R10: 20__ год | S10: 20__ год | T10: последующие годы | Y10: План | Z10: Факт | AA10: Отклонение | AC10: План | AD10: Факт | AE10: Отклонение | AG10: План | AH10: Факт | AI10: Отклонение | AK10: План | AL10: Факт | AM10: Отклонение | AN10: Дирекция по направлению деятельности | AO10: План | AP10: Факт | AQ10: Отклонение | AS10: План | AT10: Факт | AU10: Отклонение | AW10: План | AX10: Факт | AY10: Отклонение | BA10: План | BB10: Факт | BC10: Отклонение | BE10: План | BF10: Факт | BG10: Отклонение | BI10: План | BJ10: Факт | BK10: Отклонение | BM10: План | BN10: Факт | BO10: Отклонение | BQ10: План | BR10: Факт | BS10: Отклонение | BU10: План | BV10: Факт | BW10: Отклонение | BY10: План | BZ10: Факт | CA10: Отклонение | CC10: План | CD10: Факт | CE10: Отклонение | CG10: План | CH10: Факт | CI10: Отклонение | CL10: План | CM10: Факт | CN10: Отклонение | CP10: План | CQ10: Факт | CR10: Отклонение | CT10: План | CU10: Факт | CV10: Отклонение | CX10: План | CY10: Факт | CZ10: Отклонение | DB10: План | DC10: Факт | DD10: Отклонение
A11: 1 | B11: * | C11: * | D11: * | E11: * | F11: 2 | G11: * | H11: * | I11: * | J11: * | K11: 3 | L11: * | M11: * | N11: * | O11: * | P11: * | Q11: * | R11: * | S11: * | T11: * | U11: * | V11: * | W11: * | X11: 4 | Y11: 5 | Z11: 6 | AA11: 7 | AB11: 8 | AC11: 9 | AD11: 10 | AE11: 11 | AF11: 12 | AG11: 13 | AH11: 14 | AI11: 15 | AJ11: 16 | AK11: 17 | AL11: 18 | AM11: 19 | AN11: 20 | AO11: 21 | AP11: 22 | AQ11: 23 | AR11: 24 | AS11: 25 | AT11: 26 | AU11: 27 | AV11: 28 | AW11: 29 | AX11: 30 | AY11: 31 | AZ11: 32 | BA11: 33 | BB11: 34 | BC11: 35 | BD11: 36 | BE11: 37 | BF11: 38 | BG11: 39 | BH11: 44 | BI11: 45 | BJ11: 46 | BK11: 47 | BL11: 48 | BM11: 49 | BN11: 50 | BO11: 51 | BP11: 52 | BQ11: 53 | BR11: 54 | BS11: 55 | BT11: 56 | BU11: 57 | BV11: 58 | BW11: 59 | BX11: 60 | BY11: 61 | BZ11: 58 | CA11: 59 | CB11: 60 | CC11: 61 | CD11: 62 | CE11: 63 | CF11: 64 | CG11: 65 | CH11: 66 | CI11: 67 | CJ11: 68 | CK11: 69 | CL11: 70 | CM11: 71 | CN11: 72 | CO11: 73 | CP11: 74 | CQ11: 75 | CR11: 76 | CS11: 77 | CT11: 78 | CU11: 79 | CV11: 80 | CW11: 81 | CX11: 82 | CY11: 83 | CZ11: 84 | DA11: 85 | DB11: 86 | DC11: 87 | DD11: 88 | DE11: 89 | DF11: 90 | DG11: 91 | DH11: 92 | DI11: 93 | DJ11: 94 | DK11: 95
K17: * | X17: Актуальные формы с детализацией заполнения сетевых графиков, учитывающие локальные акты предприятия размещены на Корпоративном портале: Документы предприятия/Регламенты и стандарты/Общекорпоративные документы СМК/СТО-ГК-0001-017 Текущее экономическое планирование»

Sheet Пр 4 заявка 4
AQ1: ПРИЛОЖЕНИЕ № 4
AQ2: К ПОРЯДКУ ТЕКУЩЕГО ПЛАНИРОВАНИЯ ПРОИЗВОДСТВЕННО-ХОЗЯЙСТВЕННОЙ ДЕЯТЕЛЬНОСТИ ФГУП «ГОСКОРПОРАЦИЯ ПО ОрВД»
S3: Форма заявки в планы 4 группы
S4: ________________________ ФГУП «Госкорпорация по ОрВД» на ____________ год
S5: (включая корректировку № ________от _______)
AX6: тыс. руб.
A7: Код статьи ВПО | B7: КУУ | C7: НД | D7: КИП | E7: КМ | F7: Год инициации | G7: Порядковый номер | H7: Код инициатора мероприятия =1-ГК, =2-филиал | I7: Код Плана (Пр. 1) | J7: Территориальный код этапа мероприятия | K7: Код места установки | L7: Объект, средство, система | M7: Тип этапа (Пр. 27) | N7: Порядковый номер этапа мероприятия | O7: Номер раздела/подраздела (Пр 2а) | P7: КВУ | Q7: Филиал | R7: Краткое наименование мероприятия | S7: Наименование мероприятия | T7: Наименование этапа | U7: Место реализации | V7: Содержание мероприятия/этапа | W7: Общая плановая стоимость мероприятия/этапа | X7: Срок начала реализации мероприятия/этапа (мм_гггг, мм-месяц, гггг-год) | Y7: Срок завершения реализации мероприятия/этапа (мм_гггг, мм-месяц, гггг-год) | Z7: Выполнено по состоянию на 01.01.____ | AA7: Оплачено по состоянию на 01.01.____ | AB7: Централизованное финансирование по состоянию на 01.01.____ | AC7: Платежи текущего финансового года, в т.ч.: | AP7: Платежи последующих периодов | AS7: Планируемая дата заключения договора (мм_гггг, мм - месяц, гггг - год | AT7: Реквизиты договора | AV7: Ответственный исполнитель в филиале | AW7: Ответственный исполнитель ГД | AX7: Передано на исполнение в филиал (дата и номер документа)
AC8: 1 кв-л по оплате | AF8: 2 кв-л по оплате | AI8: 3 кв-л по оплате | AL8: 4 кв-л по оплате | AO8: Итого
F9: ОО | G9: YYYY | H9: К | I9: XXX.X | J9: FFFF | K9: BBB | L9: CCC | M9: GG | N9: HH | O9: DD.EEEE | AC9: январь | AD9: февраль | AE9: март | AF9: апрель | AG9: май | AH9: июнь | AI9: июль | AJ9: август | AK9: сентябрь | AL9: октябрь | AM9: ноябрь | AN9: декабрь | AP9: 1-й плановый год | AQ9: 2-й плановый год | AR9: последующие годы | AT9: Номер / Планируемый ** | AU9: Дата /Планируемый**
A10: * | B10: * | C10: * | D10: * | E10: * | F10: * | G10: * | H10: * | I10: * | J10: * | K10: * | L10: * | M10: * | N10: * | O10: * | P10: * | Q10: 1 | R10: * | S10: 2 | T10: 3 | U10: 4 | V10: 5 | W10: 6 | X10: 7 | Y10: 8 | Z10: * | AA10: 9 | AB10: 10 | AC10: * | AD10: * | AE10: * | AF10: * | AG10: * | AH10: * | AI10: * | AJ10: * | AK10: * | AL10: * | AM10: * | AN10: * | AO10: 11 | AP10: 12 | AQ10: 13 | AR10: 14 | AS10: 15 | AT10: * | AU10: * | AV10: * | AW10: 16 | AX10: 17
Q11: Всего по мероприятиям, инициированным в планируемом году, в том числе:
Q13: Всего по переходящим мероприятиям, в том числе:
A17: Примечание: | S17: Заместитель генерального директора / руководитель по направлению деятельности
A18: Колонки (1)-(13) для печатной формы плана
A19: Колонки (1)-(13),(*) - для электронной формы плана | S19: ПРИМЕЧАНИЕ: | V19: ВПО - план возникновения и погашения обязательств
V20: КУУ - код управленческого учета
V21: КМ-код мероприятия
V22: КВУ- код внутреннего учета

Sheet Пр 5 план 1, 2, 3 гр.
AG2: ПРИЛОЖЕНИЕ № 5
AG3: К ПОРЯДКУ ТЕКУЩЕГО ПЛАНИРОВАНИЯ ПРОИЗВОДСТВЕННО-ХОЗЯЙСТВЕННОЙ ДЕЯТЕЛЬНОСТИ ФГУП «ГОСКОРПОРАЦИЯ ПО ОрВД»
A6: План централизованных мероприятий (по планам 1, 2, 3 группы) ФГУП "Госкорпорация по ОрВД" на ____ год
A7: наименование плана
A8: тыс.руб.
A9: № п/п | B9: КИП | C9: КМ | D9: Год инициации | E9: Порядковый номер | F9: Код инициатора мероприятия =1-ГК, =2-филиал | G9: Код Плана (Пр. 1) | H9: Территориальный код этапа мероприятия | I9: Код места установки | J9: Объект, средство, система | K9: Тип этапа (Пр. 27) | L9: Порядковый номер этапа мероприятия | M9: Номер раздела/подраздела (Пр 2а) | N9: Статья ВПО | O9: КУУ | P9: КВУ | Q9: Филиал | R9: Номер УИПа | S9: Номер показателя ПДП (справочник) | T9: Наименование показателя Ипр (справочник) | U9: Номер поручения ФОИВ (справочник) | V9: Признак инновационности мероприятия (да/нет) | W9: Относится к Стратегии цифровой трансформации (да/нет)***** | X9: Статус мероприятия (закрыто/исполняется) | Y9: Наименование мероприятия | Z9: Краткое наименование мероприятия | AA9: Место реализации | AB9: Наименование оборудования / ОС / НМА/Воздушного судна | AC9: Наименование этапа (вид работ) | AD9: Срок реализации мероприятия/этапа (мм_гггг -мм_гггг, мм-месяц, гггг-год)*** | AE9: Реквизиты договора | AG9: Стоимость мероприятия (этапа) планируемая | AH9: Финансирование по договору по состоянию на 01.01.____ | AI9: Платежи текущего финансового года | BB9: Платежи последующих периодов | BW9: Планируемая дата заключения контракта (договора) ( мм_гггг) | BX9: Период выполнения обязательств по договору (для текущих расходов) (мм_гггг - мм_гггг)**** | BY9: Ответственный исполнитель | BZ9: Передано на исполнение в филиал (дата и номер Распоряжения)
AE10: Номер / Планируемый ** | AF10: Дата /Планируемый** | AI10: 1 кв-л по оплате | AL10: 2 кв-л по оплате | AO10: 3 кв-л по оплате | AR10: 4 кв-л по оплате | AU10: Итого | AV10: Ключевые показатели эффективности (КПЭ) цифровой трансформации***** | BB10: 1-й плановый год | BC10: Ключевые показатели эффективности (КПЭ) цифровой трансформации***** | BI10: 2-й плановый год | BJ10: Ключевые показатели эффективности (КПЭ) цифровой трансформации***** | BP10: последующие годы | BQ10: Ключевые показатели эффективности (КПЭ) цифровой трансформации*****
D11: ОО | E11: YYYY | F11: К | G11: XXX.X | H11: FFFF | I11: BBB | J11: CCC | K11: GG | L11: HH | M11: DD.EEEE | AI11: январь | AJ11: февраль | AK11: март | AL11: апрель | AM11: май | AN11: июнь | AO11: июль | AP11: август | AQ11: сентябрь | AR11: октябрь | AS11: ноябрь | AT11: декабрь | AV11: КПЭ 17 | AW11: КПЭ 23 | AX11: КПЭ 19 | AY11: КПЭ 26 | AZ11: КПЭ 20 | BA11: КПЭ 22 | BC11: КПЭ 17 | BD11: КПЭ 23 | BE11: КПЭ 19 | BF11: КПЭ 26 | BG11: КПЭ 20 | BH11: КПЭ 22 | BJ11: КПЭ 17 | BK11: КПЭ 23 | BL11: КПЭ 19 | BM11: КПЭ 26 | BN11: КПЭ 20 | BO11: КПЭ 22 | BQ11: КПЭ 17 | BR11: КПЭ 23 | BS11: КПЭ 19 | BT11: КПЭ 26 | BU11: КПЭ 20 | BV11: КПЭ 22
A12: 1 | B12: * | C12: * | D12: * | E12: * | F12: * | G12: * | H12: * | I12: * | J12: * | K12: * | L12: * | M12: * | N12: * | O12: * | P12: * | Q12: 2 | R12: * | S12: * | T12: * | U12: * | V12: * | W12: * | X12: * | Y12: 3 | Z12: * | AA12: * | AB12: * | AC12: * | AD12: 4 | AE12: 5.1. | AF12: 5.2. | AG12: 6 | AH12: 7 | AI12: * | AJ12: * | AK12: * | AL12: * | AM12: * | AN12: * | AO12: * | AP12: * | AQ12: * | AR12: * | AS12: * | AT12: * | AU12: 8 | AV12: * | AW12: * | AX12: * | AY12: * | AZ12: * | BA12: * | BB12: 9 | BC12: * | BD12: * | BE12: * | BF12: * | BG12: * | BH12: * | BI12: 10 | BJ12: * | BK12: * | BL12: * | BM12: * | BN12: * | BO12: * | BP12: 11 | BQ12: * | BR12: * | BS12: * | BT12: * | BU12: * | BV12: * | BW12: 12 | BX12: 13 | BY12: 14 | BZ12: *
R13: выбор из выпадающего списка | S13: выбор из выпадающего списка | T13: выбор из выпадающего списка | U13: выбор из выпадающего списка | Y13: ИТОГО: | AG13: 0 | AH13: 0 | AU13: 0
A14: <Наименование раздела плана> | R14: Наблюдение (УИП 2) | S14: Раздел | T14: Раздел | U14: Раздел | V14: Раздел | Y14: действующие договоры | AG14: 0 | AH14: 0 | AU14: 0
R15: Наблюдение (УИП 2) | S15: выбор из выпадающего списка | T15: выбор из выпадающего списка | U15: выбор из выпадающего списка | Y15: планируемые к заключению договоры | AG15: 0 | AH15: 0 | AU15: 0
R16: Хоз деятельность (УИП 6 Прочее) | S16: Подраздел | T16: Подраздел | U16: Подраздел | V16: Подраздел
A17: <Наименование подраздела плана> | S17: выбор из выпадающего списка | T17: выбор из выпадающего списка | U17: выбор из выпадающего списка
C18: =RIGHT(D18,2)&"."&E18&"."&F18&"."&G18&"."&H18&"."&I18&"."&J18&"."&K18&"."&L18&"."&M18&"" -> ......... | S18: выбор из выпадающего списка | T18: выбор из выпадающего списка | U18: выбор из выпадающего списка | Y18: ВСЕГО ПО РАЗДЕЛУ: | AG18: =SUM(AG19:AG21) -> 0 | AH18: =SUM(AH19:AH21) -> 0 | AU18: =SUM(AU19:AU21) -> 0
C19: =RIGHT(D19,2)&"."&E19&"."&F19&"."&G19&"."&H19&"."&I19&"."&J19&"."&K19&"."&L19&"."&M19&"" -> ...11.0130...... | G19: 11.0130 | S19: выбор из выпадающего списка | T19: выбор из выпадающего списка | U19: выбор из выпадающего списка
S20: выбор из выпадающего списка | T20: выбор из выпадающего списка | U20: выбор из выпадающего списка
A23: <Наименование раздела плана>
Y24: ВСЕГО ПО РАЗДЕЛУ: | AG24: =SUM(AH25:AH27) -> 0 | AH24: =SUM(AQ25:AQ27) -> 0 | AU24: =SUM(AR25:AR27) -> 0
A26: <Наименование подраздела плана>
A30: ПРИМЕЧАНИЕ
A31: * колонки в печатную форму не включаются.
A32: ** если договор еще не заключен, то в колонках 5.1. и 5.2. пишется "Планируемый"
A33: ***Срок реализации мероприятия/этапа (мм_гггг -мм_гггг, мм-месяц, гггг-год) | U33: период с начала закупочных процедур до полной оплаты
A34: ****Период выполнения обязательств по договору (мм_гггг - мм_гггг) | U34: период выполнения работ/оказания услуг (ожидаемый период выполнения работ/за какой период мы платим)
A35: ***** заполнятся на основании заявок на мероприятия в централизованный план в соответствии с приложениями к Приложению № 3 и Приложению № 3.3,а также изменений согласно приложению к Приложению № 7

Sheet Пр5а Перечень тематик НИОКР
B3: ПРИЛОЖЕНИЕ №5а К ПОРЯДКУ ТЕКУЩЕГО ПЛАНИРОВАНИЯ ПРОИЗВОДСТВЕННО-ХОЗЯЙСТВЕННОЙ ДЕЯТЕЛЬНОСТИ ФГУП «ГОСКОРПОРАЦИЯ ПО ОрВД»
B5: Приложение к Плану научно-исследовательских и опытно-конструкторских работ ФГУП «Госкорпорация по ОрВД» на ____ год
B6: Перечень тематик НИОКР, планируемых к выполнению в _____ году
A7: № п/п | B7: Наименование тематик
A8: 1.
A9: 2.
A10: …

Sheet Пр 6 план 4
AJ2: ПРИЛОЖЕНИЕ № 6
AJ3: К ПОРЯДКУ ТЕКУЩЕГО ПЛАНИРОВАНИЯ ПРОИЗВОДСТВЕННО-ХОЗЯЙСТВЕННОЙ ДЕЯТЕЛЬНОСТИ ФГУП «ГОСКОРПОРАЦИЯ ПО ОрВД»
A6: План мероприятий (по планам 4 группы) ФГУП "Госкорпорация по ОрВД" на ____ год
A7: наименование плана
A8: тыс.руб.
A9: № п/п | B9: КИП | C9: КМ | D9: Год инициации | E9: Порядковый номер | F9: Код инициатора мероприятия =1-ГК, =2-филиал | G9: Код Плана (Пр. 1) | H9: Территориальный код этапа мероприятия | I9: Код места установки | J9: Объект, средство, система | K9: Тип этапа (Пр. 27) | L9: Порядковый номер этапа мероприятия | M9: Номер раздела/подраздела (Пр 2а) | N9: Филиал | O9: Краткое наименование мероприятия | P9: Наименование мероприятия | Q9: Место реализации | R9: Год инициации мероприятия | S9: Срок реализации мероприятия/этапа (мм_гггг -мм_гггг, мм-месяц, гггг-год)*** | T9: Реквизиты договора | V9: Стоимость мероприятия (этапа) планируемая | W9: Платежи текущего финансового года | AJ9: Платежи последующих периодов | AM9: Планируемая дата заключения договора | AN9: Ответственный исполнитель ГД | AO9: Передано на исполнение в филиал (дата и номер Распоряжения)
W10: 1 кв-л по оплате | Z10: 2 кв-л по оплате | AC10: 3 кв-л по оплате | AF10: 4 кв-л по оплате | AI10: Итого
D11: ОО | E11: YYYY | F11: К | G11: XXX.X | H11: FFFF | I11: BBB | J11: CCC | K11: GG | L11: HH | M11: DD.EEEE | T11: Номер / Планируемый ** | U11: Дата /Планируемый** | W11: январь | X11: февраль | Y11: март | Z11: апрель | AA11: май | AB11: июнь | AC11: июль | AD11: август | AE11: сентябрь | AF11: октябрь | AG11: ноябрь | AH11: декабрь | AJ11: 1-й плановый год | AK11: 2-й плановый год | AL11: последующие годы
A12: 1 | B12: * | C12: * | D12: * | E12: * | F12: * | G12: * | H12: * | I12: * | J12: * | K12: * | L12: * | M12: * | N12: 2 | O12: * | P12: 3 | Q12: * | R12: * | S12: 4 | T12: 5.1. | U12: 5.2. | V12: 6 | W12: * | X12: * | Y12: * | Z12: * | AA12: * | AB12: * | AC12: * | AD12: * | AE12: * | AF12: * | AG12: * | AH12: * | AI12: 8 | AJ12: 9 | AK12: 10 | AL12: 11 | AM12: 12 | AN12: 13 | AO12: *
P13: ИТОГО: | V13: 0
P14: действующие договоры | V14: 0
P15: планируемые к заключению договоры | V15: 0
A16: <Наименование раздела плана>
P17: ВСЕГО ПО РАЗДЕЛУ: | V17: =SUM(V18:V18) -> 0
A21: ПРИМЕЧАНИЕ
A22: * колонки в печатную форму не включаются.
A23: ** если договор еще не заключен, то в колонках 5.1. и 5.2. пишется "Планируемый"
A24: ***Срок реализации мероприятия (мм_гггг -мм_гггг, мм-месяц, гггг-год) | U24: период с начала закупочных процедур до полной оплаты

Sheet Пр 7 изм. в план
BP1: ПРИЛОЖЕНИЕ № 7
BP2: К ПОРЯДКУ ТЕКУЩЕГО ЭКОНОМИЧЕСКОГО ПЛАНИРОВАНИЯ ПРОИЗВОДСТВЕННО-ХОЗЯЙСТВЕННОЙ ДЕЯТЕЛЬНОСТИ ФГУП «ГОСКОРПОРАЦИЯ ПО ОрВД»
A3: Федеральное агентство воздушного транспорта
A4: (РОСАВИАЦИЯ)
A5: Федеральное государственное унитарное предприятие
A6: "ГОСУДАРСТВЕННАЯ КОРПОРАЦИЯ ПО ОРГАНИЗАЦИИ ВОЗДУШНОГО ДВИЖЕНИЯ В РОССИЙСКОЙ ФЕДЕРАЦИИ"
A7: (ФГУП "Госкорпорация по ОрВД")
BP8: УТВЕРЖДАЮ
BP9: Генеральный директор
BP10: ФГУП "Госкорпорация по ОрВД"
BP11: ________________
AD12: ИЗМЕНЕНИЕ № ____________________
AE13: в планы 1 - 3 группы
AE14: наименование плана
A16: Обоснование внесения изменений:
A17: Инициатор:
BZ18: тыс. руб.
A19: № | B19: КИП | C19: КМ | D19: Год инициации | E19: Порядковый номер | F19: Код инициатора мероприятия =1-ГК, =2-филиал | G19: Код Плана (Пр. 1) | H19: Территориальный код этапа мероприятия | I19: Код места установки | J19: Объект, средство, система | K19: Тип этапа (Пр. 27) | L19: Порядковый номер этапа мероприятия | M19: Номер раздела/подраздела (Пр 2а) | N19: Статья ВПО | O19: КУУ | P19: КВУ | Q19: Филиал | R19: Номер УИПа | S19: Номер показателя ПДП (справочник) | T19: Наименование показателя Ипр (справочник) | U19: Номер поручения ФОИВ (справочник) | V19: Признак инновационности мероприятия (да/нет) | W19: Статус мероприятия (закрыто/исполняется) | X19: Наименование мероприятия | Y19: Краткое наименование мероприятия | Z19: Относится к Стратегии цифровой трансформации (да/нет)*** | AA19: Место реализации | AB19: Наименование оборудования / ОС / НМА/Воздушного судна | AC19: Наименование этапа (вид работ) | AD19: Срок начала реализации мероприятия/этапа (мм_гггг -мм_гггг, мм-месяц, гггг-год) | AE19: Реквизиты договора | AG19: Стоимость мероприятия (этапа) планируемая | AH19: Финансирование по договору по состоянию на 01.01.___ | AJ19: Платежи текущего финансового года | BB19: Платежи последующих периодов | BW19: Планируемая дата заключения контракта (договора) | BX19: Период выполнения обязательств по договору (для текущих расходов) (мм_гггг - мм_гггг) | BY19: Ответственный исполнитель | BZ19: Причины внесения изменений
AI20: 1 кв-л | AL20: 2 кв-л | AO20: 3 кв-л | AR20: 4 кв-л | AU20: Итого | AV20: Ключевые показатели эффективности (КПЭ) цифровой трансформации***** | BB20: 1-й плановый год | BC20: Ключевые показатели эффективности (КПЭ) цифровой трансформации***** | BI20: 2-й плановый год | BJ20: Ключевые показатели эффективности (КПЭ) цифровой трансформации***** | BP20: последующие годы | BQ20: Ключевые показатели эффективности (КПЭ) цифровой трансформации*****
D21: ОО | E21: YYYY | F21: К | G21: XXX.X | H21: FFFF | I21: BBB | J21: CCC | K21: GG | L21: HH | M21: DD.EEEE | AE21: Номер договора/планируемый | AF21: Дата договора/планируемый | AI21: январь | AJ21: февраль | AK21: март | AL21: апрель | AM21: май | AN21: июнь | AO21: июль | AP21: август | AQ21: сентябрь | AR21: октябрь | AS21: ноябрь | AT21: декабрь | AV21: КПЭ 17 | AW21: КПЭ 23 | AX21: КПЭ 19 | AY21: КПЭ 26 | AZ21: КПЭ 20 | BA21: КПЭ 22 | BC21: КПЭ 17 | BD21: КПЭ 23 | BE21: КПЭ 19 | BF21: КПЭ 26 | BG21: КПЭ 20 | BH21: КПЭ 22 | BJ21: КПЭ 17 | BK21: КПЭ 23 | BL21: КПЭ 19 | BM21: КПЭ 26 | BN21: КПЭ 20 | BO21: КПЭ 22 | BQ21: КПЭ 17 | BR21: КПЭ 23 | BS21: КПЭ 19 | BT21: КПЭ 26 | BU21: КПЭ 20 | BV21: КПЭ 22
A22: 1 | B22: * | C22: * | D22: * | E22: * | F22: * | G22: * | H22: * | I22: * | J22: * | K22: * | L22: * | M22: * | N22: * | O22: * | P22: * | Q22: 2 | R22: * | S22: * | T22: * | U22: * | V22: * | W22: * | X22: 3 | Y22: * | Z22: * | AA22: * | AB22: * | AC22: * | AD22: 4 | AE22: 5.1. | AF22: 5.2. | AG22: 6 | AH22: 7 | AI22: 8.1. | AJ22: 8.2. | AK22: 8.3. | AL22: 8.4. | AM22: 8.5. | AN22: 8.6. | AO22: 8.7. | AP22: 8.8. | AQ22: 8.9. | AR22: 8.10. | AS22: 8.11. | AT22: 8.12. | AU22: 8.13. | AV22: * | AW22: * | AX22: * | AY22: * | AZ22: * | BA22: * | BB22: 9 | BC22: * | BD22: * | BE22: * | BF22: * | BG22: * | BH22: * | BI22: 10 | BJ22: * | BK22: * | BL22: * | BM22: * | BN22: * | BO22: * | BP22: 11 | BQ22: * | BR22: * | BS22: * | BT22: * | BU22: * | BV22: * | BW22: 12 | BX22: * | BY22: 13 | BZ22: 14
R23: выбор из выпадающего списка | S23: выбор из выпадающего списка | T23: выбор из выпадающего списка | U23: выбор из выпадающего списка
A24: Принять мероприятие(я) в новой редакции:
A25: Старая редакция
R26: Наблюдение (УИП 2) | S26: Раздел | T26: Раздел | U26: Раздел | V26: Раздел
R27: Наблюдение (УИП 2) | S27: выбор из выпадающего списка | T27: выбор из выпадающего списка | U27: выбор из выпадающего списка
S28: Подраздел | T28: Подраздел | U28: Подраздел | V28: Подраздел
S29: выбор из выпадающего списка | T29: выбор из выпадающего списка | U29: выбор из выпадающего списка
A30: Новая редакция
A34: Исключить мероприятие(я):
A38: Включить мероприятие(я):
A42: ПРИМЕЧАНИЕ
A43: * колонки в печатную форму не включаются.
A44: ** если договор еще не заключен, то в колонках 5.1. и 5.2. пишется "Планируемый"
A45: *** в колонке "Относится к Стратегии цифровой трансформации (да/нет)" проставляется признак "да" в случае отнесения меропрития к СЦТ и "нет" - в случае, если мероприятие не относится к СЦТ.
A46: ****заполнятся в случае отнесения мероприятия к Стратегии цифровой трансформации при проставлении признака "да" на основании приложения к Приложению № 7

Sheet Приложение к Пр 7 изм
Y1: ПРИЛОЖЕНИЕ К ПРИЛОЖЕНИЮ № 7
Y2: К ПОРЯДКУ ТЕКУЩЕГО ПЛАНИРОВАНИЯ ПРОИЗВОДСТВЕННО-ХОЗЯЙСТВЕННОЙ ДЕЯТЕЛЬНОСТИ ФГУП «ГОСКОРПОРАЦИЯ ПО ОрВД»
A3: Приложение к изменению___№ в планы 1 - 3 группы *
AI4: тыс. рублей
A5: № п/п | B5: КМ | C5: № инициативы СЦТ | D5: Код мероприятия | E5: Наименование мероприятия | F5: Номер договора и дата/планируемый | G5: Стоимость мероприятия (этапа) планируемая | H5: Лимит финансирования на ____ год, в т.ч. | I5: Текущий год | O5: Платежи последующих периодов
O6: 1-й плановый год | V6: 2-й плановый год | AC6: последующие годы
I7: Ключевые показатели эффективности (КПЭ) цифровой трансформации** | O7: Итого | P7: Ключевые показатели эффективности (КПЭ) цифровой трансформации** | V7: Итого | W7: Ключевые показатели эффективности (КПЭ) цифровой трансформации** | AC7: Итого | AD7: Ключевые показатели эффективности (КПЭ) цифровой трансформации**
I8: КПЭ 17 | J8: КПЭ 23 | K8: КПЭ 19 | L8: КПЭ 26 | M8: КПЭ 20 | N8: КПЭ 22 | P8: КПЭ 17 | Q8: КПЭ 23 | R8: КПЭ 19 | S8: КПЭ 26 | T8: КПЭ 20 | U8: КПЭ 22 | W8: КПЭ 17 | X8: КПЭ 23 | Y8: КПЭ 19 | Z8: КПЭ 26 | AA8: КПЭ 20 | AB8: КПЭ 22 | AD8: КПЭ 17 | AE8: КПЭ 23 | AF8: КПЭ 19 | AG8: КПЭ 26 | AH8: КПЭ 20 | AI8: КПЭ 22
A9: 1 | C9: 2 | D9: 3 | E9: 4 | F9: 5 | G9: 6 | H9: 7 | I9: 8 | J9: 9 | K9: 11 | L9: 12 | M9: 13 | N9: 14 | O9: 15 | P9: 16 | Q9: 17 | R9: 19 | S9: 20 | T9: 21 | U9: 22 | V9: 23 | W9: 24 | X9: 25 | Y9: 27 | Z9: 28 | AA9: 29 | AB9: 30 | AC9: 31 | AD9: 32 | AE9: 33 | AF9: 35 | AG9: 36 | AH9: 37 | AI9: 38
A10: 1 | C10: 1 | E10: Мероприятие 1 | F10: № ___ от _____ | G10: =H10+O10+V10+AC10 -> 500000 | H10: =SUM(I10:N10) -> 100000 | I10: =SUM(I11:I15) -> 30000 | J10: 20000 | K10: =SUM(K11:K15) -> 30000 | L10: =SUM(L11:L15) -> 20000 | M10: =SUM(M11:M15) -> 0 | N10: =SUM(N11:N15) -> 0 | O10: =SUM(P10:U10) -> 100000 | P10: =SUM(P11:P15) -> 30000 | Q10: =SUM(Q11:Q15) -> 20000 | R10: =SUM(R11:R15) -> 30000 | S10: =SUM(S11:S15) -> 20000 | T10: =SUM(T11:T15) -> 0 | U10: =SUM(U11:U15) -> 0 | V10: =SUM(W10:AB10) -> 100000 | W10: =SUM(W11:W15) -> 30000 | X10: =SUM(X11:X15) -> 20000 | Y10: =SUM(Y11:Y15) -> 30000 | Z10: =SUM(Z11:Z15) -> 20000 | AA10: =SUM(AA11:AA15) -> 0 | AB10: =SUM(AB11:AB15) -> 0 | AC10: =SUM(AD10:AI10) -> 200000 | AD10: =SUM(AD11:AD15) -> 0 | AE10: =SUM(AE11:AE15) -> 0 | AF10: =SUM(AF11:AF15) -> 100000 | AG10: =SUM(AG11:AG15) -> 100000 | AH10: =SUM(AH11:AH15) -> 0 | AI10: =SUM(AI11:AI15) -> 0
C11: 1 | E11: Код ОКПД2 | I11: 30000 | P11: 30000 | W11: 30000
C12: 1 | E12: Код ОКПД2 | J12: 20000 | Q12: 20000 | X12: 20000
C13: 1 | E13: Код ОКПД2 | K13: 20000 | R13: 30000 | AF13: 100000
C14: 1 | E14: Код ОКПД2 | K14: 10000 | Y14: 30000
C15: 1 | E15: Код ОКПД2 | L15: 20000 | S15: 20000 | Z15: 20000 | AG15: 100000
A16: 2 | C16: 3 | E16: Мероприятие 2 | F16: Планируемый | G16: =H16+O16+V16+AC16 -> 30000 | H16: =SUM(H17) -> 30000 | I16: =SUM(I17) -> 0 | K16: 0 | M16: 0 | N16: =SUM(N17) -> 30000 | O16: =SUM(P16:U16) -> 0 | P16: =SUM(P17) -> 0 | R16: =SUM(R17) -> 0 | T16: =SUM(T17) -> 0 | U16: =SUM(U17) -> 0 | V16: =W16+Y16+AA16+AB16 -> 0 | W16: =SUM(W17) -> 0 | Y16: =SUM(Y17) -> 0 | AA16: =SUM(AA17) -> 0 | AB16: =SUM(AB17) -> 0 | AC16: =SUM(AD16:AI16) -> 0 | AD16: =SUM(AD17) -> 0 | AF16: =SUM(AF17) -> 0 | AH16: =SUM(AH17) -> 0 | AI16: =SUM(AI17) -> 0
C17: 3 | E17: Код ОКПД2 | G17: =H17+O17+V17+AC17 -> 30000 | H17: =I17+K17+M17+N17 -> 30000 | I17: 0 | K17: 0 | M17: 0 | N17: 30000 | O17: =SUM(P17:U17) -> 0 | P17: 0 | R17: 0 | T17: 0 | U17: 0 | V17: 0 | W17: 0 | Y17: 0 | AA17: 0 | AB17: 0 | AC17: 0 | AD17: 0 | AF17: 0 | AH17: 0 | AI17: 0
A18: 3 | C18: 6 | E18: Мероприятие 3 | F18: Планируемый | G18: =H18+O18+V18+AC18 -> 200000 | H18: =I18+K18+M18+N18 -> 70000 | I18: =SUM(I19) -> 0 | K18: =SUM(K19) -> 0 | M18: =SUM(M19) -> 70000 | N18: =SUM(N19) -> 0 | O18: =P18+R18+T18+U18 -> 100000 | P18: =SUM(P19) -> 100000 | R18: =SUM(R19) -> 0 | T18: =SUM(T19) -> 0 | U18: =SUM(U19) -> 0 | V18: 30000 | W18: =SUM(W19) -> 0 | Y18: =SUM(Y19) -> 0 | AA18: =SUM(AA19) -> 0 | AB18: =SUM(AB19) -> 0 | AC18: =AD18+AF18+AH18+AI18 -> 0 | AD18: =SUM(AD19) -> 0 | AF18: =SUM(AF19) -> 0 | AH18: =SUM(AH19) -> 0 | AI18: =SUM(AI19) -> 0
C19: 6 | E19: Код ОКПД2 | G19: =H19+O19+V19+AC19 -> 170000 | H19: =I19+K19+M19+N19 -> 70000 | I19: 0 | K19: 0 | M19: 70000 | N19: 0 | O19: =P19+R19+T19+U19 -> 100000 | P19: 100000 | R19: 0 | T19: 0 | U19: 0 | V19: =W19+Y19+AA19+AB19 -> 0 | W19: 0 | Y19: 0 | AA19: 0 | AB19: 0 | AC19: =AD19+AF19+AH19+AI19 -> 0 | AD19: 0 | AF19: 0 | AH19: 0 | AI19: 0
A20: N
A22: * Приложение заполняется только в том случае , если мероприятие относится к Стратегии цифровой трансформации (СЦТ)
A23: ** Определяются в соответствии с общероссийским классификатором по видам экономической деятельности (ОКПД2).
A24: В гр.2 указывается № инициативы СЦТ в соответсвии с утвержденной СЦТ ФГУП «Госкорпорация по ОрВД» до 2030 года и действующей редакцией методических рекомендаций по цифровой трансформации государственных корпораций и компаний с государственным участием (приложение №3)
A25: Сумма КПЭ: по гр. 8-14 должна быть равна лимиту финансирования текущего года, отраженному в гр. 7; по гр. 16-22 должна быть равна лимиту 1-го планового года, отраженному в гр. 15; по гр. 24-30 должна быть равна лимиту 2-го планового года, отраженному в гр. 23; по гр. 32-38 должна быть равна лимиту последующих годов, отраженному в гр. 31;
A26: Гр. 6 равна сумме гр. 7, 15,23,31
A27: В гр. 8; гр. 16; гр. 24; гр.32 (КПЭ 17 -"Увеличение вложений в российские решения в сфере информационных технологий")- указывается объем расходов на российское ПО, включенное в Единый реестр российских программ для электронных вычислительных машин и баз данных или в Единый реестр программ для электронных вычислительных машин и баз данных государств - членов Евразийского экономического союза, и связанные с ним работы (услуги). В случае если ПО является свободно распространяемым, но сведения о таком программном обеспечении не включены в Единый реестр российского ПО, то такое ПО относится к иностранному ПО и заполняются гр. 9; гр. 17; гр. 25; гр.33 в соответствующем периоде;
A28: В гр. 9, гр.17, гр. 25, гр. 33 (КПЭ 23 " Увеличение расходов на информационные технологии") - указывается объем расходов на иностранное ПО и связанные с ним работы (услуги).
A29: В гр. 11; гр. 19; гр. 27; гр.35 (КПЭ 19 "Увеличение вложений в радиоэлектронную продукцию российского происхождения, в том числе в телекоммуникационное оборудование и программно-аппаратные комплексы"- указывается объем расходов государственной компании на радиоэлектронную продукцию российского происхождения, в том числе телекоммуникационное оборудование и программно-аппаратные комплексы. Под радиоэлектронной продукцией российского происхождения понимается радиоэлектронная продукция, сведения о которой включены в реестр российской промышленной продукции (согласно постановлению Правительства Российской Федерации от 17.07.2015 N 719). Также включаются расходы на радиоэлектронную продукцию, которая включена в евразийский реестр промышленных товаров государств - членов Евразийского экономического союза. В данные графы не включаются расходы на работы (услуги), связанные с радиоэлектронной продукцией. Указанные затраты отражаются в гр. 12,гр.20,гр.28, гр. 36 в соответствующем периоде.
A30: В гр. 12; гр. 20; гр. 28; гр.36 (КПЭ 26 "Увеличение расходов, направленных на закупку радиоэлектронной продукции, телекоммуникационного оборудования и программно-аппаратных комплексов, а также связанных с ней работ (услуг)") - указывается объем расходов государственной компании на радиоэлектронную продукцию иностранного производства, в том числе телекоммуникационное оборудование и программно-аппаратные комплексы, а также связанные с ней работы (услуги), а также работы (услуги) связанные с приобретением радиоэлектронной продукции российского производства.
A31: В гр. 13; гр. 21; гр. 29; гр.37 (КПЭ 20 "Объем затрат на исследования и разработки, направленных на создание и развитие передовых и критически важных для отрасли цифровых технологий и решений, в том числе новых производственных технологий, связанных с интенсивным применением информационно-коммуникационных технологий в рамках реализации инициатив (проектов) СЦТ") - указывается объем затрат на научные исследования и разработки (НИОКР), направленных на создание и развитие передовых и критически важных для отрасли цифровых технологий и решений, в том числе новых производственных технологий, связанных с интенсивным применением информационно-коммуникационных технологий.
A32: В гр. 13; гр. 21; гр. 29; гр.37 (КПЭ 22 "Объем расходов государственных компаний на реализацию инициатив (мероприятий), связанных с созданием, внедрением и применением технологий и решений в сфере искусственного интеллекта") - указываются расходы связанные с технологиями и решениями в сфере искусственного интеллекта.

Sheet Пр 7а изм. в план
AJ1: ПРИЛОЖЕНИЕ № 7а
AJ2: К ПОРЯДКУ ТЕКУЩЕГО ПЛАНИРОВАНИЯ ПРОИЗВОДСТВЕННО-ХОЗЯЙСТВЕННОЙ ДЕЯТЕЛЬНОСТИ ФГУП «ГОСКОРПОРАЦИЯ ПО ОрВД»
AJ6: УТВЕРЖДАЮ
AJ7: Генеральный директор
AJ8: ФГУП "Госкорпорация по ОрВД"
AJ9: ________________
S10: ИЗМЕНЕНИЕ № ____________________
T11: в централизованные планы 4 группы
T12: наименование плана
A13: Обоснование внесения изменений:
A14: Инициатор:
AM15: тыс.руб.
A16: № п/п | B16: КИП | C16: КМ | D16: Год инициации | E16: Порядковый номер | F16: Код инициатора мероприятия =1-ГК, =2-филиал | G16: Код Плана (Пр. 1) | H16: Территориальный код этапа мероприятия | I16: Код места установки | J16: Объект, средство, система | K16: Тип этапа (Пр. 27) | L16: Порядковый номер этапа мероприятия | M16: Номер раздела/подраздела (Пр 2а) | N16: Филиал | O16: Краткое наименование мероприятия | P16: Наименование мероприятия | Q16: Место реализации | R16: Год инициации мероприятия | S16: Срок начала реализации мероприятия/этапа (мм_гггг -мм_гггг, мм-месяц, гггг-год) | T16: Реквизиты договора | V16: Стоимость мероприятия (этапа) планируемая | W16: Платежи текущего финансового года | AJ16: Платежи последующих периодов | AM16: Планируемая дата заключения договора | AN16: Ответственный исполнитель ГД | AO16: Передано на исполнение в филиал (дата и номер Распоряжения)
D17: ОО | E17: YYYY | F17: К | G17: XXX.X | H17: FFFF | I17: BBB | J17: CCC | K17: GG | L17: HH | M17: DD.EEEE | T17: Номер / Планируемый ** | U17: Дата /Планируемый** | W17: 1 кв-л по оплате | Z17: 2 кв-л по оплате | AC17: 3 кв-л по оплате | AF17: 4 кв-л по оплате | AI17: Итого
W18: январь | X18: февраль | Y18: март | Z18: апрель | AA18: май | AB18: июнь | AC18: июль | AD18: август | AE18: сентябрь | AF18: октябрь | AG18: ноябрь | AH18: декабрь | AJ18: 1-й плановый год | AK18: 2-й плановый год | AL18: последующие годы
A19: 1 | B19: * | C19: * | D19: * | E19: * | F19: * | G19: * | H19: * | I19: * | J19: * | K19: * | L19: * | M19: * | N19: 2 | O19: * | P19: 3 | Q19: * | R19: * | S19: 4 | T19: 5.1. | U19: 5.2. | V19: 6 | W19: * | X19: * | Y19: * | Z19: * | AA19: * | AB19: * | AC19: * | AD19: * | AE19: * | AF19: * | AG19: * | AH19: * | AI19: 7 | AJ19: 8 | AK19: 9 | AL19: 10 | AM19: 11 | AN19: 13 | AO19: *
A21: Принять мероприятие(я) в новой редакции:
A22: Старая редакция
A24: Новая редакция
A28: ПРИМЕЧАНИЕ
A29: * колонки в печатную форму не включаются.
A30: ** если договор еще не заключен, то в колонках 5.1. и 5.2. пишется "Планируемый"

Sheet Пр 8 ЦВПО
O1: ПРИЛОЖЕНИЕ № 8
O2: К ПОРЯДКУ ТЕКУЩЕГО ПЛАНИРОВАНИЯ ПРОИЗВОДСТВЕННО-ХОЗЯЙСТВЕННОЙ ДЕЯТЕЛЬНОСТИ ФГУП «ГОСКОРПОРАЦИЯ ПО ОрВД»
H3: План возникновения и погашения обязательств по централизованным договорам и резервам
H4: на_________________год
G5: по состоянию на __________________
F6: (1-й квартал, 1-е полугодие, 9 месяцев, год)
A7: № статьи ВПО | B7: Наименование статьи | C7: сальдо обяза-тельств на начало года | D7: в т. ч. по кварталам | S7: ИТОГО | V7: сальдо обяза-тельств на конец года
D8: 1 кв-л | H8: 2 кв-л | L8: 3 кв-л | P8: 4 кв-л | S8: за год
D9: план/факт/прогноз | H9: план/факт/прогноз | L9: план/факт/прогноз | P9: план/прогноз
D10: по начис-лению | E10: по оплате | F10: неденеж-ные измене-ния | G10: сальдо задолженности | H10: план по начислению | I10: план по оплате | J10: неденеж-ные измене-ния | K10: сальдо задолженности | L10: план по начис-лению | M10: план по оплате | N10: неденеж-ные измене-ния | O10: сальдо задолженности | P10: план по начис-лению | Q10: план по оплате | R10: неденеж-ные измене-ния | S10: план по начислению | T10: план по оплате | U10: неденеж-ные измене-ния
A11: 1 | B11: 2 | C11: 3 | D11: 4 | E11: 5 | F11: 6 | G11: 7 | H11: 8 | I11: 9 | J11: 10 | K11: 11 | L11: 12 | M11: 13 | N11: 14 | O11: 15 | P11: 16 | Q11: 17 | R11: 18 | S11: 19 | T11: 20 | U11: 21 | V11: 22
A12: 01000 | B12: Входящий остаток денежных средств | C12: Х | D12: Х | F12: Х | G12: Х | H12: Х | I12: =E114 -> 0 | J12: Х | K12: Х | L12: Х | M12: =I114 -> 0 | N12: Х | O12: Х | P12: Х | Q12: =M114 -> 0 | R12: Х | S12: Х | T12: 0 | U12: Х | V12: Х
A13: 10000 | B13: ДОХОДЫ (10100+10200+10400+10500+10600+10700) | C13: =C14+C19+C36+C39+C44+C48 -> 0 | D13: =D14+D19+D36+D39+D44+D48 -> 0 | E13: =E14+E19+E36+E39+E44+E48 -> 0 | F13: =F14+F19+F36+F39+F44+F48 -> 0 | G13: =C13+D13-E13-F13 -> 0 | H13: =H14+H19+H36+H39+H44+H48 -> 0 | I13: =I14+I19+I36+I39+I44+I48 -> 0 | J13: =J14+J19+J36+J39+J44+J48 -> 0 | K13: =G13+H13-I13-J13 -> 0 | L13: =L14+L19+L36+L39+L44+L48 -> 0 | M13: =M14+M19+M36+M39+M44+M48 -> 0 | N13: =N14+N19+N36+N39+N44+N48 -> 0 | O13: =K13+L13-M13-N13 -> 0 | P13: =P14+P19+P36+P39+P44+P48 -> 0 | Q13: =Q14+Q19+Q36+Q39+Q44+Q48 -> 0 | R13: =R14+R19+R36+R39+R44+R48 -> 0 | S13: =S14+S19+S36+S39+S44+S48 -> 0 | T13: =T14+T19+T36+T39+T44+T48 -> 0 | U13: =U14+U19+U36+U39+U44+U48 -> 0 | V13: =O13+P13-Q13-R13 -> 0
A14: 10100 | B14: Выручка по обычным видам деятельности всего, в т.ч. | C14: =SUM(C15:C18) -> 0 | D14: =SUM(D15:D18) -> 0 | E14: =SUM(E15:E18) -> 0 | F14: =SUM(F15:F18) -> 0 | G14: =C14+D14-E14-F14 -> 0 | H14: =SUM(H15:H18) -> 0 | I14: =SUM(I15:I18) -> 0 | J14: =SUM(J15:J18) -> 0 | K14: =G14+H14-I14-J14 -> 0 | L14: =SUM(L15:L18) -> 0 | M14: =SUM(M15:M18) -> 0 | N14: =SUM(N15:N18) -> 0 | O14: =K14+L14-M14-N14 -> 0 | P14: =SUM(P15:P18) -> 0 | Q14: =SUM(Q15:Q18) -> 0 | R14: =SUM(R15:R18) -> 0 | S14: =SUM(S15:S17) -> 0 | T14: =SUM(T15:T17) -> 0 | U14: =SUM(U15:U17) -> 0 | V14: =SUM(V15:V17) -> 0
A15: 10110 | B15: от АНО на маршрутах обслуживания воздушного движения | G15: =C15+D15-E15-F15 -> 0 | K15: =G15+H15-I15-J15 -> 0 | O15: =K15+L15-M15-N15 -> 0 | S15: =D15+H15+L15+P15 -> 0 | T15: =E15+I15+M15+Q15 -> 0 | U15: =F15+J15+N15+R15 -> 0 | V15: =O15+P15-Q15 -> 0
A16: 10120 | B16: от АНО в районах аэродромов | G16: =C16+D16-E16-F16 -> 0 | K16: =G16+H16-I16-J16 -> 0 | O16: =K16+L16-M16-N16 -> 0 | S16: =D16+H16+L16+P16 -> 0 | T16: =E16+I16+M16+Q16 -> 0 | U16: =F16+J16+N16+R16 -> 0 | V16: =O16+P16-Q16 -> 0
A17: 10140 | B17: от прочей деятельности | G17: =C17+D17-E17-F17 -> 0 | K17: =G17+H17-I17-J17 -> 0 | O17: =K17+L17-M17-N17 -> 0 | S17: =D17+H17+L17+P17 -> 0 | T17: =E17+I17+M17+Q17 -> 0 | U17: =F17+J17+N17+R17 -> 0 | V17: =O17+P17-Q17 -> 0
A18: 10150 | B18: Недополученные доходы от АНО полетов ВС пользователей ВП, освобожденных в соответствии с законодательством РФ от платы за АНО | G18: =C18+D18-E18-F18 -> 0 | K18: =G18+H18-I18-J18 -> 0 | O18: =K18+L18-M18-N18 -> 0 | S18: =D18+H18+L18+P18 -> 0 | T18: =E18+I18+M18+Q18 -> 0 | U18: =F18+J18+N18+R18 -> 0 | V18: =O18+P18-Q18 -> 0
A19: 10200 | B19: Прочие доходы | C19: =SUM(C20,C24:C35) -> 0 | D19: =SUM(D20,D24:D35) -> 0 | E19: =SUM(E20,E24:E35) -> 0 | F19: =SUM(F20,F24:F35) -> 0 | G19: =C19+D19-E19-F19 -> 0 | H19: =SUM(H20,H24:H35) -> 0 | I19: =SUM(I20,I24:I35) -> 0 | J19: =SUM(J20,J24:J35) -> 0 | K19: =G19+H19-I19-J19 -> 0 | L19: =SUM(L20,L24:L35) -> 0 | M19: =SUM(M20,M24:M35) -> 0 | N19: =SUM(N20,N24:N35) -> 0 | O19: =K19+L19-M19-N19 -> 0 | P19: =SUM(P20,P24:P35) -> 0 | Q19: =SUM(Q20,Q24:Q35) -> 0 | R19: =SUM(R20,R24:R35) -> 0 | S19: =P19+L19+H19+D19 -> 0 | T19: =Q19+M19+I19+E19 -> 0 | U19: =R19+N19+J19+F19 -> 0 | V19: =O19+P19-Q19-R19 -> 0
A20: 10210 | B20: Проценты к получению | C20: =C21+C22+C23 -> 0 | D20: =D21+D22+D23 -> 0 | E20: =E21+E22+E23 -> 0 | F20: =F21+F22+F23 -> 0 | G20: =C20+D20-E20-F20 -> 0 | H20: =H21+H22+H23 -> 0 | I20: =I21+I22+I23 -> 0 | J20: =J21+J22+J23 -> 0 | K20: =G20+H20-I20-J20 -> 0 | L20: =L21+L22+L23 -> 0 | M20: =M21+M22+M23 -> 0 | N20: =N21+N22+N23 -> 0 | O20: =K20+L20-M20-N20 -> 0 | P20: =P21+P22+P23 -> 0 | Q20: =Q21+Q22+Q23 -> 0 | R20: =R21+R22+R23 -> 0 | S20: =P20+L20+H20+D20 -> 0 | T20: =Q20+M20+I20+E20 -> 0 | U20: =R20+N20+J20+F20 -> 0 | V20: =O20+P20-Q20-R20 -> 0
A21: 102101 | B21: по облигациям, депозитам, государственным ценным бумагам | G21: =C21+D21-E21-F21 -> 0 | K21: =G21+H21-I21-J21 -> 0 | O21: =K21+L21-M21-N21 -> 0 | S21: =D21+H21+L21+P21 -> 0 | T21: =E21+I21+M21+Q21 -> 0 | U21: =F21+J21+N21+R21 -> 0 | V21: =O21+P21-Q21 -> 0
A22: 102102 | B22: за предоставление в пользование денежных средств | G22: =C22+D22-E22-F22 -> 0 | K22: =G22+H22-I22-J22 -> 0 | O22: =K22+L22-M22-N22 -> 0 | S22: =D22+H22+L22+P22 -> 0 | T22: =E22+I22+M22+Q22 -> 0 | U22: =F22+J22+N22+R22 -> 0 | V22: =O22+P22-Q22 -> 0
A23: 102103 | B23: за использование кредитной организацией денежных средств, находящихся на счете организации в этой кредитной организации | G23: =C23+D23-E23-F23 -> 0 | K23: =G23+H23-I23-J23 -> 0 | O23: =K23+L23-M23-N23 -> 0 | S23: =D23+H23+L23+P23 -> 0 | T23: =E23+I23+M23+Q23 -> 0 | U23: =F23+J23+N23+R23 -> 0 | V23: =O23+P23-Q23 -> 0
A24: 10211 | B24: Доходы от участия в других организациях (доходы, связанные с участием в уставных капиталах других организаций) | G24: =C24+D24-E24-F24 -> 0 | K24: =G24+H24-I24-J24 -> 0 | O24: =K24+L24-M24-N24 -> 0 | S24: =D24+H24+L24+P24 -> 0 | T24: =E24+I24+M24+Q24 -> 0 | U24: =F24+J24+N24+R24 -> 0 | V24: =O24+P24-Q24 -> 0
A25: 10212 | B25: Прибыль, полученная (подлежащая получению) в результате совместной деятельности (по договору простого товарищества) | G25: =C25+D25-E25-F25 -> 0 | K25: =G25+H25-I25-J25 -> 0 | O25: =K25+L25-M25-N25 -> 0 | S25: =D25+H25+L25+P25 -> 0 | T25: =E25+I25+M25+Q25 -> 0 | U25: =F25+J25+N25+R25 -> 0 | V25: =O25+P25-Q25 -> 0
A26: 10213 | B26: Сумма вознаграждения за переданное в общее владение и (или) пользование имущество или возврат имущества при его разделе сверх величины вклада (в части денежных средств) | G26: =C26+D26-E26-F26 -> 0 | K26: =G26+H26-I26-J26 -> 0 | O26: =K26+L26-M26-N26 -> 0 | S26: =D26+H26+L26+P26 -> 0 | T26: =E26+I26+M26+Q26 -> 0 | U26: =F26+J26+N26+R26 -> 0 | V26: =O26+P26-Q26 -> 0
A27: 10214 | B27: Сумма дохода, определенная к получению в соответствии с условиями договора продажи основных средств и иных активов | G27: =C27+D27-E27-F27 -> 0 | K27: =G27+H27-I27-J27 -> 0 | O27: =K27+L27-M27-N27 -> 0 | S27: =D27+H27+L27+P27 -> 0 | T27: =E27+I27+M27+Q27 -> 0 | U27: =F27+J27+N27+R27 -> 0 | V27: =O27+P27-Q27 -> 0
A28: 10220 | B28: Штрафные санкции и возмещение причиненных организации убытков | G28: =C28+D28-E28-F28 -> 0 | K28: =G28+H28-I28-J28 -> 0 | O28: =K28+L28-M28-N28 -> 0 | S28: =D28+H28+L28+P28 -> 0 | T28: =E28+I28+M28+Q28 -> 0 | U28: =F28+J28+N28+R28 -> 0 | V28: =O28+P28-Q28 -> 0
A29: 10221 | B29: Выявленная в плановом периоде прибыль прошлых лет, поступление прибыли прошлых лет, компенсационные выплаты | G29: =C29+D29-E29-F29 -> 0 | K29: =G29+H29-I29-J29 -> 0 | O29: =K29+L29-M29-N29 -> 0 | S29: =D29+H29+L29+P29 -> 0 | T29: =E29+I29+M29+Q29 -> 0 | U29: =F29+J29+N29+R29 -> 0 | V29: =O29+P29-Q29 -> 0
A30: 10222 | B30: Суммы кредиторской и депонентской задолженности, по которой истек срок исковой давности | G30: =C30+D30-E30-F30 -> 0 | K30: =G30+H30-I30-J30 -> 0 | O30: =K30+L30-M30-N30 -> 0 | S30: =D30+H30+L30+P30 -> 0 | T30: =E30+I30+M30+Q30 -> 0 | U30: =F30+J30+N30+R30 -> 0 | V30: =O30+P30-Q30 -> 0
A31: 10230 | B31: Доходы от операций с иностранной валютой и переоценки валютных денежных средств и эквивалентов | G31: =C31+D31-E31-F31 -> 0 | K31: =G31+H31-I31-J31 -> 0 | O31: =K31+L31-M31-N31 -> 0 | S31: =D31+H31+L31+P31 -> 0 | T31: =E31+I31+M31+Q31 -> 0 | U31: =F31+J31+N31+R31 -> 0 | V31: =O31+P31-Q31 -> 0
A32: 10240 | B32: Суммы страхового возмещения и покрытия из других источников | G32: =C32+D32-E32-F32 -> 0 | K32: =G32+H32-I32-J32 -> 0 | O32: =K32+L32-M32-N32 -> 0 | S32: =D32+H32+L32+P32 -> 0 | T32: =E32+I32+M32+Q32 -> 0 | U32: =F32+J32+N32+R32 -> 0 | V32: =O32+P32-Q32 -> 0
A33: 10241 | B33: Стоимость материальных ценностей, остающихся от списания непригодных к восстановлению и дальнейшему использованию активов | G33: =C33+D33-E33-F33 -> 0 | K33: =G33+H33-I33-J33 -> 0 | O33: =K33+L33-M33-N33 -> 0 | S33: =D33+H33+L33+P33 -> 0 | T33: =E33+I33+M33+Q33 -> 0 | U33: =F33+J33+N33+R33 -> 0 | V33: =O33+P33-Q33 -> 0
A34: 10260 | B34: Кредиты и займы (кредитные договоры) | G34: =C34+D34-E34-F34 -> 0 | K34: =G34+H34-I34-J34 -> 0 | O34: =K34+L34-M34-N34 -> 0 | S34: =D34+H34+L34+P34 -> 0 | T34: =E34+I34+M34+Q34 -> 0 | U34: =F34+J34+N34+R34 -> 0 | V34: =O34+P34-Q34 -> 0
A35: 10299 | B35: Прочие финансируемые доходы | G35: =C35+D35-E35-F35 -> 0 | K35: =G35+H35-I35-J35 -> 0 | O35: =K35+L35-M35-N35 -> 0 | S35: =D35+H35+L35+P35 -> 0 | T35: =E35+I35+M35+Q35 -> 0 | U35: =F35+J35+N35+R35 -> 0 | V35: =O35+P35-Q35 -> 0
A36: 10400 | B36: Финансовая поддержка сторонних организаций | C36: =SUM(C37:C38) -> 0 | D36: =SUM(D37:D38) -> 0 | E36: =SUM(E37:E38) -> 0 | F36: =SUM(F37:F38) -> 0 | G36: =C36+D36-E36-F36 -> 0 | H36: =SUM(H37:H38) -> 0 | I36: =SUM(I37:I38) -> 0 | J36: =SUM(J37:J38) -> 0 | K36: =G36+H36-I36-J36 -> 0 | L36: =SUM(L37:L38) -> 0 | M36: =SUM(M37:M38) -> 0 | N36: =SUM(N37:N38) -> 0 | O36: =K36+L36-M36-N36 -> 0 | P36: =SUM(P37:P38) -> 0 | Q36: =SUM(Q37:Q38) -> 0 | R36: =SUM(R37:R38) -> 0 | S36: =SUM(S37:S38) -> 0 | T36: =SUM(T37:T38) -> 0 | U36: =F36+J36+N36+R36 -> 0 | V36: =SUM(V37:V38) -> 0
A37: 10410 | B37: Средства российских А/К | G37: =C37+D37-E37-F37 -> 0 | K37: =G37+H37-I37-J37 -> 0 | O37: =K37+L37-M37-N37 -> 0 | S37: =D37+H37+L37+P37 -> 0 | T37: =E37+I37+M37+Q37 -> 0 | U37: =F37+J37+N37+R37 -> 0 | V37: =O37+P37-Q37 -> 0
A38: 10420 | B38: Средства иностранных А/К | G38: =C38+D38-E38-F38 -> 0 | K38: =G38+H38-I38-J38 -> 0 | O38: =K38+L38-M38-N38 -> 0 | S38: =D38+H38+L38+P38 -> 0 | T38: =E38+I38+M38+Q38 -> 0 | U38: =F38+J38+N38+R38 -> 0 | V38: =O38+P38-Q38 -> 0
A39: 10500 | B39: Средства Федерального бюджета | C39: =SUM(C40:C43) -> 0 | D39: =SUM(D40:D43) -> 0 | E39: =SUM(E40:E43) -> 0 | F39: =SUM(F40:F43) -> 0 | G39: =C39+D39-E39-F39 -> 0 | H39: =SUM(H40:H43) -> 0 | I39: =SUM(I40:I43) -> 0 | J39: =SUM(J40:J43) -> 0 | K39: =G39+H39-I39-J39 -> 0 | L39: =SUM(L40:L43) -> 0 | M39: =SUM(M40:M43) -> 0 | N39: =SUM(N40:N43) -> 0 | O39: =K39+L39-M39-N39 -> 0 | P39: =SUM(P40:P43) -> 0 | Q39: =SUM(Q40:Q43) -> 0 | R39: =SUM(R40:R43) -> 0 | S39: =S40 -> 0 | T39: =T40 -> 0 | U39: =F39+J39+N39+R39 -> 0 | V39: =V40 -> 0
A40: 10511 | B40: На функционирование КЦ Россия-НАТО | G40: =C40+D40-E40-F40 -> 0 | K40: =G40+H40-I40-J40 -> 0 | O40: =K40+L40-M40-N40 -> 0 | S40: =D40+H40+L40+P40 -> 0 | T40: =E40+I40+M40+Q40 -> 0 | U40: =F40+J40+N40+R40 -> 0 | V40: =O40+P40-Q40 -> 0
A41: 10520 | B41: На обеспечение функционирования Предприятия | G41: =C41+D41-E41-F41 -> 0 | K41: =G41+H41-I41-J41 -> 0 | O41: =K41+L41-M41-N41 -> 0 | S41: =D41+H41+L41+P41 -> 0 | T41: =E41+I41+M41+Q41 -> 0 | U41: =F41+J41+N41+R41 -> 0 | V41: =O41+P41-Q41 -> 0
A42: 10530 | B42: На возмещение затрат, понесенных при осуществлении закупки средств радиотехнического обеспечения полетов и авиационной электросвязи для полетов беспилотных воздушных судов | G42: =C42+D42-E42-F42 -> 0 | K42: =G42+H42-I42-J42 -> 0 | O42: =K42+L42-M42-N42 -> 0 | S42: =D42+H42+L42+P42 -> 0 | T42: =E42+I42+M42+Q42 -> 0 | U42: =F42+J42+N42+R42 -> 0 | V42: =O42+P42-Q42 -> 0
A43: 10540 | B43: На обеспечение реализации мероприятий, связанных с внедрением в эксплуатацию унифицированной инфраструктуры государственного поставщика услуг по обслуживанию линий управления БАС | G43: =C43+D43-E43-F43 -> 0 | K43: =G43+H43-I43-J43 -> 0 | O43: =K43+L43-M43-N43 -> 0 | S43: =D43+H43+L43+P43 -> 0 | T43: =E43+I43+M43+Q43 -> 0 | U43: =F43+J43+N43+R43 -> 0 | V43: =O43+P43-Q43 -> 0
A44: 10600 | B44: Средства бюджетов субъектов Российской Федерации и местных бюджетов | C44: =SUM(C45:C47) -> 0 | D44: =SUM(D45:D47) -> 0 | E44: =SUM(E45:E47) -> 0 | F44: =SUM(F45:F47) -> 0 | G44: =C44+D44-E44-F44 -> 0 | H44: =SUM(H45:H47) -> 0 | I44: =SUM(I45:I47) -> 0 | J44: =SUM(J45:J47) -> 0 | K44: =G44+H44-I44-J44 -> 0 | L44: =SUM(L45:L47) -> 0 | M44: =SUM(M45:M47) -> 0 | N44: =SUM(N45:N47) -> 0 | O44: =K44+L44-M44-N44 -> 0 | P44: =SUM(P45:P47) -> 0 | Q44: =SUM(Q45:Q47) -> 0 | R44: =SUM(R45:R47) -> 0 | S44: =P44+L44+H44+D44 -> 0 | T44: =Q44+M44+I44+E44 -> 0 | U44: =R44+N44+J44+F44 -> 0 | V44: =O44+P44-Q44-R44 -> 0
A45: 10601 | B45: Средства бюджетов субъектов РФ
A46: 10602 | B46: Средства местных бюджетов
A47: 10603 | B47: Средства прочих источников | G47: =C47+D47-E47-F47 -> 0 | K47: =G47+H47-I47-J47 -> 0 | O47: =K47+L47-M47-N47 -> 0 | S47: =D47+H47+L47+P47 -> 0 | T47: =E47+I47+M47+Q47 -> 0 | U47: =F47+J47+N47+R47 -> 0 | V47: =O47+P47-Q47 -> 0
A48: 10700 | B48: Возврат денежных средств по расходам прошлых периодов | C48: =SUM(C49:C50) -> 0 | D48: =SUM(D49:D50) -> 0 | E48: =SUM(E49:E50) -> 0 | F48: =SUM(F49:F50) -> 0 | G48: =C48+D48-E48-F48 -> 0 | H48: =SUM(H49:H50) -> 0 | I48: =SUM(I49:I50) -> 0 | J48: =SUM(J49:J50) -> 0 | K48: =G48+H48-I48-J48 -> 0 | L48: =SUM(L49:L50) -> 0 | M48: =SUM(M49:M50) -> 0 | N48: =SUM(N49:N50) -> 0 | O48: =K48+L48-M48-N48 -> 0 | P48: =SUM(P49:P50) -> 0 | Q48: =SUM(Q49:Q50) -> 0 | R48: =SUM(R49:R50) -> 0 | S48: =D48+H48+L48+P48 -> 0 | T48: =E48+I48+M48+Q48 -> 0 | U48: =F48+J48+N48+R48 -> 0 | V48: =O48+P48-Q48 -> 0
A50: 10700_код статьи ВПО | B50: Статья ВПО | G50: =C50+D50-E50-F50 -> 0 | K50: =G50+H50-I50-J50 -> 0 | O50: =K50+L50-M50-N50 -> 0 | S50: =D50+H50+L50+P50 -> 0 | T50: =E50+I50+M50+Q50 -> 0 | U50: =F50+J50+N50+R50 -> 0 | V50: =O50+P50-Q50 -> 0
A51: 02000 | B51: Движение денежных средств, не влияющее на сальдо обязательств (02100+02200) | C51: =SUM(C52:C54) -> 0 | D51: =SUM(D52:D54) -> 0 | E51: =SUM(E52:E54) -> 0 | F51: =SUM(F52:F54) -> 0 | G51: =SUM(G52:G54) -> 0 | H51: =SUM(H52:H54) -> 0 | I51: =SUM(I52:I54) -> 0 | J51: =SUM(J52:J54) -> 0 | ... V51: =SUM(V52:V54) -> 0
A52: 02100 | B52: Поступления денежных средств по агентским договорам | G52: =C52+D52-E52-F52 -> 0 | K52: =G52+H52-I52-J52 -> 0 | O52: =K52+L52-M52-N52 -> 0 | S52: =D52+H52+L52+P52 -> 0 | T52: =E52+I52+M52+Q52 -> 0 | U52: =F52+J52+N52+R52 -> 0 | V52: =O52+P52-Q52 -> 0
A53: 02200 | B53: Прочие поступления денежных средств, не влияющие на сальдо обязательств | G53: =C53+D53-E53-F53 -> 0 | K53: =G53+H53-I53-J53 -> 0 | O53: =K53+L53-M53-N53 -> 0 | S53: =D53+H53+L53+P53 -> 0 | T53: =E53+I53+M53+Q53 -> 0 | U53: =F53+J53+N53+R53 -> 0 | V53: =O53+P53-Q53 -> 0
A54: 02300 | B54: Поступление/возврат от контрагента финансового обеспечения выданного | G54: =C54+D54-E54-F54 -> 0 | K54: =G54+H54-I54-J54 -> 0 | O54: =K54+L54-M54-N54 -> 0 | S54: =P54+L54+H54+D54 -> 0 | T54: =Q54+M54+I54+E54 -> 0 | U54: =R54+N54+J54+F54 -> 0 | V54: =O54+P54-Q54-R54 -> 0
A55: 20000 | B55: РАСХОДЫ (20001+20120+20300+20500+ 20600+20703+20800+20810) | C55: =C56+C58+C59+C60+C64+C83+C94+C95+C104 -> 0 | D55: =D56+D58+D59+D60+D64+D83+D94+D95+D104 -> 0 | E55: =E56+E58+E59+E60+E64+E83+E94+E95+E104 -> 0 | F55: =F56+F58+F59+F60+F64+F83+F94+F95+F104 -> 0 | G55: =G56+G58+G59+G60+G64+G83+G94+G95+G104 -> 0 | H55: =H56+H58+H59+H60+H64+H83+H94+H95+H104 -> 0 | I55: =I56+I58+I59+I60+I64+I83+I94+I95+I104 -> 0 | J55: =J56+J58+J59+J60+J64+J83+J94+J95+J104 -> 0 | ... V55: =V56+V58+V59+V60+V64+V83+V94+V95+V104 -> 0
A56: 20001 | B56: Централизованное финансирование филиалов | C56: =C57+C58 -> 0 | D56: =D57+D58 -> 0 | E56: =E57+E58 -> 0 | F56: =F57+F58 -> 0 | G56: =C56+D56-E56-F56 -> 0 | H56: =H57+H58 -> 0 | I56: =I57+I58 -> 0 | J56: =J57+J58 -> 0 | K56: =G56+H56-I56-J56 -> 0 | L56: =L57+L58 -> 0 | M56: =M57+M58 -> 0 | N56: =N57+N58 -> 0 | O56: =K56+L56-M56-N56 -> 0 | P56: =P57+P58 -> 0 | Q56: =Q57+Q58 -> 0 | R56: =R57+R58 -> 0 | S56: =S57+S58 -> 0 | T56: =T57+T58 -> 0 | U56: =U57+U58 -> 0 | V56: =V57+V58 -> 0
A57: 200011 | B57: Централизованное финансирование филиалов в пределах лимитов
A58: 200012 | B58: Централизованное финансирование сверх лимита
A59: 20110 | B59: Лимит ФОТ | G59: =C59+D59-E59-F59 -> 0 | K59: =G59+H59-I59-J59 -> 0 | O59: =K59+L59-M59-N59 -> 0 | S59: =D59+H59+L59+P59 -> 0 | T59: =E59+I59+M59+Q59 -> 0 | U59: =F59+J59+N59+R59 -> 0 | V59: =O59+P59-Q59 -> 0
A60: 20120 | B60: Затраты социального характера | C60: =C61+C62 -> 0 | D60: =D61+D62 -> 0 | E60: =E61+E62 -> 0 | F60: =F61+F62 -> 0 | G60: =C60+D60-E60-F60 -> 0 | H60: =H61+H62 -> 0 | I60: =I61+I62 -> 0 | J60: =J61+J62 -> 0 | K60: =G60+H60-I60-J60 -> 0 | L60: =L61+L62 -> 0 | M60: =M61+M62 -> 0 | N60: =N61+N62 -> 0 | O60: =K60+L60-M60-N60 -> 0 | P60: =P61+P62 -> 0 | Q60: =Q61+Q62 -> 0 | R60: =R61+R62 -> 0 | S60: =D60+H60+L60+P60 -> 0 | T60: =E60+I60+M60+Q60 -> 0 | U60: =F60+J60+N60+R60 -> 0 | V60: =O60+P60-Q60 -> 0
A61: 20121 | B61: Затраты социального характера ПДФ ,учитываемые в составе расходов на производство товаров, работ, услуг | G61: =C61+D61-E61-F61 -> 0 | K61: =G61+H61-I61-J61 -> 0 | O61: =K61+L61-M61-N61 -> 0 | S61: =D61+H61+L61+P61 -> 0 | T61: =E61+I61+M61+Q61 -> 0 | U61: =F61+J61+N61+R61 -> 0 | V61: =O61+P61-Q61 -> 0
A62: 20122 | B62: Расходы по Централизованному плану мероприятий Социальной программы,учитываемые в составе расходов на производство товаров, работ, услуг | G62: =C62+D62-E62-F62 -> 0 | K62: =G62+H62-I62-J62 -> 0 | O62: =K62+L62-M62-N62 -> 0 | S62: =D62+H62+L62+P62 -> 0 | T62: =E62+I62+M62+Q62 -> 0 | U62: =F62+J62+N62+R62 -> 0 | V62: =O62+P62-Q62 -> 0
A63: 20200 | B63: Страховые взносы во внебюджетные фонды РФ | G63: =C63+D63-E63-F63 -> 0 | K63: =G63+H63-I63-J63 -> 0 | O63: =K63+L63-M63-N63 -> 0 | S63: =P63+L63+H63+D63 -> 0 | T63: =Q63+M63+I63+E63 -> 0 | U63: =R63+N63+J63+F63 -> 0 | V63: =O63+P63-Q63-R63 -> 0
A64: 20300 | B64: Материальные затраты и прочие производственные расходы | C64: =SUM(C65:C68)+SUM(C69:C82) -> 0 | D64: =SUM(D65:D68)+SUM(D69:D82) -> 0 | E64: =SUM(E65:E68)+SUM(E69:E82) -> 0 | F64: =SUM(F65:F68)+SUM(F69:F82) -> 0 | G64: =C64+D64-E64-F64 -> 0 | H64: =SUM(H65:H68)+SUM(H69:H82) -> 0 | I64: =SUM(I65:I68)+SUM(I69:I82) -> 0 | J64: =SUM(J65:J68)+SUM(J69:J82) -> 0 | K64: =G64+H64-I64-J64 -> 0 | L64: =SUM(L65:L68)+SUM(L69:L82) -> 0 | M64: =SUM(M65:M68)+SUM(M69:M82) -> 0 | N64: =SUM(N65:N68)+SUM(N69:N82) -> 0 | O64: =K64+L64-M64-N64 -> 0 | P64: =SUM(P65:P68)+SUM(P69:P82) -> 0 | Q64: =SUM(Q65:Q68)+SUM(Q69:Q82) -> 0 | R64: =SUM(R65:R68)+SUM(R69:R82) -> 0 | S64: =D64+H64+L64+P64 -> 0 | T64: =E64+I64+M64+Q64 -> 0 | U64: =F64+J64+N64+R64 -> 0 | V64: =O64+P64-Q64 -> 0
A65: 20301 | B65: Услуги связи | G65: =C65+D65-E65-F65 -> 0 | K65: =G65+H65-I65-J65 -> 0 | O65: =K65+L65-M65-N65 -> 0 | S65: =D65+H65+L65+P65 -> 0 | T65: =E65+I65+M65+Q65 -> 0 | U65: =F65+J65+N65+R65 -> 0 | V65: =O65+P65-Q65 -> 0
A66: 20302 | B66: ПСО, тренировочные полеты | G66: =C66+D66-E66-F66 -> 0 | K66: =G66+H66-I66-J66 -> 0 | O66: =K66+L66-M66-N66 -> 0 | S66: =D66+H66+L66+P66 -> 0 | T66: =E66+I66+M66+Q66 -> 0 | U66: =F66+J66+N66+R66 -> 0 | V66: =O66+P66-Q66 -> 0
A67: 20308 | B67: Авиаметеообеспечение | G67: =C67+D67-E67-F67 -> 0 | K67: =G67+H67-I67-J67 -> 0 | O67: =K67+L67-M67-N67 -> 0 | S67: =D67+H67+L67+P67 -> 0 | T67: =E67+I67+M67+Q67 -> 0 | U67: =F67+J67+N67+R67 -> 0 | V67: =O67+P67-Q67 -> 0
A68: 20380 | B68: Летные проверки | G68: =C68+D68-E68-F68 -> 0 | K68: =G68+H68-I68-J68 -> 0 | O68: =K68+L68-M68-N68 -> 0 | S68: =D68+H68+L68+P68 -> 0 | T68: =E68+I68+M68+Q68 -> 0 | U68: =F68+J68+N68+R68 -> 0 | V68: =O68+P68-Q68 -> 0
A69: 20421 | B69: Расходы на международные и корпоративные мероприятия | G69: =C69+D69-E69-F69 -> 0 | K69: =G69+H69-I69-J69 -> 0 | O69: =K69+L69-M69-N69 -> 0 | S69: =D69+H69+L69+P69 -> 0 | T69: =E69+I69+M69+Q69 -> 0 | U69: =F69+J69+N69+R69 -> 0 | V69: =O69+P69-Q69 -> 0
A70: 20422 | B70: Аудит | G70: =C70+D70-E70-F70 -> 0 | K70: =G70+H70-I70-J70 -> 0 | O70: =K70+L70-M70-N70 -> 0 | S70: =D70+H70+L70+P70 -> 0 | T70: =E70+I70+M70+Q70 -> 0 | U70: =F70+J70+N70+R70 -> 0 | V70: =O70+P70-Q70 -> 0
A71: 20423 | B71: Информационные, консультационные услуги | G71: =C71+D71-E71-F71 -> 0 | K71: =G71+H71-I71-J71 -> 0 | O71: =K71+L71-M71-N71 -> 0 | S71: =D71+H71+L71+P71 -> 0 | T71: =E71+I71+M71+Q71 -> 0 | U71: =F71+J71+N71+R71 -> 0 | V71: =O71+P71-Q71 -> 0
A72: 20429 | B72: Страхование гражданской ответственности | G72: =C72+D72-E72-F72 -> 0 | K72: =G72+H72-I72-J72 -> 0 | O72: =K72+L72-M72-N72 -> 0 | S72: =D72+H72+L72+P72 -> 0 | T72: =E72+I72+M72+Q72 -> 0 | U72: =F72+J72+N72+R72 -> 0 | V72: =O72+P72-Q72 -> 0
A73: 20430 | B73: Расходы по Плану НИОКР | G73: =C73+D73-E73-F73 -> 0 | K73: =G73+H73-I73-J73 -> 0 | O73: =K73+L73-M73-N73 -> 0 | S73: =D73+H73+L73+P73 -> 0 | T73: =E73+I73+M73+Q73 -> 0 | U73: =F73+J73+N73+R73 -> 0 | V73: =O73+P73-Q73 -> 0
A74: 204321 | B74: Централизованные текущие расходы по обеспечению информационной безопасности | G74: =C74+D74-E74-F74 -> 0 | K74: =G74+H74-I74-J74 -> 0 | O74: =K74+L74-M74-N74 -> 0 | S74: =D74+H74+L74+P74 -> 0 | T74: =E74+I74+M74+Q74 -> 0 | U74: =F74+J74+N74+R74 -> 0 | V74: =O74+P74-Q74 -> 0
A75: 20439 | B75: Услуги по обеспечению пожарной безопасности, включая ТО
A76: 20440 | B76: Услуги по обеспечению междусменного отдыха диспетчерского состава
A77: 20441 | B77: Расходы на проведение работ по организации съемки координат
A78: 20442 | B78: Расходы на охрану окружающей среды, утилизация опасных отходов, вывоз БО
A79: 20443 | B79: Мониторинг характеристик выдерживания высоты воздушных судов в воздушном пространстве с RVSM
A80: 20450 | B80: Расходы на составление фин.отчетности по МСФО | G80: =C80+D80-E80-F80 -> 0 | K80: =G80+H80-I80-J80 -> 0 | O80: =K80+L80-M80-N80 -> 0 | S80: =D80+H80+L80+P80 -> 0 | T80: =E80+I80+M80+Q80 -> 0 | U80: =F80+J80+N80+R80 -> 0 | V80: =O80+P80-Q80 -> 0
A81: 204951 | B81: Централизованные текущие расходы по поддержанию информационных технологий | G81: =C81+D81-E81-F81 -> 0 | K81: =G81+H81-I81-J81 -> 0 | O81: =K81+L81-M81-N81 -> 0 | S81: =D81+H81+L81+P81 -> 0 | T81: =E81+I81+M81+Q81 -> 0 | U81: =F81+J81+N81+R81 -> 0 | V81: =O81+P81-Q81 -> 0
A82: 20499 | B82: Другие производственные расходы | G82: =C82+D82-E82-F82 -> 0 | K82: =G82+H82-I82-J82 -> 0 | O82: =K82+L82-M82-N82 -> 0 | S82: =D82+H82+L82+P82 -> 0 | T82: =E82+I82+M82+Q82 -> 0 | U82: =F82+J82+N82+R82 -> 0 | V82: =O82+P82-Q82 -> 0
A83: 20500 | B83: Прочие расходы | C83: =SUM(C85:C93) -> 0 | D83: =SUM(D85:D93) -> 0 | E83: =SUM(E85:E93) -> 0 | F83: =SUM(F85:F93) -> 0 | G83: =C83+D83-E83-F83 -> 0 | H83: =SUM(H85:H93) -> 0 | I83: =SUM(I85:I93) -> 0 | J83: =SUM(J85:J93) -> 0 | K83: =G83+H83-I83-J83 -> 0 | L83: =SUM(L85:L93) -> 0 | M83: =SUM(M85:M93) -> 0 | N83: =SUM(N85:N93) -> 0 | O83: =K83+L83-M83-N83 -> 0 | P83: =SUM(P85:P93) -> 0 | Q83: =SUM(Q85:Q93) -> 0 | R83: =SUM(R85:R93) -> 0 | S83: =SUM(S85:S93) -> 0 | T83: =SUM(T85:T93) -> 0 | U83: =F83+J83+N83+R83 -> 0 | V83: =SUM(V85:V93) -> 0
A84: 20501 | B84: Проценты к уплате
A85: 20502 | B85: Услуги банков | G85: =C85+D85-E85-F85 -> 0 | K85: =G85+H85-I85-J85 -> 0 | O85: =K85+L85-M85-N85 -> 0 | S85: =D85+H85+L85+P85 -> 0 | T85: =E85+I85+M85+Q85 -> 0 | U85: =F85+J85+N85+R85 -> 0 | V85: =O85+P85-Q85 -> 0
A86: 20503 | B86: Штрафы, пени, неустойки, возмещение причиненных организацией убытков | G86: =C86+D86-E86-F86 -> 0 | K86: =G86+H86-I86-J86 -> 0 | O86: =K86+L86-M86-N86 -> 0 | S86: =D86+H86+L86+P86 -> 0 | T86: =E86+I86+M86+Q86 -> 0 | U86: =F86+J86+N86+R86 -> 0 | V86: =O86+P86-Q86 -> 0
A87: 20504 | B87: Расходы от операций с иностранной валютой и переоценки валютных денежных средств и эквивалентов | G87: =C87+D87-E87-F87 -> 0 | K87: =G87+H87-I87-J87 -> 0 | O87: =K87+L87-M87-N87 -> 0 | S87: =D87+H87+L87+P87 -> 0 | T87: =E87+I87+M87+Q87 -> 0 | U87: =F87+J87+N87+R87 -> 0 | V87: =O87+P87-Q87 -> 0
A88: 20505 | B88: Выявленные убытки прошлых лет | G88: =C88+D88-E88-F88 -> 0 | K88: =G88+H88-I88-J88 -> 0 | O88: =K88+L88-M88-N88 -> 0 | S88: =D88+H88+L88+P88 -> 0 | T88: =E88+I88+M88+Q88 -> 0 | U88: =F88+J88+N88+R88 -> 0 | V88: =O88+P88-Q88 -> 0
A89: 20506 | B89: Расходы по Жилищной программе | G89: =C89+D89-E89-F89 -> 0 | K89: =G89+H89-I89-J89 -> 0 | O89: =K89+L89-M89-N89 -> 0 | S89: =D89+H89+L89+P89 -> 0 | T89: =E89+I89+M89+Q89 -> 0 | U89: =F89+J89+N89+R89 -> 0 | V89: =O89+P89-Q89 -> 0
A90: 20507 | B90: Пенсионный фонд АО "НПФ "Авиаполис" | G90: =C90+D90-E90-F90 -> 0 | K90: =G90+H90-I90-J90 -> 0 | O90: =K90+L90-M90-N90 -> 0 | S90: =D90+H90+L90+P90 -> 0 | T90: =E90+I90+M90+Q90 -> 0 | U90: =F90+J90+N90+R90 -> 0 | V90: =O90+P90-Q90 -> 0
A91: 20508 | B91: Затраты социального характера ПДФ в составе прочих расходов | G91: =C91+D91-E91-F91 -> 0 | K91: =G91+H91-I91-J91 -> 0 | O91: =K91+L91-M91-N91 -> 0 | S91: =D91+H91+L91+P91 -> 0 | T91: =E91+I91+M91+Q91 -> 0 | U91: =F91+J91+N91+R91 -> 0 | V91: =O91+P91-Q91 -> 0
A92: 20515 | B92: Расходы по централизованному Плану профподготовки | G92: =C92+D92-E92-F92 -> 0 | K92: =G92+H92-I92-J92 -> 0 | O92: =K92+L92-M92-N92 -> 0 | S92: =D92+H92+L92+P92 -> 0 | T92: =E92+I92+M92+Q92 -> 0 | U92: =F92+J92+N92+R92 -> 0 | V92: =O92+P92-Q92 -> 0
A93: 20599 | B93: Прочие финансируемые расходы | G93: =C93+D93-E93-F93 -> 0 | K93: =G93+H93-I93-J93 -> 0 | O93: =K93+L93-M93-N93 -> 0 | S93: =D93+H93+L93+P93 -> 0 | T93: =E93+I93+M93+Q93 -> 0 | U93: =F93+J93+N93+R93 -> 0 | V93: =O93+P93-Q93 -> 0
A94: 20600 | B94: Резерв на непредвиденные расходы | G94: =C94+D94-E94-F94 -> 0 | K94: =G94+H94-I94-J94 -> 0 | O94: =K94+L94-M94-N94 -> 0 | S94: =D94+H94+L94+P94 -> 0 | T94: =E94+I94+M94+Q94 -> 0 | U94: =F94+J94+N94+R94 -> 0 | V94: =O94+P94-Q94 -> 0
A95: 20703 | B95: Расходы по централизованным планам ремонтов и капитальных вложений | C95: =SUM(C96:C100,C101,C102,C103) -> 0 | D95: =SUM(D96:D100,D101,D102,D103) -> 0 | E95: =SUM(E96:E100,E101,E102,E103) -> 0 | F95: =SUM(F96:F100,F101,F102,F103) -> 0 | G95: =C95+D95-E95-F95 -> 0 | H95: =SUM(H96:H100,H101,H102,H103) -> 0 | I95: =SUM(I96:I100,I101,I102,I103) -> 0 | J95: =SUM(J96:J100,J101,J102,J103) -> 0 | K95: =G95+H95-I95-J95 -> 0 | L95: =SUM(L96:L100,L101,L102,L103) -> 0 | M95: =SUM(M96:M100,M101,M102,M103) -> 0 | N95: =SUM(N96:N100,N101,N102,N103) -> 0 | O95: =K95+L95-M95-N95 -> 0 | P95: =SUM(P96:P100,P101,P102,P103) -> 0 | Q95: =SUM(Q96:Q100,Q101,Q102,Q103) -> 0 | R95: =SUM(R96:R100,R101,R102,R103) -> 0 | S95: =D95+H95+L95+P95 -> 0 | T95: =E95+I95+M95+Q95 -> 0 | U95: =F95+J95+N95+R95 -> 0 | V95: =O95+P95-Q95 -> 0
A96: 2070311 | B96: Государственная программа Российской Федерации "Космическая деятельность России» | G96: =C96+D96-E96-F96 -> 0 | K96: =G96+H96-I96-J96 -> 0 | O96: =K96+L96-M96-N96 -> 0 | S96: =D96+H96+L96+P96 -> 0 | T96: =E96+I96+M96+Q96 -> 0 | U96: =F96+J96+N96+R96 -> 0 | V96: =O96+P96-Q96 -> 0
A97: 2070314 | B97: Централизованный план мероприятий по реализации федерального проекта «Развитие инфраструктуры, обеспечение безопасности и формирование специализированной системы сертификации беспилотных авиационных систем» | G97: =C97+D97-E97-F97 -> 0 | K97: =G97+H97-I97-J97 -> 0 | O97: =K97+L97-M97-N97 -> 0 | S97: =D97+H97+L97+P97 -> 0 | T97: =E97+I97+M97+Q97 -> 0 | U97: =F97+J97+N97+R97 -> 0 | V97: =O97+P97-Q97 -> 0
A98: 2070315 | B98: Централизованный план по развитию опорной сети аэродромов объектов ЕС ОрВД | G98: =C98+D98-E98-F98 -> 0 | K98: =G98+H98-I98-J98 -> 0 | O98: =K98+L98-M98-N98 -> 0 | S98: =D98+H98+L98+P98 -> 0 | T98: =E98+I98+M98+Q98 -> 0 | U98: =F98+J98+N98+R98 -> 0 | V98: =O98+P98-Q98 -> 0
A99: 2070322 | B99: Централизованный план строительства, оснащения и модернизации объектов ЕС ОрВД | G99: =C99+D99-E99-F99 -> 0 | K99: =G99+H99-I99-J99 -> 0 | O99: =K99+L99-M99-N99 -> 0 | S99: =D99+H99+L99+P99 -> 0 | T99: =E99+I99+M99+Q99 -> 0 | U99: =F99+J99+N99+R99 -> 0 | V99: =O99+P99-Q99 -> 0
A100: 2070323 | B100: Централизованный план мероприятий по обеспечению информационной безопасности ФГУП «Госкорпорация по ОрВД» в части капитальных расходов | G100: =C100+D100-E100-F100 -> 0 | K100: =G100+H100-I100-J100 -> 0 | O100: =K100+L100-M100-N100 -> 0 | S100: =D100+H100+L100+P100 -> 0 | T100: =E100+I100+M100+Q100 -> 0 | U100: =F100+J100+N100+R100 -> 0 | V100: =O100+P100-Q100 -> 0
A101: 2070324 | B101: Централизованный план мероприятий по развитию информационных технологий ФГУП «Госкорпорация по ОрВД» в части капитальных расходов | G101: =C101+D101-E101-F101 -> 0 | K101: =G101+H101-I101-J101 -> 0 | O101: =K101+L101-M101-N101 -> 0 | S101: =D101+H101+L101+P101 -> 0 | T101: =E101+I101+M101+Q101 -> 0 | U101: =F101+J101+N101+R101 -> 0 | V101: =O101+P101-Q101 -> 0
...

Sheet Пр 9 Титульный лист
K1: ПРИЛОЖЕНИЕ № 9
J2: К ПОРЯДКУ ТЕКУЩЕГО ПЛАНИРОВАНИЯ ПРОИЗВОДСТВЕННО-ХОЗЯЙСТВЕННОЙ ДЕЯТЕЛЬНОСТИ ФГУП «ГОСКОРПОРАЦИЯ ПО ОрВД»
A10: УТВЕРЖДАЮ | J10: СОГЛАСОВАНО
A11: Директор | J11: Генеральный директор
A12: филиала « » | J12: ФГУП «Госкорпорация по ОрВД»
A13: ФГУП «Госкорпорация по ОрВД»
A25: ПРОГРАММА / УТОЧНЕННАЯ ПРОГРАММА
A26: деятельности филиала « »
A27: ФГУП «Госкорпорация по ОрВД»
D28: на | J28: год
D37: г. Москва – ________г.

Sheet Пр 10 План ВПО 
O1: ПРИЛОЖЕНИЕ № 10
M2: К ПОРЯДКУ ТЕКУЩЕГО ПЛАНИРОВАНИЯ ПРОИЗВОДСТВЕННО-ХОЗЯЙСТВЕННОЙ ДЕЯТЕЛЬНОСТИ ФГУП «ГОСКОРПОРАЦИЯ ПО ОрВД»
C3: План возникновения и погашения обязательств
B4: по филиалу
B5: ФГУП «Госкорпорация по ОрВД» за | H5: г.
A6: (1-й квартал, 1-е полугодие, 9 месяцев, год) | V6: тыс.руб.
A7: № статьи ВПО | B7: Наименование статьи | C7: сальдо обязательств на начало года | D7: в т. ч. по кварталам | S7: ИТОГО | V7: сальдо обязательств на конец года | W7: Предельная (максимальная) стоимость закупки | X7: Примечание к кол.23
D8: 1 кв-л | H8: 2 кв-л | L8: 3 кв-л | P8: 4 кв-л | S8: за год
D9: план/факт | H9: план/факт | L9: план/факт | P9: план | S9: план
D10: по начис-лению | E10: по оплате | F10: неденежные изменения | G10: сальдо задолженности | H10: по начис-лению | I10: по оплате | J10: неденежные изменения | K10: сальдо задолженности | L10: по начис-лению | M10: по оплате | N10: неденежные изменения | O10: сальдо задолженности | P10: по начис-лению | Q10: по оплате | R10: неденежные изменения | S10: по начис-лению | T10: по оплате | U10: неденежные изменения
A11: 1 | B11: 2 | C11: 3 | D11: 4 | E11: 5 | F11: 6 | G11: 7 | H11: 8 | I11: 9 | J11: 10 | K11: 11 | L11: 12 | M11: 13 | N11: 14 | O11: 15 | P11: 16 | Q11: 17 | R11: 18 | S11: 19 | T11: 20 | U11: 21 | V11: 22 | W11: 23 | X11: *
A12: 01000 | B12: Остаток денежных средств на начало периода | C12: Х | D12: Х | F12: Х | G12: Х | H12: Х | J12: =F163 -> Х | K12: Х | L12: Х | N12: Х | O12: Х | P12: Х | R12: Х | S12: Х | U12: =F12 -> Х | V12: Х
A13: 10000 | B13: ДОХОДЫ (ПОСТУПЛЕНИЯ) (10100+10200+10400+10500+10600+10700) | C13: =C14+C19+C36+C37+C41+C45 -> 0 | D13: =D14+D19+D36+D37+D41+D45 -> 0 | E13: =E14+E19+E36+E37+E41+E45 -> 0 | F13: =F14+F19+F36+F37+F41+F45 -> 0 | G13: =C13+D13-E13-F13 -> 0 | H13: =H14+H19+H36+H37+H41+H45 -> 0 | I13: =I14+I19+I36+I37+I41+I45 -> 0 | J13: =J14+J19+J36+J37+J41+J45 -> 0 | K13: =G13+H13-I13-J13 -> 0 | L13: =L14+L19+L36+L37+L41+L45 -> 0 | M13: =M14+M19+M36+M37+M41+M45 -> 0 | N13: =N14+N19+N36+N37+N41+N45 -> 0 | O13: =K13+L13-M13-N13 -> 0 | P13: =P14+P19+P36+P37+P41+P45 -> 0 | Q13: =Q14+Q19+Q36+Q37+Q41+Q45 -> 0 | R13: =R14+R19+R36+R37+R41+R45 -> 0 | S13: =S14+S19+S36+S37+S41+S45 -> 0 | T13: =T14+T19+T36+T37+T41+T45 -> 0 | U13: =U14+U19+U36+U37+U41+U45 -> 0 | V13: =O13+P13-Q13-R13 -> 0
A14: 10100 | B14: Выручка (поступления) по обычным видам деятельности всего, в т.ч. | C14: =SUM(C15:C18) -> 0 | D14: =SUM(D15:D18) -> 0 | E14: =SUM(E15:E18) -> 0 | F14: =SUM(F15:F18) -> 0 | G14: =C14+D14-E14-F14 -> 0 | H14: =SUM(H15:H18) -> 0 | I14: =SUM(I15:I18) -> 0 | J14: =SUM(J15:J18) -> 0 | K14: =G14+H14-I14-J14 -> 0 | L14: =SUM(L15:L18) -> 0 | M14: =SUM(M15:M18) -> 0 | N14: =SUM(N15:N18) -> 0 | O14: =K14+L14-M14-N14 -> 0 | P14: =SUM(P15:P18) -> 0 | Q14: =SUM(Q15:Q18) -> 0 | R14: =SUM(R15:R18) -> 0 | S14: =P14+L14+H14+D14 -> 0 | T14: =Q14+M14+I14+E14 -> 0 | U14: =R14+N14+J14+F14 -> 0 | V14: =O14+P14-Q14-R14 -> 0
A15: 10110 | B15: от АНО на маршрутах обслуживания воздушного движения | G15: =C15+D15-E15-F15 -> 0 | K15: =G15+H15-I15-J15 -> 0 | O15: =K15+L15-M15-N15 -> 0 | S15: =P15+L15+H15+D15 -> 0 | T15: =Q15+M15+I15+E15 -> 0 | U15: =R15+N15+J15+F15 -> 0 | V15: =O15+P15-Q15-R15 -> 0
A16: 10120 | B16: от АНО в районах аэродромов | G16: =C16+D16-E16-F16 -> 0 | K16: =G16+H16-I16-J16 -> 0 | O16: =K16+L16-M16-N16 -> 0 | S16: =P16+L16+H16+D16 -> 0 | T16: =Q16+M16+I16+E16 -> 0 | U16: =R16+N16+J16+F16 -> 0 | V16: =O16+P16-Q16-R16 -> 0
A17: 10140 | B17: от прочей деятельности | G17: =C17+D17-E17-F17 -> 0 | K17: =G17+H17-I17-J17 -> 0 | O17: =K17+L17-M17-N17 -> 0 | S17: =P17+L17+H17+D17 -> 0 | T17: =Q17+M17+I17+E17 -> 0 | U17: =R17+N17+J17+F17 -> 0 | V17: =O17+P17-Q17-R17 -> 0
A18: 10150 | B18: Недополученные доходы от АНО полетов ВС пользователей ВП, освобожденных в соответствии с законодательством РФ от платы за АНО | G18: =C18+D18-E18-F18 -> 0 | K18: =G18+H18-I18-J18 -> 0 | O18: =K18+L18-M18-N18 -> 0 | S18: =P18+L18+H18+D18 -> 0 | T18: =Q18+M18+I18+E18 -> 0 | U18: =R18+N18+J18+F18 -> 0 | V18: =O18+P18-Q18-R18 -> 0
A19: 10200 | B19: Прочие доходы (поступления) | C19: =SUM(C20,C24:C35) -> 0 | D19: =SUM(D20,D24:D35) -> 0 | E19: =SUM(E20,E24:E35) -> 0 | F19: =SUM(F20,F24:F35) -> 0 | G19: =C19+D19-E19-F19 -> 0 | H19: =SUM(H20,H24:H35) -> 0 | I19: =SUM(I20,I24:I35) -> 0 | J19: =SUM(J20,J24:J35) -> 0 | K19: =G19+H19-I19-J19 -> 0 | L19: =SUM(L20,L24:L35) -> 0 | M19: =SUM(M20,M24:M35) -> 0 | N19: =SUM(N20,N24:N35) -> 0 | O19: =K19+L19-M19-N19 -> 0 | P19: =SUM(P20,P24:P35) -> 0 | Q19: =SUM(Q20,Q24:Q35) -> 0 | R19: =SUM(R20,R24:R35) -> 0 | S19: =P19+L19+H19+D19 -> 0 | T19: =Q19+M19+I19+E19 -> 0 | U19: =R19+N19+J19+F19 -> 0 | V19: =O19+P19-Q19-R19 -> 0
A20: 10210 | B20: Проценты к получению | C20: =C21+C22+C23 -> 0 | D20: =D21+D22+D23 -> 0 | E20: =E21+E22+E23 -> 0 | F20: =F21+F22+F23 -> 0 | G20: =C20+D20-E20-F20 -> 0 | H20: =H21+H22+H23 -> 0 | I20: =I21+I22+I23 -> 0 | J20: =J21+J22+J23 -> 0 | K20: =G20+H20-I20-J20 -> 0 | L20: =L21+L22+L23 -> 0 | M20: =M21+M22+M23 -> 0 | N20: =N21+N22+N23 -> 0 | O20: =K20+L20-M20-N20 -> 0 | P20: =P21+P22+P23 -> 0 | Q20: =Q21+Q22+Q23 -> 0 | R20: =R21+R22+R23 -> 0 | S20: =P20+L20+H20+D20 -> 0 | T20: =Q20+M20+I20+E20 -> 0 | U20: =R20+N20+J20+F20 -> 0 | V20: =O20+P20-Q20-R20 -> 0
A21: 102101 | B21: проценты к получению по облигациям, депозитам, государственным ценным бумагам | G21: =C21+D21-E21-F21 -> 0 | K21: =G21+H21-I21-J21 -> 0 | O21: =K21+L21-M21-N21 -> 0 | S21: =P21+L21+H21+D21 -> 0 | T21: =Q21+M21+I21+E21 -> 0 | U21: =R21+N21+J21+F21 -> 0 | V21: =O21+P21-Q21-R21 -> 0
A22: 102102 | B22: проценты к получению за предоставление в пользование денежных средств | G22: =C22+D22-E22-F22 -> 0 | K22: =G22+H22-I22-J22 -> 0 | O22: =K22+L22-M22-N22 -> 0 | S22: =P22+L22+H22+D22 -> 0 | T22: =Q22+M22+I22+E22 -> 0 | U22: =R22+N22+J22+F22 -> 0 | V22: =O22+P22-Q22-R22 -> 0
A23: 102103 | B23: проценты к получению за использование кредитной организацией денежными средствами, находящимися на счетах организации в этой кредитной организации | G23: =C23+D23-E23-F23 -> 0 | K23: =G23+H23-I23-J23 -> 0 | O23: =K23+L23-M23-N23 -> 0 | S23: =P23+L23+H23+D23 -> 0 | T23: =Q23+M23+I23+E23 -> 0 | U23: =R23+N23+J23+F23 -> 0 | V23: =O23+P23-Q23-R23 -> 0
A24: 10211 | B24: Доходы от участия в других организациях (доходы, связанные с участием в уставных капиталах других организаций) | G24: =C24+D24-E24-F24 -> 0 | K24: =G24+H24-I24-J24 -> 0 | O24: =K24+L24-M24-N24 -> 0 | S24: =P24+L24+H24+D24 -> 0 | T24: =Q24+M24+I24+E24 -> 0 | U24: =R24+N24+J24+F24 -> 0 | V24: =O24+P24-Q24-R24 -> 0
A25: 10212 | B25: Прибыль, полученная (подлежащая получению) в результате совместной деятельности (по договору простого товарищества) | G25: =C25+D25-E25-F25 -> 0 | K25: =G25+H25-I25-J25 -> 0 | O25: =K25+L25-M25-N25 -> 0 | S25: =P25+L25+H25+D25 -> 0 | T25: =Q25+M25+I25+E25 -> 0 | U25: =R25+N25+J25+F25 -> 0 | V25: =O25+P25-Q25-R25 -> 0
A26: 10213 | B26: Сумма вознаграждения за переданное в общее владение и (или) пользование имущество или возврат имущества при его разделе сверх величины вклада (в части денежных средств) | G26: =C26+D26-E26-F26 -> 0 | K26: =G26+H26-I26-J26 -> 0 | O26: =K26+L26-M26-N26 -> 0 | S26: =P26+L26+H26+D26 -> 0 | T26: =Q26+M26+I26+E26 -> 0 | U26: =R26+N26+J26+F26 -> 0 | V26: =O26+P26-Q26-R26 -> 0
A27: 10214 | B27: Сумма дохода, определенная к получению в соответствии с условиями договора продажи основных средств и иных активов | G27: =C27+D27-E27-F27 -> 0 | K27: =G27+H27-I27-J27 -> 0 | O27: =K27+L27-M27-N27 -> 0 | S27: =P27+L27+H27+D27 -> 0 | T27: =Q27+M27+I27+E27 -> 0 | U27: =R27+N27+J27+F27 -> 0 | V27: =O27+P27-Q27-R27 -> 0
A28: 10220 | B28: Штрафные санкции и возмещение причиненных организации убытков | G28: =C28+D28-E28-F28 -> 0 | K28: =G28+H28-I28-J28 -> 0 | O28: =K28+L28-M28-N28 -> 0 | S28: =P28+L28+H28+D28 -> 0 | T28: =Q28+M28+I28+E28 -> 0 | U28: =R28+N28+J28+F28 -> 0 | V28: =O28+P28-Q28-R28 -> 0
A29: 10221 | B29: Выявленная в плановом периоде прибыль прошлых лет, поступление прибыли прошлых лет, компенсационные выплаты | G29: =C29+D29-E29-F29 -> 0 | K29: =G29+H29-I29-J29 -> 0 | O29: =K29+L29-M29-N29 -> 0 | S29: =P29+L29+H29+D29 -> 0 | T29: =Q29+M29+I29+E29 -> 0 | U29: =R29+N29+J29+F29 -> 0 | V29: =O29+P29-Q29-R29 -> 0
A30: 10222 | B30: Суммы кредиторской и депонентской задолженности, по которой истек срок исковой давности | G30: =C30+D30-E30-F30 -> 0 | K30: =G30+H30-I30-J30 -> 0 | O30: =K30+L30-M30-N30 -> 0 | S30: =P30+L30+H30+D30 -> 0 | T30: =Q30+M30+I30+E30 -> 0 | U30: =R30+N30+J30+F30 -> 0 | V30: =O30+P30-Q30-R30 -> 0
A31: 10230 | B31: Доходы от операций с иностранной валютой и переоценки валютных денежных средств и эквивалентов | G31: =C31+D31-E31-F31 -> 0 | K31: =G31+H31-I31-J31 -> 0 | O31: =K31+L31-M31-N31 -> 0 | S31: =P31+L31+H31+D31 -> 0 | T31: =Q31+M31+I31+E31 -> 0 | U31: =R31+N31+J31+F31 -> 0 | V31: =O31+P31-Q31-R31 -> 0
A32: 10240 | B32: Суммы страхового возмещения и покрытия из других источников | G32: =C32+D32-E32-F32 -> 0 | K32: =G32+H32-I32-J32 -> 0 | O32: =K32+L32-M32-N32 -> 0 | S32: =P32+L32+H32+D32 -> 0 | T32: =Q32+M32+I32+E32 -> 0 | U32: =R32+N32+J32+F32 -> 0 | V32: =O32+P32-Q32-R32 -> 0
A33: 10241 | B33: Стоимость материальных ценностей, остающихся от списания непригодных к восстановлению и дальнейшему использованию активов | G33: =C33+D33-E33-F33 -> 0 | K33: =G33+H33-I33-J33 -> 0 | O33: =K33+L33-M33-N33 -> 0 | S33: =P33+L33+H33+D33 -> 0 | T33: =Q33+M33+I33+E33 -> 0 | U33: =R33+N33+J33+F33 -> 0 | V33: =O33+P33-Q33-R33 -> 0
A34: 10260 | B34: Кредиты и займы (кредитные договоры) | G34: =C34+D34-E34-F34 -> 0 | K34: =G34+H34-I34-J34 -> 0 | O34: =K34+L34-M34-N34 -> 0 | S34: =P34+L34+H34+D34 -> 0 | T34: =Q34+M34+I34+E34 -> 0 | U34: =R34+N34+J34+F34 -> 0 | V34: =O34+P34-Q34-R34 -> 0
A35: 10299 | B35: Прочие финансируемые доходы | G35: =C35+D35-E35-F35 -> 0 | K35: =G35+H35-I35-J35 -> 0 | O35: =K35+L35-M35-N35 -> 0 | S35: =P35+L35+H35+D35 -> 0 | T35: =Q35+M35+I35+E35 -> 0 | U35: =R35+N35+J35+F35 -> 0 | V35: =O35+P35-Q35-R35 -> 0
A36: 10400 | B36: Финансовая поддержка сторонних организаций | G36: =C36+D36-E36-F36 -> 0 | K36: =G36+H36-I36-J36 -> 0 | O36: =K36+L36-M36-N36 -> 0 | S36: =P36+L36+H36+D36 -> 0 | T36: =Q36+M36+I36+E36 -> 0 | U36: =R36+N36+J36+F36 -> 0 | V36: =O36+P36-Q36-R36 -> 0
A37: 10500 | B37: Средства Федерального бюджета | C37: =SUM(C38:C40) -> 0 | D37: =SUM(D38:D40) -> 0 | E37: =SUM(E38:E40) -> 0 | F37: =SUM(F38:F40) -> 0 | G37: =C37+D37-E37-F37 -> 0 | H37: =SUM(H38:H40) -> 0 | I37: =SUM(I38:I40) -> 0 | J37: =SUM(J38:J40) -> 0 | K37: =G37+H37-I37-J37 -> 0 | L37: =SUM(L38:L40) -> 0 | M37: =SUM(M38:M40) -> 0 | N37: =SUM(N38:N40) -> 0 | O37: =K37+L37-M37-N37 -> 0 | P37: =SUM(P38:P40) -> 0 | Q37: =SUM(Q38:Q40) -> 0 | R37: =SUM(R38:R40) -> 0 | S37: =P37+L37+H37+D37 -> 0 | T37: =Q37+M37+I37+E37 -> 0 | U37: =R37+N37+J37+F37 -> 0 | V37: =O37+P37-Q37-R37 -> 0
A38: 10520 | B38: На обеспечение функционирования Предприятия | G38: =C38+D38-E38-F38 -> 0 | K38: =G38+H38-I38-J38 -> 0 | O38: =K38+L38-M38-N38 -> 0 | S38: =P38+L38+H38+D38 -> 0 | T38: =Q38+M38+I38+E38 -> 0 | U38: =R38+N38+J38+F38 -> 0 | V38: =O38+P38-Q38-R38 -> 0
A39: 10530 | B39: На возмещение затрат, понесенных при осуществлении закупки средств радиотехнического обеспечения полетов и авиационной электросвязи для полетов беспилотных воздушных судов | G39: =C39+D39-E39-F39 -> 0 | K39: =G39+H39-I39-J39 -> 0 | O39: =K39+L39-M39-N39 -> 0 | S39: =P39+L39+H39+D39 -> 0 | T39: =Q39+M39+I39+E39 -> 0 | U39: =R39+N39+J39+F39 -> 0 | V39: =O39+P39-Q39-R39 -> 0
A40: 10540 | B40: На обеспечение реализации мероприятий, связанных с внедрением в эксплуатацию унифицированной инфраструктуры государственного поставщика услуг по обслуживанию линий управления БАС | G40: =C40+D40-E40-F40 -> 0 | K40: =G40+H40-I40-J40 -> 0 | O40: =K40+L40-M40-N40 -> 0 | S40: =P40+L40+H40+D40 -> 0 | T40: =Q40+M40+I40+E40 -> 0 | U40: =R40+N40+J40+F40 -> 0 | V40: =O40+P40-Q40-R40 -> 0
A41: 10600 | B41: Средства бюджетов субъектов РФ и местных бюджетов | C41: =SUM(C42:C44) -> 0 | D41: =SUM(D42:D44) -> 0 | E41: =SUM(E42:E44) -> 0 | F41: =SUM(F42:F44) -> 0 | G41: =C41+D41-E41-F41 -> 0 | H41: =SUM(H42:H44) -> 0 | I41: =SUM(I42:I44) -> 0 | J41: =SUM(J42:J44) -> 0 | K41: =G41+H41-I41-J41 -> 0 | L41: =SUM(L42:L44) -> 0 | M41: =SUM(M42:M44) -> 0 | N41: =SUM(N42:N44) -> 0 | O41: =K41+L41-M41-N41 -> 0 | P41: =SUM(P42:P44) -> 0 | Q41: =SUM(Q42:Q44) -> 0 | R41: =SUM(R42:R44) -> 0 | S41: =P41+L41+H41+D41 -> 0 | T41: =Q41+M41+I41+E41 -> 0 | U41: =R41+N41+J41+F41 -> 0 | V41: =O41+P41-Q41-R41 -> 0
A42: 10601 | B42: Средства бюджетов субъектов РФ | G42: =C42+D42-E42-F42 -> 0 | K42: =G42+H42-I42-J42 -> 0 | O42: =K42+L42-M42-N42 -> 0 | S42: =P42+L42+H42+D42 -> 0 | T42: =Q42+M42+I42+E42 -> 0 | U42: =R42+N42+J42+F42 -> 0 | V42: =O42+P42-Q42-R42 -> 0
A43: 10602 | B43: Средства местных бюджетов | G43: =C43+D43-E43-F43 -> 0 | K43: =G43+H43-I43-J43 -> 0 | O43: =K43+L43-M43-N43 -> 0 | S43: =P43+L43+H43+D43 -> 0 | T43: =Q43+M43+I43+E43 -> 0 | U43: =R43+N43+J43+F43 -> 0 | V43: =O43+P43-Q43-R43 -> 0
A44: 10603 | B44: Средства прочих источников | G44: =C44+D44-E44-F44 -> 0 | K44: =G44+H44-I44-J44 -> 0 | O44: =K44+L44-M44-N44 -> 0 | S44: =P44+L44+H44+D44 -> 0 | T44: =Q44+M44+I44+E44 -> 0 | U44: =R44+N44+J44+F44 -> 0 | V44: =O44+P44-Q44-R44 -> 0
A45: 10700 | B45: Возврат денежных средств по расходам прошлых периодов | C45: =C46+C47 -> 0 | D45: =D46+D47 -> 0 | E45: =E46+E47 -> 0 | F45: =F46+F47 -> 0 | G45: =C45+D45-E45-F45 -> 0 | H45: =H46+H47 -> 0 | I45: =I46+I47 -> 0 | J45: =J46+J47 -> 0 | K45: =G45+H45-I45-J45 -> 0 | L45: =L46+L47 -> 0 | M45: =M46+M47 -> 0 | N45: =N46+N47 -> 0 | O45: =K45+L45-M45-N45 -> 0 | P45: =P46+P47 -> 0 | Q45: =Q46+Q47 -> 0 | R45: =R46+R47 -> 0 | S45: =P45+L45+H45+D45 -> 0 | T45: =Q45+M45+I45+E45 -> 0 | U45: =R45+N45+J45+F45 -> 0 | V45: =O45+P45-Q45-R45 -> 0
A46: 10701 | B46: Возврат денежных средств по централизованным расходам | G46: =C46+D46-E46-F46 -> 0 | K46: =G46+H46-I46-J46 -> 0 | O46: =K46+L46-M46-N46 -> 0 | S46: =P46+L46+H46+D46 -> 0 | T46: =Q46+M46+I46+E46 -> 0 | U46: =R46+N46+J46+F46 -> 0 | V46: =O46+P46-Q46-R46 -> 0
A47: 10702 | B47: Возврат денежных средств по расходам ПДФ | G47: =C47+D47-E47-F47 -> 0 | K47: =G47+H47-I47-J47 -> 0 | O47: =K47+L47-M47-N47 -> 0 | S47: =P47+L47+H47+D47 -> 0 | T47: =Q47+M47+I47+E47 -> 0 | U47: =R47+N47+J47+F47 -> 0 | V47: =O47+P47-Q47-R47 -> 0
A48: 10300 | B48: Централизованное финансирование (10310+10320-31000)** | C48: =C49+C50-C156 -> 0 | D48: =D49+D50-D156 -> 0 | E48: =E49+E50-E156 -> 0 | F48: =F49+F50-F156 -> 0 | G48: =C48+D48-E48-F48 -> 0 | H48: =H49+H50-H156 -> 0 | I48: =I49+I50-I156 -> 0 | J48: =J49+J50-J156 -> 0 | K48: =G48+H48-I48-J48 -> 0 | L48: =L49+L50-L156 -> 0 | M48: =M49+M50-M156 -> 0 | N48: =N49+N50-N156 -> 0 | O48: =K48+L48-M48-N48 -> 0 | P48: =P49+P50-P156 -> 0 | Q48: =Q49+Q50-Q156 -> 0 | R48: =R49+R50-R156 -> 0 | S48: =P48+L48+H48+D48 -> 0 | T48: =Q48+M48+I48+E48 -> 0 | U48: =R48+N48+J48+F48 -> 0 | V48: =O48+P48-Q48-R48 -> 0
A49: 10310 | B49: Централизованное финансирование филиала | G49: =C49+D49-E49-F49 -> 0 | K49: =G49+H49-I49-J49 -> 0 | O49: =K49+L49-M49-N49 -> 0 | S49: =P49+L49+H49+D49 -> 0 | T49: =Q49+M49+I49+E49 -> 0 | U49: =R49+N49+J49+F49 -> 0 | V49: =O49+P49-Q49-R49 -> 0
A50: 10320 | B50: Централизованное финансирование сверх лимита | G50: =C50+D50-E50-F50 -> 0 | K50: =G50+H50-I50-J50 -> 0 | O50: =K50+L50-M50-N50 -> 0 | S50: =P50+L50+H50+D50 -> 0 | T50: =Q50+M50+I50+E50 -> 0 | U50: =R50+N50+J50+F50 -> 0 | V50: =O50+P50-Q50-R50 -> 0
A51: 02000 | B51: Движение денежных средств, не влияющее на сальдо обязательств (02200+02300) | C51: =SUM(C52:C53) -> 0 | D51: =SUM(D52:D53) -> 0 | E51: =SUM(E52:E53) -> 0 | F51: =SUM(F52:F53) -> 0 | G51: =C51+D51-E51-F51 -> 0 | H51: =SUM(H52:H53) -> 0 | I51: =SUM(I52:I53) -> 0 | J51: =SUM(J52:J53) -> 0 | K51: =G51+H51-I51-J51 -> 0 | L51: =SUM(L52:L53) -> 0 | M51: =SUM(M52:M53) -> 0 | N51: =SUM(N52:N53) -> 0 | O51: =K51+L51-M51-N51 -> 0 | P51: =SUM(P52:P53) -> 0 | Q51: =SUM(Q52:Q53) -> 0 | R51: =SUM(R52:R53) -> 0 | S51: =P51+L51+H51+D51 -> 0 | T51: =Q51+M51+I51+E51 -> 0 | U51: =R51+N51+J51+F51 -> 0 | V51: =O51+P51-Q51-R51 -> 0
A52: 02200 | B52: Прочие поступления денежных средств, не влияющие на сальдо обязательств | G52: =C52+D52-E52-F52 -> 0 | K52: =G52+H52-I52-J52 -> 0 | O52: =K52+L52-M52-N52 -> 0 | S52: =P52+L52+H52+D52 -> 0 | T52: =Q52+M52+I52+E52 -> 0 | U52: =R52+N52+J52+F52 -> 0 | V52: =O52+P52-Q52-R52 -> 0
A53: 02300 | B53: Поступление от контрагента финансового обеспечения выданного | G53: =C53+D53-E53-F53 -> 0 | K53: =G53+H53-I53-J53 -> 0 | O53: =K53+L53-M53-N53 -> 0 | S53: =P53+L53+H53+D53 -> 0 | T53: =Q53+M53+I53+E53 -> 0 | U53: =R53+N53+J53+F53 -> 0 | V53: =O53+P53-Q53-R53 -> 0
A54: 20000 | B54: РАСХОДЫ (ПЛАТЕЖИ) (21000+22000) | C54: =C55+C67 -> 0 | D54: =D55+D67 -> 0 | E54: =E55+E67 -> 0 | F54: =F55+F67 -> 0 | G54: =C54+D54-E54-F54 -> 0 | H54: =H55+H67 -> 0 | I54: =I55+I67 -> 0 | J54: =J55+J67 -> 0 | K54: =G54+H54-I54-J54 -> 0 | L54: =L55+L67 -> 0 | M54: =M55+M67 -> 0 | N54: =N55+N67 -> 0 | O54: =K54+L54-M54-N54 -> 0 | P54: =P55+P67 -> 0 | Q54: =Q55+Q67 -> 0 | R54: =R55+R67 -> 0 | S54: =P54+L54+H54+D54 -> 0 | T54: =Q54+M54+I54+E54 -> 0 | U54: =R54+N54+J54+F54 -> 0 | V54: =O54+P54-Q54-R54 -> 0
A55: 21000 | B55: КАПИТАЛЬНЫЕ РАСХОДЫ (20701+20703) | C55: =C64+C56 -> 0 | D55: =D64+D56 -> 0 | E55: =E64+E56 -> 0 | F55: =F64+F56 -> 0 | G55: =C55+D55-E55-F55 -> 0 | H55: =H64+H56 -> 0 | I55: =I64+I56 -> 0 | J55: =J64+J56 -> 0 | K55: =G55+H55-I55-J55 -> 0 | L55: =L64+L56 -> 0 | M55: =M64+M56 -> 0 | N55: =N64+N56 -> 0 | O55: =K55+L55-M55-N55 -> 0 | P55: =P64+P56 -> 0 | Q55: =Q64+Q56 -> 0 | R55: =R64+R56 -> 0 | S55: =P55+L55+H55+D55 -> 0 | T55: =Q55+M55+I55+E55 -> 0 | U55: =R55+N55+J55+F55 -> 0 | V55: =O55+P55-Q55-R55 -> 0
A56: 20703 | B56: Расходы по централизованным планам капитальных вложений | C56: =SUM(C57:C63) -> 0 | D56: =SUM(D57:D63) -> 0 | E56: =SUM(E57:E63) -> 0 | F56: =SUM(F57:F63) -> 0 | G56: =SUM(G57:G63) -> 0 | H56: =SUM(H57:H63) -> 0 | I56: =SUM(I57:I63) -> 0 | J56: =SUM(J57:J63) -> 0 | ... V56: =SUM(V57:V63) -> 0
A57: 2070311 | B57: Государственная программа Российской Федерации "Космическая деятельность России» | G57: =C57+D57-E57-F57 -> 0 | K57: =G57+H57-I57-J57 -> 0 | O57: =K57+L57-M57-N57 -> 0 | S57: =P57+L57+H57+D57 -> 0 | T57: =Q57+M57+I57+E57 -> 0 | U57: =R57+N57+J57+F57 -> 0 | V57: =O57+P57-Q57-R57 -> 0
A58: 2070314 | B58: Централизованный план мероприятий по реализации федерального проекта «Развитие инфраструктуры, обеспечение безопасности и формирование специализированной системы сертификации беспилотных авиационных систем» ФГУП «Госкорпорация по ОрВД» | G58: =C58+D58-E58-F58 -> 0 | K58: =G58+H58-I58-J58 -> 0 | O58: =K58+L58-M58-N58 -> 0 | S58: =P58+L58+H58+D58 -> 0 | T58: =Q58+M58+I58+E58 -> 0 | U58: =R58+N58+J58+F58 -> 0 | V58: =O58+P58-Q58-R58 -> 0
A59: 2070315 | B59: Централизованный план по развитию опорной сети аэродромов объектов ЕС ОрВД | G59: =C59+D59-E59-F59 -> 0 | K59: =G59+H59-I59-J59 -> 0 | O59: =K59+L59-M59-N59 -> 0 | S59: =P59+L59+H59+D59 -> 0 | T59: =Q59+M59+I59+E59 -> 0 | U59: =R59+N59+J59+F59 -> 0 | V59: =O59+P59-Q59-R59 -> 0
A60: 2070322 | B60: Централизованный план строительства, оснащения и модернизации объектов ЕС ОрВД | G60: =C60+D60-E60-F60 -> 0 | K60: =G60+H60-I60-J60 -> 0 | O60: =K60+L60-M60-N60 -> 0 | S60: =P60+L60+H60+D60 -> 0 | T60: =Q60+M60+I60+E60 -> 0 | U60: =R60+N60+J60+F60 -> 0 | V60: =O60+P60-Q60-R60 -> 0
A61: 2070323 | B61: Централизованный план мероприятий по обеспечению информационной безопасности ФГУП «Госкорпорация по ОрВД» в части капитальных расходов | G61: =C61+D61-E61-F61 -> 0 | K61: =G61+H61-I61-J61 -> 0 | O61: =K61+L61-M61-N61 -> 0 | S61: =P61+L61+H61+D61 -> 0 | T61: =Q61+M61+I61+E61 -> 0 | U61: =R61+N61+J61+F61 -> 0 | V61: =O61+P61-Q61-R61 -> 0
A62: 2070324 | B62: Централизованный план мероприятий по развитию информационных технологий ФГУП «Госкорпорация по ОрВД» в части капитальных расходов | G62: =C62+D62-E62-F62 -> 0 | K62: =G62+H62-I62-J62 -> 0 | O62: =K62+L62-M62-N62 -> 0 | S62: =P62+L62+H62+D62 -> 0 | T62: =Q62+M62+I62+E62 -> 0 | U62: =R62+N62+J62+F62 -> 0 | V62: =O62+P62-Q62-R62 -> 0
A63: 2070391 | B63: Госэкспертиза проектно-сметной документации и сопровождение строительства | G63: =C63+D63-E63-F63 -> 0 | K63: =G63+H63-I63-J63 -> 0 | O63: =K63+L63-M63-N63 -> 0 | S63: =P63+L63+H63+D63 -> 0 | T63: =Q63+M63+I63+E63 -> 0 | U63: =R63+N63+J63+F63 -> 0 | V63: =O63+P63-Q63-R63 -> 0
A64: 20701 | B64: Расходы по Плану развития и поддержания работоспособности объектов ЕС ОрВД в компетенции филиала | C64: =C66+C65 -> 0 | D64: =D66+D65 -> 0 | E64: =E66+E65 -> 0 | F64: =F66+F65 -> 0 | G64: =C64+D64-E64-F64 -> 0 | H64: =H66+H65 -> 0 | I64: =I66+I65 -> 0 | J64: =J66+J65 -> 0 | K64: =G64+H64-I64-J64 -> 0 | L64: =L66+L65 -> 0 | M64: =M66+M65 -> 0 | N64: =N66+N65 -> 0 | O64: =O66+O65 -> 0 | P64: =P66+P65 -> 0 | Q64: =Q66+Q65 -> 0 | R64: =R66+R65 -> 0 | S64: =S66+S65 -> 0 | ... V64: =V66+V65 -> 0
A65: 207011 | B65: План развития и поддержания работоспособности объектов ЕС ОрВД (часть 1) | G65: =C65+D65-E65-F65 -> 0 | K65: =G65+H65-I65-J65 -> 0 | O65: =K65+L65-M65-N65 -> 0 | S65: =P65+L65+H65+D65 -> 0 | T65: =Q65+M65+I65+E65 -> 0 | U65: =R65+N65+J65+F65 -> 0 | V65: =O65+P65-Q65-R65 -> 0
A66: 207012 | B66: План развития и поддержания работоспособности объектов ЕС ОрВД (часть 2) | G66: =C66+D66-E66-F66 -> 0 | K66: =G66+H66-I66-J66 -> 0 | O66: =K66+L66-M66-N66 -> 0 | S66: =P66+L66+H66+D66 -> 0 | T66: =Q66+M66+I66+E66 -> 0 | U66: =R66+N66+J66+F66 -> 0 | V66: =O66+P66-Q66-R66 -> 0
A67: 22000 | B67: ТЕКУЩИЕ РАСХОДЫ (20300+20500+20510+20600+20100+20800+20810) | C67: =C68+C146+C133+C147+C150+C154 -> 0 | D67: =D68+D146+D133+D147+D150+D154 -> 0 | E67: =E68+E146+E133+E147+E150+E154 -> 0 | F67: =F68+F133+F146+F147+F150+F154 -> 0 | G67: =C67+D67-E67-F67 -> 0 | H67: =H68+H146+H133+H147+H150+H154 -> 0 | I67: =I68+I146+I133+I147+I150+I154 -> 0 | J67: =J68+J133+J146+J147+J150+J154 -> 0 | K67: =G67+H67-I67-J67 -> 0 | L67: =L68+L146+L133+L147+L150+L154 -> 0 | M67: =M68+M146+M133+M147+M150+M154 -> 0 | N67: =N68+N133+N146+N147+N150+N154 -> 0 | O67: =K67+L67-M67-N67 -> 0 | P67: =P68+P146+P133+P147+P150+P154 -> 0 | Q67: =Q68+Q146+Q133+Q147+Q150+Q154 -> 0 | R67: =R68+R133+R146+R147+R150+R154 -> 0 | S67: =P67+L67+H67+D67 -> 0 | T67: =Q67+M67+I67+E67 -> 0 | U67: =R67+N67+J67+F67 -> 0 | V67: =O67+P67-Q67-R67 -> 0 | Y67: =(T68-(T70+T76+T78+T97+T98+T101+T103+T106+T118+T119+T121+T124+T128+T132))+T134+T138+T143+T145+T146 -> 0 | Z67: лимит эксплуатационных расходов, включая РВР
A68: 20300 | B68: Расходы на производство продукции, работ, услуг | C68: =SUM(C69:C78,C79,C82,C85,C88,C89,C95,C96:C100,C103,C104,C105,C108,C109:C120,C123,C126:C127,C130) -> 0 | D68: =SUM(D69:D78,D79,D82,D85,D88,D89,D95,D96:D100,D103,D104,D105,D108,D109:D120,D123,D126:D127,D130) -> 0 | E68: =SUM(E69:E78,E79,E82,E85,E88,E89,E95,E96:E100,E103,E104,E105,E108,E109:E120,E123,E126:E127,E130) -> 0 | F68: =SUM(F69:F78,F79,F82,F85,F88,F89,F95,F96:F100,F103,F104,F105,F108,F109:F120,F123,F126:F127,F130) -> 0 | G68: =C68+D68-E68-F68 -> 0 | H68: =SUM(H69:H78,H79,H82,H85,H88,H89,H95,H96:H100,H103,H104,H105,H108,H109:H120,H123,H126:H127,H130) -> 0 | I68: =SUM(I69:I78,I79,I82,I85,I88,I89,I95,I96:I100,I103,I104,I105,I108,I109:I120,I123,I126:I127,I130) -> 0 | J68: =SUM(J69:J78,J79,J82,J85,J88,J89,J95,J96:J100,J103,J104,J105,J108,J109:J120,J123,J126:J127,J130) -> 0 | K68: =G68+H68-I68-J68 -> 0 | L68: =SUM(L69:L78,L79,L82,L85,L88,L89,L95,L96:L100,L103,L104,L105,L108,L109:L120,L123,L126:L127,L130) -> 0 | M68: =SUM(M69:M78,M79,M82,M85,M88,M89,M95,M96:M100,M103,M104,M105,M108,M109:M120,M123,M126:M127,M130) -> 0 | N68: =SUM(N69:N78,N79,N82,N85,N88,N89,N95,N96:N100,N103,N104,N105,N108,N109:N120,N123,N126:N127,N130) -> 0 | O68: =K68+L68-M68-N68 -> 0 | P68: =SUM(P69:P78,P79,P82,P85,P88,P89,P95,P96:P100,P103,P104,P105,P108,P109:P120,P123,P126:P127,P130) -> 0 | Q68: =SUM(Q69:Q78,Q79,Q82,Q85,Q88,Q89,Q95,Q96:Q100,Q103,Q104,Q105,Q108,Q109:Q120,Q123,Q126:Q127,Q130) -> 0 | R68: =SUM(R69:R78,R79,R82,R85,R88,R89,R95,R96:R100,R103,R104,R105,R108,R109:R120,R123,R126:R127,R130) -> 0 | S68: =P68+L68+H68+D68 -> 0 | T68: =Q68+M68+I68+E68 -> 0 | U68: =R68+N68+J68+F68 -> 0 | V68: =O68+P68-Q68-R68 -> 0
A69: 20301 | B69: Услуги связи | G69: =C69+D69-E69-F69 -> 0 | K69: =G69+H69-I69-J69 -> 0 | O69: =K69+L69-M69-N69 -> 0 | S69: =P69+L69+H69+D69 -> 0 | T69: =Q69+M69+I69+E69 -> 0 | U69: =R69+N69+J69+F69 -> 0 | V69: =O69+P69-Q69-R69 -> 0
A70: 20302 | B70: ПСО, тренировочные полеты | G70: =C70+D70-E70-F70 -> 0 | K70: =G70+H70-I70-J70 -> 0 | O70: =K70+L70-M70-N70 -> 0 | S70: =P70+L70+H70+D70 -> 0 | T70: =Q70+M70+I70+E70 -> 0 | U70: =R70+N70+J70+F70 -> 0 | V70: =O70+P70-Q70-R70 -> 0
A71: 20303 | B71: Электроэнергия | G71: =C71+D71-E71-F71 -> 0 | K71: =G71+H71-I71-J71 -> 0 | O71: =K71+L71-M71-N71 -> 0 | S71: =P71+L71+H71+D71 -> 0 | T71: =Q71+M71+I71+E71 -> 0 | U71: =R71+N71+J71+F71 -> 0 | V71: =O71+P71-Q71-R71 -> 0
A72: 20304 | B72: Расходы по содержанию зданий и сооружений, коммунальные услуги (кроме электроэнергии) | G72: =C72+D72-E72-F72 -> 0 | K72: =G72+H72-I72-J72 -> 0 | O72: =K72+L72-M72-N72 -> 0 | S72: =P72+L72+H72+D72 -> 0 | T72: =Q72+M72+I72+E72 -> 0 | U72: =R72+N72+J72+F72 -> 0 | V72: =O72+P72-Q72-R72 -> 0
A73: 20305 | B73: Материалы | G73: =C73+D73-E73-F73 -> 0 | K73: =G73+H73-I73-J73 -> 0 | O73: =K73+L73-M73-N73 -> 0 | S73: =P73+L73+H73+D73 -> 0 | T73: =Q73+M73+I73+E73 -> 0 | U73: =R73+N73+J73+F73 -> 0 | V73: =O73+P73-Q73-R73 -> 0
A74: 20306 | B74: ГСМ | G74: =C74+D74-E74-F74 -> 0 | K74: =G74+H74-I74-J74 -> 0 | O74: =K74+L74-M74-N74 -> 0 | S74: =P74+L74+H74+D74 -> 0 | T74: =Q74+M74+I74+E74 -> 0 | U74: =R74+N74+J74+F74 -> 0 | V74: =O74+P74-Q74-R74 -> 0
A75: 20307 | B75: Расходные материалы, инструменты, инвентарь, прочие материалы, МПЗ | G75: =C75+D75-E75-F75 -> 0 | K75: =G75+H75-I75-J75 -> 0 | O75: =K75+L75-M75-N75 -> 0 | S75: =P75+L75+H75+D75 -> 0 | T75: =Q75+M75+I75+E75 -> 0 | U75: =R75+N75+J75+F75 -> 0 | V75: =O75+P75-Q75-R75 -> 0
A76: 20308 | B76: Авиаметеообеспечение | G76: =C76+D76-E76-F76 -> 0 | K76: =G76+H76-I76-J76 -> 0 | O76: =K76+L76-M76-N76 -> 0 | S76: =P76+L76+H76+D76 -> 0 | T76: =Q76+M76+I76+E76 -> 0 | U76: =R76+N76+J76+F76 -> 0 | V76: =O76+P76-Q76-R76 -> 0
A77: 20309 | B77: Услуги по медицинскому обеспечению | G77: =C77+D77-E77-F77 -> 0 | K77: =G77+H77-I77-J77 -> 0 | O77: =K77+L77-M77-N77 -> 0 | S77: =P77+L77+H77+D77 -> 0 | T77: =Q77+M77+I77+E77 -> 0 | U77: =R77+N77+J77+F77 -> 0 | V77: =O77+P77-Q77-R77 -> 0
A78: 20380 | B78: Летные проверки | G78: =C78+D78-E78-F78 -> 0 | K78: =G78+H78-I78-J78 -> 0 | O78: =K78+L78-M78-N78 -> 0 | S78: =P78+L78+H78+D78 -> 0 | T78: =Q78+M78+I78+E78 -> 0 | U78: =R78+N78+J78+F78 -> 0 | V78: =O78+P78-Q78-R78 -> 0
A79: 20401 | B79: Профессиональная подготовка и переподготовка | C79: =C80+C81 -> 0 | D79: =D80+D81 -> 0 | E79: =E80+E81 -> 0 | F79: =F80+F81 -> 0 | G79: =C79+D79-E79-F79 -> 0 | H79: =H80+H81 -> 0 | I79: =I80+I81 -> 0 | J79: =J80+J81 -> 0 | K79: =G79+H79-I79-J79 -> 0 | L79: =L80+L81 -> 0 | M79: =M80+M81 -> 0 | N79: =N80+N81 -> 0 | O79: =K79+L79-M79-N79 -> 0 | P79: =P80+P81 -> 0 | Q79: =Q80+Q81 -> 0 | R79: =R80+R81 -> 0 | S79: =P79+L79+H79+D79 -> 0 | T79: =Q79+M79+I79+E79 -> 0 | U79: =R79+N79+J79+F79 -> 0 | V79: =O79+P79-Q79-R79 -> 0
A80: 204011 | B80: Подготовка и переподготовка кадров (ПДФ) | G80: =C80+D80-E80-F80 -> 0 | K80: =G80+H80-I80-J80 -> 0 | O80: =K80+L80-M80-N80 -> 0 | S80: =P80+L80+H80+D80 -> 0 | T80: =Q80+M80+I80+E80 -> 0 | U80: =R80+N80+J80+F80 -> 0 | V80: =O80+P80-Q80-R80 -> 0
A81: 204012 | B81: Командировочные расходы (КПК, ПДФ) | G81: =C81+D81-E81-F81 -> 0 | K81: =G81+H81-I81-J81 -> 0 | O81: =K81+L81-M81-N81 -> 0 | S81: =P81+L81+H81+D81 -> 0 | T81: =Q81+M81+I81+E81 -> 0 | U81: =R81+N81+J81+F81 -> 0 | V81: =O81+P81-Q81-R81 -> 0
A82: 20403 | B82: Аренда ОПФ. Регистрация имущественных прав | C82: =C83+C84 -> 0 | D82: =D83+D84 -> 0 | E82: =E83+E84 -> 0 | F82: =F83+F84 -> 0 | G82: =C82+D82-E82-F82 -> 0 | H82: =H83+H84 -> 0 | I82: =I83+I84 -> 0 | J82: =J83+J84 -> 0 | K82: =G82+H82-I82-J82 -> 0 | L82: =L83+L84 -> 0 | M82: =M83+M84 -> 0 | N82: =N83+N84 -> 0 | O82: =K82+L82-M82-N82 -> 0 | P82: =P83+P84 -> 0 | Q82: =Q83+Q84 -> 0 | R82: =R83+R84 -> 0 | S82: =P82+L82+H82+D82 -> 0 | T82: =Q82+M82+I82+E82 -> 0 | U82: =R82+N82+J82+F82 -> 0 | V82: =O82+P82-Q82-R82 -> 0
A83: 204031 | B83: Аренда ОПФ | G83: =C83+D83-E83-F83 -> 0 | K83: =G83+H83-I83-J83 -> 0 | O83: =K83+L83-M83-N83 -> 0 | S83: =P83+L83+H83+D83 -> 0 | T83: =Q83+M83+I83+E83 -> 0 | U83: =R83+N83+J83+F83 -> 0 | V83: =O83+P83-Q83-R83 -> 0
A84: 204032 | B84: Регистрация имущественных прав | G84: =C84+D84-E84-F84 -> 0 | K84: =G84+H84-I84-J84 -> 0 | O84: =K84+L84-M84-N84 -> 0 | S84: =P84+L84+H84+D84 -> 0 | T84: =Q84+M84+I84+E84 -> 0 | U84: =R84+N84+J84+F84 -> 0 | V84: =O84+P84-Q84-R84 -> 0
A85: 20404 | B85: Аренда земли. Регистрация прав на землю, землеустроительные работы | C85: =C86+C87 -> 0 | D85: =D86+D87 -> 0 | E85: =E86+E87 -> 0 | F85: =F86+F87 -> 0 | G85: =C85+D85-E85-F85 -> 0 | H85: =H86+H87 -> 0 | I85: =I86+I87 -> 0 | J85: =J86+J87 -> 0 | K85: =G85+H85-I85-J85 -> 0 | L85: =L86+L87 -> 0 | M85: =M86+M87 -> 0 | N85: =N86+N87 -> 0 | O85: =K85+L85-M85-N85 -> 0 | P85: =P86+P87 -> 0 | Q85: =Q86+Q87 -> 0 | R85: =R86+R87 -> 0 | S85: =P85+L85+H85+D85 -> 0 | T85: =Q85+M85+I85+E85 -> 0 | U85: =R85+N85+J85+F85 -> 0 | V85: =O85+P85-Q85-R85 -> 0
A86: 204041 | B86: Аренда земли | G86: =C86+D86-E86-F86 -> 0 | K86: =G86+H86-I86-J86 -> 0 | O86: =K86+L86-M86-N86 -> 0 | S86: =P86+L86+H86+D86 -> 0 | T86: =Q86+M86+I86+E86 -> 0 | U86: =R86+N86+J86+F86 -> 0 | V86: =O86+P86-Q86-R86 -> 0
A87: 204042 | B87: Регистрация прав на землю, землеустроительные работы | G87: =C87+D87-E87-F87 -> 0 | K87: =G87+H87-I87-J87 -> 0 | O87: =K87+L87-M87-N87 -> 0 | S87: =P87+L87+H87+D87 -> 0 | T87: =Q87+M87+I87+E87 -> 0 | U87: =R87+N87+J87+F87 -> 0 | V87: =O87+P87-Q87-R87 -> 0
A88: 20405 | B88: Командировки (кроме КПК) | G88: =C88+D88-E88-F88 -> 0 | K88: =G88+H88-I88-J88 -> 0 | O88: =K88+L88-M88-N88 -> 0 | S88: =P88+L88+H88+D88 -> 0 | T88: =Q88+M88+I88+E88 -> 0 | U88: =R88+N88+J88+F88 -> 0 | V88: =O88+P88-Q88-R88 -> 0
A89: 20406 | B89: Налоги, сборы, платежи | C89: =SUM(C90:C94) -> 0 | D89: =SUM(D90:D94) -> 0 | E89: =SUM(E90:E94) -> 0 | F89: =SUM(F90:F94) -> 0 | G89: =C89+D89-E89-F89 -> 0 | H89: =SUM(H90:H94) -> 0 | I89: =SUM(I90:I94) -> 0 | J89: =SUM(J90:J94) -> 0 | K89: =G89+H89-I89-J89 -> 0 | L89: =SUM(L90:L94) -> 0 | M89: =SUM(M90:M94) -> 0 | N89: =SUM(N90:N94) -> 0 | O89: =K89+L89-M89-N89 -> 0 | P89: =SUM(P90:P94) -> 0 | Q89: =SUM(Q90:Q94) -> 0 | R89: =SUM(R90:R94) -> 0 | S89: =P89+L89+H89+D89 -> 0 | T89: =Q89+M89+I89+E89 -> 0 | U89: =R89+N89+J89+F89 -> 0 | V89: =O89+P89-Q89-R89 -> 0
A90: 204061 | B90: Транспортный налог | G90: =C90+D90-E90-F90 -> 0 | K90: =G90+H90-I90-J90 -> 0 | O90: =K90+L90-M90-N90 -> 0 | S90: =P90+L90+H90+D90 -> 0 | T90: =Q90+M90+I90+E90 -> 0 | U90: =R90+N90+J90+F90 -> 0 | V90: =O90+P90-Q90-R90 -> 0
A91: 204062 | B91: Земельный налог | G91: =C91+D91-E91-F91 -> 0 | K91: =G91+H91-I91-J91 -> 0 | O91: =K91+L91-M91-N91 -> 0 | S91: =P91+L91+H91+D91 -> 0 | T91: =Q91+M91+I91+E91 -> 0 | U91: =R91+N91+J91+F91 -> 0 | V91: =O91+P91-Q91-R91 -> 0
A92: 204063 | B92: Налог на имущество | G92: =C92+D92-E92-F92 -> 0 | K92: =G92+H92-I92-J92 -> 0 | O92: =K92+L92-M92-N92 -> 0 | S92: =P92+L92+H92+D92 -> 0 | T92: =Q92+M92+I92+E92 -> 0 | U92: =R92+N92+J92+F92 -> 0 | V92: =O92+P92-Q92-R92 -> 0
A93: 204064 | B93: Водный налог | G93: =C93+D93-E93-F93 -> 0 | K93: =G93+H93-I93-J93 -> 0 | O93: =K93+L93-M93-N93 -> 0 | S93: =P93+L93+H93+D93 -> 0 | T93: =Q93+M93+I93+E93 -> 0 | U93: =R93+N93+J93+F93 -> 0 | V93: =O93+P93-Q93-R93 -> 0
A94: 204065 | B94: Прочие налоги, сборы, платежи (кроме налога на прибыль) | G94: =C94+D94-E94-F94 -> 0 | K94: =G94+H94-I94-J94 -> 0 | O94: =K94+L94-M94-N94 -> 0 | S94: =P94+L94+H94+D94 -> 0 | T94: =Q94+M94+I94+E94 -> 0 | U94: =R94+N94+J94+F94 -> 0 | V94: =O94+P94-Q94-R94 -> 0
A95: 20407 | B95: Представительские расходы (кроме международных и корпоративных мероприятий по централизованным решениям) | G95: =C95+D95-E95-F95 -> 0 | K95: =G95+H95-I95-J95 -> 0 | O95: =K95+L95-M95-N95 -> 0 | S95: =P95+L95+H95+D95 -> 0 | T95: =Q95+M95+I95+E95 -> 0 | U95: =R95+N95+J95+F95 -> 0 | V95: =O95+P95-Q95-R95 -> 0
A96: 20408 | B96: Охрана имущества, включая ТО | G96: =C96+D96-E96-F96 -> 0 | K96: =G96+H96-I96-J96 -> 0 | O96: =K96+L96-M96-N96 -> 0 | S96: =P96+L96+H96+D96 -> 0 | T96: =Q96+M96+I96+E96 -> 0 | U96: =R96+N96+J96+F96 -> 0 | V96: =O96+P96-Q96-R96 -> 0
A97: 20421 | B97: Расходы на международные и корпоративные мероприятия | G97: =C97+D97-E97-F97 -> 0 | K97: =G97+H97-I97-J97 -> 0 | O97: =K97+L97-M97-N97 -> 0 | S97: =P97+L97+H97+D97 -> 0 | T97: =Q97+M97+I97+E97 -> 0 | U97: =R97+N97+J97+F97 -> 0 | V97: =O97+P97-Q97-R97 -> 0
A98: 20422 | B98: Аудит | G98: =C98+D98-E98-F98 -> 0 | K98: =G98+H98-I98-J98 -> 0 | O98: =K98+L98-M98-N98 -> 0 | S98: =P98+L98+H98+D98 -> 0 | T98: =Q98+M98+I98+E98 -> 0 | U98: =R98+N98+J98+F98 -> 0 | V98: =O98+P98-Q98-R98 -> 0
A99: 20423 | B99: Информационные, консультационные услуги | G99: =C99+D99-E99-F99 -> 0 | K99: =G99+H99-I99-J99 -> 0 | O99: =K99+L99-M99-N99 -> 0 | S99: =P99+L99+H99+D99 -> 0 | T99: =Q99+M99+I99+E99 -> 0 | U99: =R99+N99+J99+F99 -> 0 | V99: =O99+P99-Q99-R99 -> 0
A100: 20429.0 | B100: Страхование гражданской ответственности | C100: =C101+C102 -> 0 | D100: =D101+D102 -> 0 | E100: =E101+E102 -> 0 | F100: =F101+F102 -> 0 | G100: =C100+D100-E100-F100 -> 0 | H100: =H101+H102 -> 0 | I100: =I101+I102 -> 0 | J100: =J101+J102 -> 0 | K100: =G100+H100-I100-J100 -> 0 | L100: =L101+L102 -> 0 | M100: =M101+M102 -> 0 | N100: =N101+N102 -> 0 | O100: =K100+L100-M100-N100 -> 0 | P100: =P101+P102 -> 0 | Q100: =Q101+Q102 -> 0 | R100: =R101+R102 -> 0 | S100: =P100+L100+H100+D100 -> 0 | T100: =Q100+M100+I100+E100 -> 0 | U100: =R100+N100+J100+F100 -> 0 | V100: =O100+P100-Q100-R100 -> 0
...

Sheet Пр 10а БДДС  (помесячно)
O1: ПРИЛОЖЕНИЕ № 10а
K2: К ПОРЯДКУ ТЕКУЩЕГО ПЛАНИРОВАНИЯ ПРОИЗВОДСТВЕННО-ХОЗЯЙСТВЕННОЙ ДЕЯТЕЛЬНОСТИ ФГУП «ГОСКОРПОРАЦИЯ ПО ОрВД»
C3: Бюджет движения денежных средств
B4: по филиалу
B5: ФГУП «Госкорпорация по ОрВД» за
A6: (1-й квартал, 1-е полугодие, 9 месяцев, год) | S6: тыс.руб.
A7: № статьи ВПО | B7: Наименование статьи | S7: ИТОГО за год
C8: 1 кв-л | G8: 2 кв-л | K8: 3 кв-л | O8: 4 кв-л
C9: январь | D9: февраль | E9: март | F9: Итого 1 квартал | G9: апрель | H9: май | I9: июнь | J9: Итого 2 квартал | K9: июль | L9: август | M9: сентябрь | N9: Итого 3 квартал | O9: октябрь | P9: ноябрь | Q9: декабрь | R9: Итого 4 квартал
A10: 1 | B10: 2 | C10: 3 | D10: 4 | E10: 5 | F10: 6 | G10: 7 | H10: 8 | I10: 9 | J10: 10 | K10: 11 | L10: 12 | M10: 13 | N10: 14 | O10: 15 | P10: 16 | Q10: 17 | R10: 18 | S10: 19
A11: 01000 | B11: Остаток денежных средств на начало периода
A12: 10000 | B12: ДОХОДЫ (ПОСТУПЛЕНИЯ) (10100+10200+10400+10500+10600+10700) | C12: =C13+C18+C35+C36+C40+C44 -> 0 | D12: =D13+D18+D35+D36+D40+D44 -> 0 | E12: =E13+E18+E35+E36+E40+E44 -> 0 | F12: =F13+F18+F35+F36+F40+F44 -> 0 | G12: =G13+G18+G35+G36+G40+G44 -> 0 | H12: =H13+H18+H35+H36+H40+H44 -> 0 | I12: =I13+I18+I35+I36+I40+I44 -> 0 | J12: =J13+J18+J35+J36+J40+J44 -> 0 | ... S12: =S13+S18+S35+S36+S40+S44 -> 0
A13: 10100 | B13: Выручка (поступления) по обычным видам деятельности всего, в т.ч. | C13: =SUM(C14:C17) -> 0 | D13: =SUM(D14:D17) -> 0 | E13: =SUM(E14:E17) -> 0 | F13: =SUM(F14:F17) -> 0 | G13: =SUM(G14:G17) -> 0 | H13: =SUM(H14:H17) -> 0 | I13: =SUM(I14:I17) -> 0 | J13: =SUM(J14:J17) -> 0 | ... R13: =SUM(R14:R17) -> 0 | S13: =R13+N13+J13+F13 -> 0
A14: 10110 | B14: от АНО на маршрутах обслуживания воздушного движения | F14: =C14+D14+E14 -> 0 | J14: =G14+H14+I14 -> 0 | N14: =K14+L14+M14 -> 0 | R14: =O14+P14+Q14 -> 0 | S14: =R14+N14+J14+F14 -> 0
A15: 10120 | B15: от АНО в районах аэродромов | F15: =C15+D15+E15 -> 0 | J15: =G15+H15+I15 -> 0 | N15: =K15+L15+M15 -> 0 | R15: =O15+P15+Q15 -> 0 | S15: =R15+N15+J15+F15 -> 0
A16: 10140 | B16: от прочей деятельности | F16: =C16+D16+E16 -> 0 | J16: =G16+H16+I16 -> 0 | N16: =K16+L16+M16 -> 0 | R16: =O16+P16+Q16 -> 0 | S16: =R16+N16+J16+F16 -> 0
A17: 10150 | B17: Недополученные доходы от АНО полетов ВС пользователей ВП, освобожденных в соответствии с законодательством РФ от платы за АНО | F17: =C17+D17+E17 -> 0 | J17: =G17+H17+I17 -> 0 | N17: =K17+L17+M17 -> 0 | R17: =O17+P17+Q17 -> 0 | S17: =R17+N17+J17+F17 -> 0
A18: 10200 | B18: Прочие доходы (поступления) | C18: =SUM(C19,C23:C34) -> 0 | D18: =SUM(D19,D23:D34) -> 0 | E18: =SUM(E19,E23:E34) -> 0 | F18: =SUM(F19,F23:F34) -> 0 | G18: =SUM(G19,G23:G34) -> 0 | H18: =SUM(H19,H23:H34) -> 0 | I18: =SUM(I19,I23:I34) -> 0 | J18: =SUM(J19,J23:J34) -> 0 | ... R18: =SUM(R19,R23:R34) -> 0 | S18: =R18+N18+J18+F18 -> 0
A19: 10210 | B19: Проценты к получению | C19: =C20+C21+C22 -> 0 | D19: =D20+D21+D22 -> 0 | E19: =E20+E21+E22 -> 0 | F19: =F20+F21+F22 -> 0 | G19: =G20+G21+G22 -> 0 | H19: =H20+H21+H22 -> 0 | I19: =I20+I21+I22 -> 0 | J19: =J20+J21+J22 -> 0 | ... R19: =R20+R21+R22 -> 0 | S19: =R19+N19+J19+F19 -> 0
A20: 102101 | B20: проценты к получению по облигациям, депозитам, государственным ценным бумагам | F20: =C20+D20+E20 -> 0 | J20: =G20+H20+I20 -> 0 | N20: =K20+L20+M20 -> 0 | R20: =O20+P20+Q20 -> 0 | S20: =R20+N20+J20+F20 -> 0
A21: 102102 | B21: проценты к получению за предоставление в пользование денежных средств | F21: =C21+D21+E21 -> 0 | J21: =G21+H21+I21 -> 0 | N21: =K21+L21+M21 -> 0 | R21: =O21+P21+Q21 -> 0 | S21: =R21+N21+J21+F21 -> 0
A22: 102103 | B22: проценты к получению за использование кредитной организацией денежными средствами, находящимися на счетах организации в этой кредитной организации | F22: =C22+D22+E22 -> 0 | J22: =G22+H22+I22 -> 0 | N22: =K22+L22+M22 -> 0 | R22: =O22+P22+Q22 -> 0 | S22: =R22+N22+J22+F22 -> 0
